Workbook
Name FilterDateFrom: '01_Home'!$B$32
Name FilterDateTo: '01_Home'!$D$32
Name FilterCollection: '01_Home'!$F$32
Name FilterSKU: '01_Home'!$H$32
Name FilterSupplier: '01_Home'!$J$32
Name FilterLocation: '01_Home'!$L$32
Name FilterCampaign: '01_Home'!$N$32
Name OverallDataQualityPct: '14_Data_Quality'!$C$40
Name SetCompanyName: '15_Settings'!$C$13
Name SetBaseCurrency: '15_Settings'!$C$14
Name SetReportingCurrency: '15_Settings'!$C$15
Name SetFiscalYearStartMonth: '15_Settings'!$C$16
Name SetDefaultVATRate: '15_Settings'!$C$17
Name SetTargetGrossMargin: '15_Settings'!$C$18
Name SetShopifyStoreDomain: '15_Settings'!$C$23
Name SetShopifyAPIVersion: '15_Settings'!$C$24
Name SetLookbackDaysIncrementalRefresh: '15_Settings'!$C$25
Name SetHistoricalBackfillStartDate: '15_Settings'!$C$26
Name SetMaxPagesPerRefreshSafetyCap: '15_Settings'!$C$27
Name BusinessHealthScore: 'BI_HealthScore'!$C$26
Name BusinessHealthStatus: 'BI_HealthScore'!$C$27
Name LookupExpenseCategory: =tbl_LookupExpenseCategory[Expense Category]
Name LookupExpenseSubcategory: =tbl_LookupExpenseSubcategory[Expense Subcategory]
Name LookupCostCenter: =tbl_LookupCostCenter[Cost Center]
Name LookupPaymentMethod: =tbl_LookupPaymentMethod[Payment Method]
Name LookupCurrency: =tbl_LookupCurrency[Currency]
Name LookupSupplierType: =tbl_LookupSupplierType[Supplier Type]
Name LookupSupplierStatus: =tbl_LookupSupplierStatus[Supplier Status]
Name LookupCapitalTransactionType: =tbl_LookupCapitalTransactionType[Capital Transaction Type]
Name LookupPOStatus: =tbl_LookupPOStatus[PO Status]
Name LookupWarehouse: =tbl_LookupWarehouse[Warehouse]
Name LookupOwner: =tbl_LookupOwner[Owner]
Name LookupBudgetPeriod: =tbl_LookupBudgetPeriod[Budget Period]
Name LookupBudgetCategory: =tbl_LookupBudgetCategory[Budget Category]
Name LookupAlertSeverity: =tbl_LookupAlertSeverity[Alert Severity]
Name SupplierNameList: =tbl_SupplierMaster[Supplier Name]
Name POHeaderList: =tbl_POHeader[PO Number]
Name SKUList: =tbl_RAW_Variants[SKU]
Name CollectionTitleList: =tbl_RAW_Collections[Title]

Sheet 01_Home
A1: PASSRESS MIS — Home
A2: PASSRESS MIS | Home
A3: Sheet Documentation (use the + outline control at left to expand)
A4: Purpose | B4: Landing page and navigation hub for the entire workbook.
A5: Input tables | B5: None — display only.
A6: Output tables | B6: None.
A7: Relationships | B7: Links to all 14 other visible sheets. Reads workbook status from LOG_RefreshHistory and LOG_DataQuality.
A8: Future data source | B8: LOG_RefreshHistory (last refresh timestamp), LOG_DataQuality (overall status) — wired in Phase 2/4.
B11: LAST REFRESH | D11: DATA QUALITY | F11: WORKBOOK VERSION | H11: PHASE COMPLETED
B12: =IFERROR(TEXT(MAX(tbl_LOG_RefreshHistory[Timestamp]),"dd-mmm hh:mm"),"—") | D12: =IFERROR(TEXT(OverallDataQualityPct,"0.0%"),"—") | F12: =INDEX(tbl_VersionLog[Version],COUNTA(tbl_VersionLog[Version])) | H12: =INDEX(tbl_VersionLog[Phase],COUNTA(tbl_VersionLog[Phase]))
B15: NAVIGATION
B16: 02 Partner Dashboard | D16: 03 CEO Dashboard | F16: 04 Sales | H16: 05 Products
B19: 06 Customers | D19: 07 Inventory | F19: 08 Finance | H19: 09 Profitability
B22: 10 Expenses | D22: 11 Capital | F22: 12 Suppliers | H22: 13 Marketing
B25: 14 Data Quality | D25: 15 Settings
B30: GLOBAL FILTERS (orange cells = type or choose 'All')
B31: Date From | D31: Date To | F31: Collection | H31: SKU | J31: Supplier | L31: Location | N31: Campaign
B32: 2026-01-01 | D32: 2026-12-31 | F32: All | H32: All | J32: All | L32: All | N32: All (reserved — see Marketing-Ready Layer, not connected yet)
B34: REPORTS & TOOLS (hidden sheets — click to open, or right-click any tab → Unhide)
B35: → Daily Executive Brief
B36: → Workflow Dashboard
B38: Phase 6 build. See 15_Settings' Version Log for the full phase history and roadmap. Data shown on dashboards resolves once the Data Model is wired — see power-query/README.md and dax/README.md.

Sheet 02_Partner_Dashboard
A1: Partner Dashboard
A2: PASSRESS MIS | Home ▸ Partner Dashboard
A3: Sheet Documentation (use the + outline control at left to expand)
A4: Purpose | B4: Executive view for business partners — the headline numbers only, no operational drill-down. Simple, beautiful, minimal by design.
A5: Input tables | B5: The Data Model (dax/MEASURES.md, dax/PHASE5_MEASURES_ADDENDUM.md) via CUBEVALUE/CUBESET — no PivotTable required.
A6: Output tables | B6: 5 KPI cards, one 12-month trend chart, a live Top 5 Products list, Key Insights (from BI_Insights).
A7: Relationships | B7: Reads the Data Model directly; BI_Insights supplies the insight text shown here.
A8: Future data source | B8: Already live: every number resolves once the Data Model + measures are wired — see power-query/README.md and dax/README.md. Until then, cards show 0 and the chart is flat — expected, not an error.
B11: REVENUE | D11: NET PROFIT | F11: MARGIN % | H11: CASH POSITION | J11: ORDERS
B12: =CUBEVALUE("ThisWorkbookDataModel","[Measures].[Net Sales]") | D12: =CUBEVALUE("ThisWorkbookDataModel","[Measures].[Net Profit]") | F12: =CUBEVALUE("ThisWorkbookDataModel","[Measures].[Gross Margin %]") | H12: =CUBEVALUE("ThisWorkbookDataModel","[Measures].[Cash Position (Direct, Cumulative)]") | J12: =CUBEVALUE("ThisWorkbookDataModel","[Measures].[Order Count]")
B15: ↓ Drill into Sales
B17: MONTHLY TREND — NET SALES
B18: Net Sales — trailing 12 months
C19: =TEXT(EDATE(TODAY(),-11),"mmm-yy") | D19: =TEXT(EDATE(TODAY(),-10),"mmm-yy") | E19: =TEXT(EDATE(TODAY(),-9),"mmm-yy") | F19: =TEXT(EDATE(TODAY(),-8),"mmm-yy") | G19: =TEXT(EDATE(TODAY(),-7),"mmm-yy") | H19: =TEXT(EDATE(TODAY(),-6),"mmm-yy") | I19: =TEXT(EDATE(TODAY(),-5),"mmm-yy") | J19: =TEXT(EDATE(TODAY(),-4),"mmm-yy") | K19: =TEXT(EDATE(TODAY(),-3),"mmm-yy") | L19: =TEXT(EDATE(TODAY(),-2),"mmm-yy") | M19: =TEXT(EDATE(TODAY(),-1),"mmm-yy") | N19: =TEXT(EDATE(TODAY(),0),"mmm-yy")
C20: =CUBEVALUE("ThisWorkbookDataModel","[Measures].[Net Sales]","[DIM_Date].[Year].&["&YEAR(EDATE(TODAY(),-11))&"]","[DIM_Date].[Month].&["&MONTH(EDATE(TODAY(),-11))&"]") | D20: =CUBEVALUE("ThisWorkbookDataModel","[Measures].[Net Sales]","[DIM_Date].[Year].&["&YEAR(EDATE(TODAY(),-10))&"]","[DIM_Date].[Month].&["&MONTH(EDATE(TODAY(),-10))&"]") | E20: =CUBEVALUE("ThisWorkbookDataModel","[Measures].[Net Sales]","[DIM_Date].[Year].&["&YEAR(EDATE(TODAY(),-9))&"]","[DIM_Date].[Month].&["&MONTH(EDATE(TODAY(),-9))&"]") | F20: =CUBEVALUE("ThisWorkbookDataModel","[Measures].[Net Sales]","[DIM_Date].[Year].&["&YEAR(EDATE(TODAY(),-8))&"]","[DIM_Date].[Month].&["&MONTH(EDATE(TODAY(),-8))&"]") | G20: =CUBEVALUE("ThisWorkbookDataModel","[Measures].[Net Sales]","[DIM_Date].[Year].&["&YEAR(EDATE(TODAY(),-7))&"]","[DIM_Date].[Month].&["&MONTH(EDATE(TODAY(),-7))&"]") | H20: =CUBEVALUE("ThisWorkbookDataModel","[Measures].[Net Sales]","[DIM_Date].[Year].&["&YEAR(EDATE(TODAY(),-6))&"]","[DIM_Date].[Month].&["&MONTH(EDATE(TODAY(),-6))&"]") | I20: =CUBEVALUE("ThisWorkbookDataModel","[Measures].[Net Sales]","[DIM_Date].[Year].&["&YEAR(EDATE(TODAY(),-5))&"]","[DIM_Date].[Month].&["&MONTH(EDATE(TODAY(),-5))&"]") | J20: =CUBEVALUE("ThisWorkbookDataModel","[Measures].[Net Sales]","[DIM_Date].[Year].&["&YEAR(EDATE(TODAY(),-4))&"]","[DIM_Date].[Month].&["&MONTH(EDATE(TODAY(),-4))&"]") | K20: =CUBEVALUE("ThisWorkbookDataModel","[Measures].[Net Sales]","[DIM_Date].[Year].&["&YEAR(EDATE(TODAY(),-3))&"]","[DIM_Date].[Month].&["&MONTH(EDATE(TODAY(),-3))&"]") | L20: =CUBEVALUE("ThisWorkbookDataModel","[Measures].[Net Sales]","[DIM_Date].[Year].&["&YEAR(EDATE(TODAY(),-2))&"]","[DIM_Date].[Month].&["&MONTH(EDATE(TODAY(),-2))&"]") | M20: =CUBEVALUE("ThisWorkbookDataModel","[Measures].[Net Sales]","[DIM_Date].[Year].&["&YEAR(EDATE(TODAY(),-1))&"]","[DIM_Date].[Month].&["&MONTH(EDATE(TODAY(),-1))&"]") | N20: =CUBEVALUE("ThisWorkbookDataModel","[Measures].[Net Sales]","[DIM_Date].[Year].&["&YEAR(EDATE(TODAY(),0))&"]","[DIM_Date].[Month].&["&MONTH(EDATE(TODAY(),0))&"]")
B38: TOP 5 PRODUCTS (by Net Sales)
B39: Top 5 Products | F39: =CUBESET("ThisWorkbookDataModel","{[DIM_Product].[Title].Children}","Top 5 Products","BDESC","[Measures].[Net Sales]")
B40: =CUBERANKEDMEMBER("ThisWorkbookDataModel",$F$39,1) | D40: =CUBEVALUE("ThisWorkbookDataModel","[Measures].[Net Sales]",CUBERANKEDMEMBER("ThisWorkbookDataModel",$F$39,1))
B41: =CUBERANKEDMEMBER("ThisWorkbookDataModel",$F$39,2) | D41: =CUBEVALUE("ThisWorkbookDataModel","[Measures].[Net Sales]",CUBERANKEDMEMBER("ThisWorkbookDataModel",$F$39,2))
B42: =CUBERANKEDMEMBER("ThisWorkbookDataModel",$F$39,3) | D42: =CUBEVALUE("ThisWorkbookDataModel","[Measures].[Net Sales]",CUBERANKEDMEMBER("ThisWorkbookDataModel",$F$39,3))
B43: =CUBERANKEDMEMBER("ThisWorkbookDataModel",$F$39,4) | D43: =CUBEVALUE("ThisWorkbookDataModel","[Measures].[Net Sales]",CUBERANKEDMEMBER("ThisWorkbookDataModel",$F$39,4))
B44: =CUBERANKEDMEMBER("ThisWorkbookDataModel",$F$39,5) | D44: =CUBEVALUE("ThisWorkbookDataModel","[Measures].[Net Sales]",CUBERANKEDMEMBER("ThisWorkbookDataModel",$F$39,5))
B46: KEY INSIGHTS
B47: ="• "&IFERROR('BI_Insights'!D15,"(resolves once Data Model is wired)")
B48: ="• "&IFERROR('BI_Insights'!D16,"(resolves once Data Model is wired)")
B49: ="• "&IFERROR('BI_Insights'!D19,"(resolves once Data Model is wired)")
B50: ="• "&IFERROR('BI_Insights'!D20,"(resolves once Data Model is wired)")

Sheet 03_CEO_Dashboard
A1: CEO Dashboard
A2: PASSRESS MIS | Home ▸ CEO Dashboard
A3: Sheet Documentation (use the + outline control at left to expand)
A4: Purpose | B4: Management view: every KPI category, Budget/Forecast/Alerts summaries, and Business Insights — the full operational picture, unlike Partner Dashboard's deliberately minimal set.
A5: Input tables | B5: The Data Model (dax/MEASURES.md, dax/PHASE5_MEASURES_ADDENDUM.md) via CUBEVALUE; BI_Alerts, BI_Forecast, BI_Insights for their respective sections.
A6: Output tables | B6: 9 KPI-card sections + Budget/Forecast/Alerts/Insights reference tables.
A7: Relationships | B7: Reads the Data Model directly for KPI cards; reads BI_Alerts/BI_Forecast/BI_Insights directly (simple cell references, not re-derived CUBE formulas) for those three sections.
A8: Future data source | B8: Already live: every number resolves once the Data Model + measures are wired — see power-query/README.md and dax/README.md.
B11: FINANCIAL KPIs
B12: NET SALES | D12: GROSS PROFIT | F12: NET PROFIT | H12: CASH POSITION
B13: =CUBEVALUE("ThisWorkbookDataModel","[Measures].[Net Sales]") | D13: =CUBEVALUE("ThisWorkbookDataModel","[Measures].[Gross Profit]") | F13: =CUBEVALUE("ThisWorkbookDataModel","[Measures].[Net Profit]") | H13: =CUBEVALUE("ThisWorkbookDataModel","[Measures].[Cash Position (Direct, Cumulative)]")
B17: SALES KPIs
B18: ORDER COUNT | D18: AVERAGE ORDER VALUE | F18: UNITS SOLD | H18: REVENUE GROWTH % YOY
B19: =CUBEVALUE("ThisWorkbookDataModel","[Measures].[Order Count]") | D19: =CUBEVALUE("ThisWorkbookDataModel","[Measures].[Average Order Value]") | F19: =CUBEVALUE("ThisWorkbookDataModel","[Measures].[Units Sold]") | H19: =CUBEVALUE("ThisWorkbookDataModel","[Measures].[Revenue Growth % (YoY)]")
B22: ↓ Drill into Sales
B24: CUSTOMER KPIs
B25: NEW CUSTOMERS | D25: RETURNING CUSTOMERS | F25: CLV (HISTORICAL) | H25: RETENTION RATE (MOM)
B26: =CUBEVALUE("ThisWorkbookDataModel","[Measures].[New Customers]") | D26: =CUBEVALUE("ThisWorkbookDataModel","[Measures].[Returning Customers]") | F26: =CUBEVALUE("ThisWorkbookDataModel","[Measures].[Customer Lifetime Value (Historical)]") | H26: =CUBEVALUE("ThisWorkbookDataModel","[Measures].[Customer Retention Rate (MoM)]")
B29: ↓ Drill into Customers
B31: INVENTORY KPIs
B32: INVENTORY VALUE | D32: INVENTORY TURNOVER | F32: DAYS OF INVENTORY | H32: SLOW MOVING SKUS
B33: =CUBEVALUE("ThisWorkbookDataModel","[Measures].[Inventory Value]") | D33: =CUBEVALUE("ThisWorkbookDataModel","[Measures].[Inventory Turnover]") | F33: =CUBEVALUE("ThisWorkbookDataModel","[Measures].[Days of Inventory]") | H33: =CUBEVALUE("ThisWorkbookDataModel","[Measures].[Slow Moving SKU Count]")
B36: ↓ Drill into Inventory
B38: PROFITABILITY
B39: GROSS MARGIN % | D39: NET PROFIT MARGIN % | F39: BREAK-EVEN NET SALES
B40: =CUBEVALUE("ThisWorkbookDataModel","[Measures].[Gross Margin %]") | D40: =CUBEVALUE("ThisWorkbookDataModel","[Measures].[Net Profit Margin %]") | F40: =CUBEVALUE("ThisWorkbookDataModel","[Measures].[Break-Even Net Sales]")
B43: ↓ Drill into Profitability
B45: EXPENSE ANALYSIS
B46: OPERATING EXPENSES | D46: EXPENSE RATIO % | F46: EXPENSE ACTUAL VS BUDGET
B47: =CUBEVALUE("ThisWorkbookDataModel","[Measures].[Operating Expenses]") | D47: =CUBEVALUE("ThisWorkbookDataModel","[Measures].[Operating Expense Ratio %]") | F47: =CUBEVALUE("ThisWorkbookDataModel","[Measures].[Expense Actual vs Budget]")
B50: ↓ Drill into Expenses
B52: BUDGET (Actual vs Budget, current period)
B53: Category | C53: Actual | D53: Budget | E53: Variance
B54: Revenue | C54: =CUBEVALUE("ThisWorkbookDataModel","[Measures].[Net Sales]") | D54: =CUBEVALUE("ThisWorkbookDataModel","[Measures].[Revenue Budget (Period)]") | E54: =CUBEVALUE("ThisWorkbookDataModel","[Measures].[Revenue Actual vs Budget]")
B55: Expense | C55: =CUBEVALUE("ThisWorkbookDataModel","[Measures].[Operating Expenses]") | D55: =CUBEVALUE("ThisWorkbookDataModel","[Measures].[Expense Budget (Period)]") | E55: =CUBEVALUE("ThisWorkbookDataModel","[Measures].[Expense Actual vs Budget]")
B56: Purchasing | C56: =CUBEVALUE("ThisWorkbookDataModel","[Measures].[Cash Paid for Purchases]") | D56: =CUBEVALUE("ThisWorkbookDataModel","[Measures].[Purchasing Budget (Period)]") | E56: =CUBEVALUE("ThisWorkbookDataModel","[Measures].[Purchasing Actual vs Budget]")
B57: Profit | C57: =CUBEVALUE("ThisWorkbookDataModel","[Measures].[Net Profit]") | D57: =CUBEVALUE("ThisWorkbookDataModel","[Measures].[Profit Budget (Period)]") | E57: =CUBEVALUE("ThisWorkbookDataModel","[Measures].[Profit Actual vs Budget]")
B59: FORECAST (next period, rolling linear trend — see BI_Forecast)
B60: Metric | C60: Forecast (Next Month)
B61: Sales | C61: ='BI_Forecast'!E37
B62: Expenses | C62: ='BI_Forecast'!E38
B63: Profit | C63: ='BI_Forecast'!E39
B64: Inventory | C64: ='BI_Forecast'!E40
B65: Cash | C65: ='BI_Forecast'!E41
B67: ALERTS (see 14_Data_Quality and BI_Alerts for full detail)
B68: Alert | C68: Status | D68: Severity
B69: ='BI_Alerts'!B15 | C69: ='BI_Alerts'!E15 | D69: ='BI_Alerts'!F15
B70: ='BI_Alerts'!B16 | C70: ='BI_Alerts'!E16 | D70: ='BI_Alerts'!F16
B71: ='BI_Alerts'!B17 | C71: ='BI_Alerts'!E17 | D71: ='BI_Alerts'!F17
B72: ='BI_Alerts'!B18 | C72: ='BI_Alerts'!E18 | D72: ='BI_Alerts'!F18
B73: ='BI_Alerts'!B19 | C73: ='BI_Alerts'!E19 | D73: ='BI_Alerts'!F19
B74: ='BI_Alerts'!B20 | C74: ='BI_Alerts'!E20 | D74: ='BI_Alerts'!F20
B75: ='BI_Alerts'!B21 | C75: ='BI_Alerts'!E21 | D75: ='BI_Alerts'!F21
B76: ='BI_Alerts'!B22 | C76: ='BI_Alerts'!E22 | D76: ='BI_Alerts'!F22
B77: ='BI_Alerts'!B23 | C77: ='BI_Alerts'!E23 | D77: ='BI_Alerts'!F23
B78: ='BI_Alerts'!B24 | C78: ='BI_Alerts'!E24 | D78: ='BI_Alerts'!F24
B79: ='BI_Alerts'!B25 | C79: ='BI_Alerts'!E25 | D79: ='BI_Alerts'!F25
B80: ='BI_Alerts'!B26 | C80: ='BI_Alerts'!E26 | D80: ='BI_Alerts'!F26
B82: BUSINESS INSIGHTS
B83: ="• "&IFERROR('BI_Insights'!D15,"(resolves once Data Model is wired)")
B84: ="• "&IFERROR('BI_Insights'!D16,"(resolves once Data Model is wired)")
B85: ="• "&IFERROR('BI_Insights'!D17,"(resolves once Data Model is wired)")
B86: ="• "&IFERROR('BI_Insights'!D18,"(resolves once Data Model is wired)")
B87: ="• "&IFERROR('BI_Insights'!D19,"(resolves once Data Model is wired)")
B88: ="• "&IFERROR('BI_Insights'!D20,"(resolves once Data Model is wired)")
B89: ="• "&IFERROR('BI_Insights'!D21,"(resolves once Data Model is wired)")
B90: ="• "&IFERROR('BI_Insights'!D22,"(resolves once Data Model is wired)")

Sheet 04_Sales
A1: Sales
A2: PASSRESS MIS | Home ▸ Sales
A3: Sheet Documentation (use the + outline control at left to expand)
A4: Purpose | B4: Sales performance detail — orders, revenue, discounts, and returns by period, product, and channel.
A5: Input tables | B5: FACT_OrderLines, FACT_Refunds, DIM_Date, DIM_Product, DIM_Collection.
A6: Output tables | B6: Sales KPI row, Sales Trend chart (doubles as Sales by Date), Sales by Product / Sales by Collection breakdown tables (CUBE-function substitutes for a PivotTable — see dax/README.md), a link to the full Order List.
A7: Relationships | B7: FACT_OrderLines links to DIM_Date/DIM_Product/DIM_Collection; FACT_Refunds links to FACT_OrderLines.
A8: Future data source | B8: Live now: every card/table below reads dax/MEASURES.md's Gross Sales/Discounts/Returns/Net Sales measures (§0/§1) directly.
B11: GROSS SALES | D11: DISCOUNTS | F11: RETURNS | H11: NET SALES
B12: =CUBEVALUE("ThisWorkbookDataModel","[Measures].[Gross Sales]") | D12: =CUBEVALUE("ThisWorkbookDataModel","[Measures].[Discounts]") | F12: =CUBEVALUE("ThisWorkbookDataModel","[Measures].[Returns]") | H12: =CUBEVALUE("ThisWorkbookDataModel","[Measures].[Net Sales]")
B16: SALES TREND / SALES BY DATE (same Net Sales-by-month data — chart and table, not recomputed twice)
B17: Net Sales — trailing 12 months
C18: =TEXT(EDATE(TODAY(),-11),"mmm-yy") | D18: =TEXT(EDATE(TODAY(),-10),"mmm-yy") | E18: =TEXT(EDATE(TODAY(),-9),"mmm-yy") | F18: =TEXT(EDATE(TODAY(),-8),"mmm-yy") | G18: =TEXT(EDATE(TODAY(),-7),"mmm-yy") | H18: =TEXT(EDATE(TODAY(),-6),"mmm-yy") | I18: =TEXT(EDATE(TODAY(),-5),"mmm-yy") | J18: =TEXT(EDATE(TODAY(),-4),"mmm-yy") | K18: =TEXT(EDATE(TODAY(),-3),"mmm-yy") | L18: =TEXT(EDATE(TODAY(),-2),"mmm-yy") | M18: =TEXT(EDATE(TODAY(),-1),"mmm-yy") | N18: =TEXT(EDATE(TODAY(),0),"mmm-yy")
C19: =CUBEVALUE("ThisWorkbookDataModel","[Measures].[Net Sales]","[DIM_Date].[Year].&["&YEAR(EDATE(TODAY(),-11))&"]","[DIM_Date].[Month].&["&MONTH(EDATE(TODAY(),-11))&"]") | D19: =CUBEVALUE("ThisWorkbookDataModel","[Measures].[Net Sales]","[DIM_Date].[Year].&["&YEAR(EDATE(TODAY(),-10))&"]","[DIM_Date].[Month].&["&MONTH(EDATE(TODAY(),-10))&"]") | E19: =CUBEVALUE("ThisWorkbookDataModel","[Measures].[Net Sales]","[DIM_Date].[Year].&["&YEAR(EDATE(TODAY(),-9))&"]","[DIM_Date].[Month].&["&MONTH(EDATE(TODAY(),-9))&"]") | F19: =CUBEVALUE("ThisWorkbookDataModel","[Measures].[Net Sales]","[DIM_Date].[Year].&["&YEAR(EDATE(TODAY(),-8))&"]","[DIM_Date].[Month].&["&MONTH(EDATE(TODAY(),-8))&"]") | G19: =CUBEVALUE("ThisWorkbookDataModel","[Measures].[Net Sales]","[DIM_Date].[Year].&["&YEAR(EDATE(TODAY(),-7))&"]","[DIM_Date].[Month].&["&MONTH(EDATE(TODAY(),-7))&"]") | H19: =CUBEVALUE("ThisWorkbookDataModel","[Measures].[Net Sales]","[DIM_Date].[Year].&["&YEAR(EDATE(TODAY(),-6))&"]","[DIM_Date].[Month].&["&MONTH(EDATE(TODAY(),-6))&"]") | I19: =CUBEVALUE("ThisWorkbookDataModel","[Measures].[Net Sales]","[DIM_Date].[Year].&["&YEAR(EDATE(TODAY(),-5))&"]","[DIM_Date].[Month].&["&MONTH(EDATE(TODAY(),-5))&"]") | J19: =CUBEVALUE("ThisWorkbookDataModel","[Measures].[Net Sales]","[DIM_Date].[Year].&["&YEAR(EDATE(TODAY(),-4))&"]","[DIM_Date].[Month].&["&MONTH(EDATE(TODAY(),-4))&"]") | K19: =CUBEVALUE("ThisWorkbookDataModel","[Measures].[Net Sales]","[DIM_Date].[Year].&["&YEAR(EDATE(TODAY(),-3))&"]","[DIM_Date].[Month].&["&MONTH(EDATE(TODAY(),-3))&"]") | L19: =CUBEVALUE("ThisWorkbookDataModel","[Measures].[Net Sales]","[DIM_Date].[Year].&["&YEAR(EDATE(TODAY(),-2))&"]","[DIM_Date].[Month].&["&MONTH(EDATE(TODAY(),-2))&"]") | M19: =CUBEVALUE("ThisWorkbookDataModel","[Measures].[Net Sales]","[DIM_Date].[Year].&["&YEAR(EDATE(TODAY(),-1))&"]","[DIM_Date].[Month].&["&MONTH(EDATE(TODAY(),-1))&"]") | N19: =CUBEVALUE("ThisWorkbookDataModel","[Measures].[Net Sales]","[DIM_Date].[Year].&["&YEAR(EDATE(TODAY(),0))&"]","[DIM_Date].[Month].&["&MONTH(EDATE(TODAY(),0))&"]")
B37: SALES BY PRODUCT
B38: Sales by Product (Top 8 by Net Sales) | F38: =CUBESET("ThisWorkbookDataModel","{[DIM_Product].[Title].Children}","Sales by Product (Top 8 by Net Sales)","BDESC","[Measures].[Net Sales]")
B39: Title | C39: Net Sales
B40: =CUBERANKEDMEMBER("ThisWorkbookDataModel",$F$38,1) | C40: =CUBEVALUE("ThisWorkbookDataModel","[Measures].[Net Sales]",CUBERANKEDMEMBER("ThisWorkbookDataModel",$F$38,1))
B41: =CUBERANKEDMEMBER("ThisWorkbookDataModel",$F$38,2) | C41: =CUBEVALUE("ThisWorkbookDataModel","[Measures].[Net Sales]",CUBERANKEDMEMBER("ThisWorkbookDataModel",$F$38,2))
B42: =CUBERANKEDMEMBER("ThisWorkbookDataModel",$F$38,3) | C42: =CUBEVALUE("ThisWorkbookDataModel","[Measures].[Net Sales]",CUBERANKEDMEMBER("ThisWorkbookDataModel",$F$38,3))
B43: =CUBERANKEDMEMBER("ThisWorkbookDataModel",$F$38,4) | C43: =CUBEVALUE("ThisWorkbookDataModel","[Measures].[Net Sales]",CUBERANKEDMEMBER("ThisWorkbookDataModel",$F$38,4))
B44: =CUBERANKEDMEMBER("ThisWorkbookDataModel",$F$38,5) | C44: =CUBEVALUE("ThisWorkbookDataModel","[Measures].[Net Sales]",CUBERANKEDMEMBER("ThisWorkbookDataModel",$F$38,5))
B45: =CUBERANKEDMEMBER("ThisWorkbookDataModel",$F$38,6) | C45: =CUBEVALUE("ThisWorkbookDataModel","[Measures].[Net Sales]",CUBERANKEDMEMBER("ThisWorkbookDataModel",$F$38,6))
B46: =CUBERANKEDMEMBER("ThisWorkbookDataModel",$F$38,7) | C46: =CUBEVALUE("ThisWorkbookDataModel","[Measures].[Net Sales]",CUBERANKEDMEMBER("ThisWorkbookDataModel",$F$38,7))
B47: =CUBERANKEDMEMBER("ThisWorkbookDataModel",$F$38,8) | C47: =CUBEVALUE("ThisWorkbookDataModel","[Measures].[Net Sales]",CUBERANKEDMEMBER("ThisWorkbookDataModel",$F$38,8))
B50: SALES BY COLLECTION
B51: Sales by Collection (Top 8 by Net Sales) | F51: =CUBESET("ThisWorkbookDataModel","{[DIM_Collection].[Title].Children}","Sales by Collection (Top 8 by Net Sales)","BDESC","[Measures].[Net Sales]")
B52: Title | C52: Net Sales
B53: =CUBERANKEDMEMBER("ThisWorkbookDataModel",$F$51,1) | C53: =CUBEVALUE("ThisWorkbookDataModel","[Measures].[Net Sales]",CUBERANKEDMEMBER("ThisWorkbookDataModel",$F$51,1))
B54: =CUBERANKEDMEMBER("ThisWorkbookDataModel",$F$51,2) | C54: =CUBEVALUE("ThisWorkbookDataModel","[Measures].[Net Sales]",CUBERANKEDMEMBER("ThisWorkbookDataModel",$F$51,2))
B55: =CUBERANKEDMEMBER("ThisWorkbookDataModel",$F$51,3) | C55: =CUBEVALUE("ThisWorkbookDataModel","[Measures].[Net Sales]",CUBERANKEDMEMBER("ThisWorkbookDataModel",$F$51,3))
B56: =CUBERANKEDMEMBER("ThisWorkbookDataModel",$F$51,4) | C56: =CUBEVALUE("ThisWorkbookDataModel","[Measures].[Net Sales]",CUBERANKEDMEMBER("ThisWorkbookDataModel",$F$51,4))
B57: =CUBERANKEDMEMBER("ThisWorkbookDataModel",$F$51,5) | C57: =CUBEVALUE("ThisWorkbookDataModel","[Measures].[Net Sales]",CUBERANKEDMEMBER("ThisWorkbookDataModel",$F$51,5))
B58: =CUBERANKEDMEMBER("ThisWorkbookDataModel",$F$51,6) | C58: =CUBEVALUE("ThisWorkbookDataModel","[Measures].[Net Sales]",CUBERANKEDMEMBER("ThisWorkbookDataModel",$F$51,6))
B59: =CUBERANKEDMEMBER("ThisWorkbookDataModel",$F$51,7) | C59: =CUBEVALUE("ThisWorkbookDataModel","[Measures].[Net Sales]",CUBERANKEDMEMBER("ThisWorkbookDataModel",$F$51,7))
B60: =CUBERANKEDMEMBER("ThisWorkbookDataModel",$F$51,8) | C60: =CUBEVALUE("ThisWorkbookDataModel","[Measures].[Net Sales]",CUBERANKEDMEMBER("ThisWorkbookDataModel",$F$51,8))
B63: ORDER LIST
B64: [ Order List (Table) — Not implementable: No Order-level dimension exists in the Data Model — CUBE functions browse dimension members (Product/Collection/Customer/Location/Date), not individual fact rows, so a row-level order list can't be built this way without adding a new Data Model object, which is out of scope (architecture frozen). The full, live order list is RAW_Orders itself, already wired once Power Query is set up. ]
B68: ↓ Drill into Orders

Sheet 05_Products
A1: Products
A2: PASSRESS MIS | Home ▸ Products
A3: Sheet Documentation (use the + outline control at left to expand)
A4: Purpose | B4: Product-level performance dashboard PLUS, as of Phase 3, the Product Cost Master — the workbook's historical/versioned SKU costing table.
A5: Input tables | B5: DIM_Product, FACT_OrderLines (dashboard). RAW_Variants, RAW_Collections (Product Cost Master dropdowns).
A6: Output tables | B6: Product KPI row, Top 10 Products chart, Product Margin breakdown table (CUBE-function substitute for a PivotTable). tbl_ProductCostMaster feeding DIM_ProductCostHistory.
A7: Relationships | B7: DIM_Product links to FACT_OrderLines on ProductKey. tbl_ProductCostMaster[SKU] links to RAW_Variants[SKU]; COGS is matched via fn_GetEffectiveCost (SKU + order date against Effective From/To Date).
A8: Future data source | B8: Live now: dashboard reads dax/MEASURES.md measures directly. Product Cost Master is manual entry — see PHASE3_DOCUMENTATION.md §1.
B11: ACTIVE SKUS | D11: BEST SELLER | F11: AVG MARGIN % | H11: SLOW MOVERS | N11: =CUBESET("ThisWorkbookDataModel","{[DIM_Product].[Title].Children}","BestSellerProduct","BDESC","[Measures].[Net Sales]")
B12: N/A | D12: =CUBERANKEDMEMBER("ThisWorkbookDataModel",$N$11,1) | F12: =CUBEVALUE("ThisWorkbookDataModel","[Measures].[Gross Margin %]") | H12: =CUBEVALUE("ThisWorkbookDataModel","[Measures].[Slow Moving SKU Count]")
B16: TOP 10 PRODUCTS (by Net Sales)
N17: =CUBESET("ThisWorkbookDataModel","{[DIM_Product].[Title].Children}","Top10Products","BDESC","[Measures].[Net Sales]")
B18: =CUBERANKEDMEMBER("ThisWorkbookDataModel",$N$17,1) | D18: =CUBEVALUE("ThisWorkbookDataModel","[Measures].[Net Sales]",CUBERANKEDMEMBER("ThisWorkbookDataModel",$N$17,1))
B19: =CUBERANKEDMEMBER("ThisWorkbookDataModel",$N$17,2) | D19: =CUBEVALUE("ThisWorkbookDataModel","[Measures].[Net Sales]",CUBERANKEDMEMBER("ThisWorkbookDataModel",$N$17,2))
B20: =CUBERANKEDMEMBER("ThisWorkbookDataModel",$N$17,3) | D20: =CUBEVALUE("ThisWorkbookDataModel","[Measures].[Net Sales]",CUBERANKEDMEMBER("ThisWorkbookDataModel",$N$17,3))
B21: =CUBERANKEDMEMBER("ThisWorkbookDataModel",$N$17,4) | D21: =CUBEVALUE("ThisWorkbookDataModel","[Measures].[Net Sales]",CUBERANKEDMEMBER("ThisWorkbookDataModel",$N$17,4))
B22: =CUBERANKEDMEMBER("ThisWorkbookDataModel",$N$17,5) | D22: =CUBEVALUE("ThisWorkbookDataModel","[Measures].[Net Sales]",CUBERANKEDMEMBER("ThisWorkbookDataModel",$N$17,5))
B23: =CUBERANKEDMEMBER("ThisWorkbookDataModel",$N$17,6) | D23: =CUBEVALUE("ThisWorkbookDataModel","[Measures].[Net Sales]",CUBERANKEDMEMBER("ThisWorkbookDataModel",$N$17,6))
B24: =CUBERANKEDMEMBER("ThisWorkbookDataModel",$N$17,7) | D24: =CUBEVALUE("ThisWorkbookDataModel","[Measures].[Net Sales]",CUBERANKEDMEMBER("ThisWorkbookDataModel",$N$17,7))
B25: =CUBERANKEDMEMBER("ThisWorkbookDataModel",$N$17,8) | D25: =CUBEVALUE("ThisWorkbookDataModel","[Measures].[Net Sales]",CUBERANKEDMEMBER("ThisWorkbookDataModel",$N$17,8))
B26: =CUBERANKEDMEMBER("ThisWorkbookDataModel",$N$17,9) | D26: =CUBEVALUE("ThisWorkbookDataModel","[Measures].[Net Sales]",CUBERANKEDMEMBER("ThisWorkbookDataModel",$N$17,9))
B27: =CUBERANKEDMEMBER("ThisWorkbookDataModel",$N$17,10) | D27: =CUBEVALUE("ThisWorkbookDataModel","[Measures].[Net Sales]",CUBERANKEDMEMBER("ThisWorkbookDataModel",$N$17,10))
B29: PRODUCT MARGIN
B30: Product Margin (Top 8 by Gross Profit) | H30: =CUBESET("ThisWorkbookDataModel","{[DIM_Product].[Title].Children}","Product Margin (Top 8 by Gross Profit)","BDESC","[Measures].[Gross Profit]")
B31: Title | C31: Net Sales | D31: Gross Profit | E31: Gross Margin %
B32: =CUBERANKEDMEMBER("ThisWorkbookDataModel",$H$30,1) | C32: =CUBEVALUE("ThisWorkbookDataModel","[Measures].[Net Sales]",CUBERANKEDMEMBER("ThisWorkbookDataModel",$H$30,1)) | D32: =CUBEVALUE("ThisWorkbookDataModel","[Measures].[Gross Profit]",CUBERANKEDMEMBER("ThisWorkbookDataModel",$H$30,1)) | E32: =CUBEVALUE("ThisWorkbookDataModel","[Measures].[Gross Margin %]",CUBERANKEDMEMBER("ThisWorkbookDataModel",$H$30,1))
B33: =CUBERANKEDMEMBER("ThisWorkbookDataModel",$H$30,2) | C33: =CUBEVALUE("ThisWorkbookDataModel","[Measures].[Net Sales]",CUBERANKEDMEMBER("ThisWorkbookDataModel",$H$30,2)) | D33: =CUBEVALUE("ThisWorkbookDataModel","[Measures].[Gross Profit]",CUBERANKEDMEMBER("ThisWorkbookDataModel",$H$30,2)) | E33: =CUBEVALUE("ThisWorkbookDataModel","[Measures].[Gross Margin %]",CUBERANKEDMEMBER("ThisWorkbookDataModel",$H$30,2))
B34: =CUBERANKEDMEMBER("ThisWorkbookDataModel",$H$30,3) | C34: =CUBEVALUE("ThisWorkbookDataModel","[Measures].[Net Sales]",CUBERANKEDMEMBER("ThisWorkbookDataModel",$H$30,3)) | D34: =CUBEVALUE("ThisWorkbookDataModel","[Measures].[Gross Profit]",CUBERANKEDMEMBER("ThisWorkbookDataModel",$H$30,3)) | E34: =CUBEVALUE("ThisWorkbookDataModel","[Measures].[Gross Margin %]",CUBERANKEDMEMBER("ThisWorkbookDataModel",$H$30,3))
B35: =CUBERANKEDMEMBER("ThisWorkbookDataModel",$H$30,4) | C35: =CUBEVALUE("ThisWorkbookDataModel","[Measures].[Net Sales]",CUBERANKEDMEMBER("ThisWorkbookDataModel",$H$30,4)) | D35: =CUBEVALUE("ThisWorkbookDataModel","[Measures].[Gross Profit]",CUBERANKEDMEMBER("ThisWorkbookDataModel",$H$30,4)) | E35: =CUBEVALUE("ThisWorkbookDataModel","[Measures].[Gross Margin %]",CUBERANKEDMEMBER("ThisWorkbookDataModel",$H$30,4))
B36: =CUBERANKEDMEMBER("ThisWorkbookDataModel",$H$30,5) | C36: =CUBEVALUE("ThisWorkbookDataModel","[Measures].[Net Sales]",CUBERANKEDMEMBER("ThisWorkbookDataModel",$H$30,5)) | D36: =CUBEVALUE("ThisWorkbookDataModel","[Measures].[Gross Profit]",CUBERANKEDMEMBER("ThisWorkbookDataModel",$H$30,5)) | E36: =CUBEVALUE("ThisWorkbookDataModel","[Measures].[Gross Margin %]",CUBERANKEDMEMBER("ThisWorkbookDataModel",$H$30,5))
B37: =CUBERANKEDMEMBER("ThisWorkbookDataModel",$H$30,6) | C37: =CUBEVALUE("ThisWorkbookDataModel","[Measures].[Net Sales]",CUBERANKEDMEMBER("ThisWorkbookDataModel",$H$30,6)) | D37: =CUBEVALUE("ThisWorkbookDataModel","[Measures].[Gross Profit]",CUBERANKEDMEMBER("ThisWorkbookDataModel",$H$30,6)) | E37: =CUBEVALUE("ThisWorkbookDataModel","[Measures].[Gross Margin %]",CUBERANKEDMEMBER("ThisWorkbookDataModel",$H$30,6))
B38: =CUBERANKEDMEMBER("ThisWorkbookDataModel",$H$30,7) | C38: =CUBEVALUE("ThisWorkbookDataModel","[Measures].[Net Sales]",CUBERANKEDMEMBER("ThisWorkbookDataModel",$H$30,7)) | D38: =CUBEVALUE("ThisWorkbookDataModel","[Measures].[Gross Profit]",CUBERANKEDMEMBER("ThisWorkbookDataModel",$H$30,7)) | E38: =CUBEVALUE("ThisWorkbookDataModel","[Measures].[Gross Margin %]",CUBERANKEDMEMBER("ThisWorkbookDataModel",$H$30,7))
B39: =CUBERANKEDMEMBER("ThisWorkbookDataModel",$H$30,8) | C39: =CUBEVALUE("ThisWorkbookDataModel","[Measures].[Net Sales]",CUBERANKEDMEMBER("ThisWorkbookDataModel",$H$30,8)) | D39: =CUBEVALUE("ThisWorkbookDataModel","[Measures].[Gross Profit]",CUBERANKEDMEMBER("ThisWorkbookDataModel",$H$30,8)) | E39: =CUBEVALUE("ThisWorkbookDataModel","[Measures].[Gross Margin %]",CUBERANKEDMEMBER("ThisWorkbookDataModel",$H$30,8))
B42: VARIANT DETAIL
B43: [ Variant Detail (PivotTable) — Not implementable: SKU/variant attributes (Price, Compare-at Price, current Unit Cost, Status) are row-level dimension data, not aggregate measures — CUBE functions can rank/aggregate a dimension's members by a measure (used above), but can't display raw per-row attribute columns the way a real PivotTable's row area can. Full variant detail is on DIM_Product / RAW_Variants directly. ]
B47: ↓ Drill into Product
B49: KNOWN GAPS ON THIS SHEET (documented, not silently missing)
B50: Active SKUs: No DAX measure counts total/active SKUs — dax/MEASURES.md's Product Profitability section (§4) covers profit PER SKU via PivotTable row context, not a SKU-count aggregate. A DISTINCTCOUNT(DIM_Product[SKU]) measure doesn't exist in the library; adding one is out of this phase's reuse-only scope.
B53: PRODUCT COST MASTER (Phase 3 — green cells = type here; Cost ID, Total Landed Cost, Expected Gross Margin %, and the overlap warning are automatic)
B54: Historical costing: never edit or delete a past row when a cost changes — add a NEW row for the new cost with its own Effective From Date, and set the OLD row's Effective To Date to the day before and its Active Flag to Inactive. Phase 4's COGS calculation will match each order line to the cost row whose SKU matches and whose Effective From/To range contains the order's date — so past orders keep using the cost that was actually active when they happened, even after costs change.
B56: Cost ID | C56: SKU | D56: Product Name | E56: Variant | F56: Collection | G56: Fabric Cost | H56: Accessories Cost | I56: Manufacturing Cost | J56: Packaging Cost | K56: Shipping Cost | L56: Other Cost | M56: Total Landed Cost | N56: Selling Price | O56: Expected Gross Margin % | P56: Effective From Date | Q56: Effective To Date | R56: Active Flag | S56: Overlap Warning
B57: ="COST-"&TEXT(ROW()-56,"00000") | D57: EXAMPLE — Amara Wrap Dress | E57: Black / M | G57: 180 | H57: 25 | I57: 90 | J57: 15 | K57: 20 | L57: 0 | M57: =SUM([@[Fabric Cost]],[@[Accessories Cost]],[@[Manufacturing Cost]],[@[Packaging Cost]],[@[Shipping Cost]],[@[Other Cost]]) | N57: 650 | O57: =IF([@[Selling Price]]=0,"",([@[Selling Price]]-[@[Total Landed Cost]])/[@[Selling Price]]) | P57: 2026-01-01 | R57: Active | S57: =IF(COUNTIFS(tbl_ProductCostMaster[SKU],[@SKU],tbl_ProductCostMaster[Active Flag],"Active")>1,"Multiple Active cost rows for this SKU — deactivate all but the current one","")

Sheet 06_Customers
A1: Customers
A2: PASSRESS MIS | Home ▸ Customers
A3: Sheet Documentation (use the + outline control at left to expand)
A4: Purpose | B4: Customer analytics — lifetime value, repeat-purchase rate, and geography.
A5: Input tables | B5: DIM_Customer, FACT_OrderLines.
A6: Output tables | B6: Customer KPI row, Top Customers / Geography breakdown tables (CUBE-function substitutes for a PivotTable).
A7: Relationships | B7: DIM_Customer links to FACT_OrderLines on CustomerKey.
A8: Future data source | B8: Live now: reads dax/MEASURES.md's Customer Metrics measures (§5) directly.
B11: TOTAL CUSTOMERS | D11: NEW CUSTOMERS | F11: REPEAT RATE % | H11: AVG LTV
B12: N/A | D12: =CUBEVALUE("ThisWorkbookDataModel","[Measures].[New Customers]") | F12: =CUBEVALUE("ThisWorkbookDataModel","[Measures].[Repeat Customer % Actual]") | H12: =CUBEVALUE("ThisWorkbookDataModel","[Measures].[Customer Lifetime Value (Historical)]")
B16: COHORT TREND / COHORT TABLE
B17: [ Cohort Trend (Chart) / Cohort Table (PivotTable) — Not implementable: dax/MEASURES.md §5 documents Customer Cohorts as a PivotTable LAYOUT (DIM_Customer[CohortMonth] on rows, DIM_Date[MonthName]/[Year] on columns), not a single measure — it is inherently a 2-dimensional matrix. CUBE functions here rank a single dimension by a single measure (used everywhere else on this sheet); reproducing a true cohort matrix would need nested CUBESET/CUBEVALUE expressions per cohort-month x calendar-month intersection — the same class of advanced, execution-untestable MDX pattern already flagged as a confidence risk in dax/README.md and the Phase 5/6 documentation. Not attempted rather than shipped unverified. ]
B23: TOP CUSTOMERS
B24: Top Customers (Top 8 by Net Sales) | G24: =CUBESET("ThisWorkbookDataModel","{[DIM_Customer].[Name].Children}","Top Customers (Top 8 by Net Sales)","BDESC","[Measures].[Net Sales]")
B25: Name | C25: Net Sales | D25: CLV (Historical)
B26: =CUBERANKEDMEMBER("ThisWorkbookDataModel",$G$24,1) | C26: =CUBEVALUE("ThisWorkbookDataModel","[Measures].[Net Sales]",CUBERANKEDMEMBER("ThisWorkbookDataModel",$G$24,1)) | D26: =CUBEVALUE("ThisWorkbookDataModel","[Measures].[Customer Lifetime Value (Historical)]",CUBERANKEDMEMBER("ThisWorkbookDataModel",$G$24,1))
B27: =CUBERANKEDMEMBER("ThisWorkbookDataModel",$G$24,2) | C27: =CUBEVALUE("ThisWorkbookDataModel","[Measures].[Net Sales]",CUBERANKEDMEMBER("ThisWorkbookDataModel",$G$24,2)) | D27: =CUBEVALUE("ThisWorkbookDataModel","[Measures].[Customer Lifetime Value (Historical)]",CUBERANKEDMEMBER("ThisWorkbookDataModel",$G$24,2))
B28: =CUBERANKEDMEMBER("ThisWorkbookDataModel",$G$24,3) | C28: =CUBEVALUE("ThisWorkbookDataModel","[Measures].[Net Sales]",CUBERANKEDMEMBER("ThisWorkbookDataModel",$G$24,3)) | D28: =CUBEVALUE("ThisWorkbookDataModel","[Measures].[Customer Lifetime Value (Historical)]",CUBERANKEDMEMBER("ThisWorkbookDataModel",$G$24,3))
B29: =CUBERANKEDMEMBER("ThisWorkbookDataModel",$G$24,4) | C29: =CUBEVALUE("ThisWorkbookDataModel","[Measures].[Net Sales]",CUBERANKEDMEMBER("ThisWorkbookDataModel",$G$24,4)) | D29: =CUBEVALUE("ThisWorkbookDataModel","[Measures].[Customer Lifetime Value (Historical)]",CUBERANKEDMEMBER("ThisWorkbookDataModel",$G$24,4))
B30: =CUBERANKEDMEMBER("ThisWorkbookDataModel",$G$24,5) | C30: =CUBEVALUE("ThisWorkbookDataModel","[Measures].[Net Sales]",CUBERANKEDMEMBER("ThisWorkbookDataModel",$G$24,5)) | D30: =CUBEVALUE("ThisWorkbookDataModel","[Measures].[Customer Lifetime Value (Historical)]",CUBERANKEDMEMBER("ThisWorkbookDataModel",$G$24,5))
B31: =CUBERANKEDMEMBER("ThisWorkbookDataModel",$G$24,6) | C31: =CUBEVALUE("ThisWorkbookDataModel","[Measures].[Net Sales]",CUBERANKEDMEMBER("ThisWorkbookDataModel",$G$24,6)) | D31: =CUBEVALUE("ThisWorkbookDataModel","[Measures].[Customer Lifetime Value (Historical)]",CUBERANKEDMEMBER("ThisWorkbookDataModel",$G$24,6))
B32: =CUBERANKEDMEMBER("ThisWorkbookDataModel",$G$24,7) | C32: =CUBEVALUE("ThisWorkbookDataModel","[Measures].[Net Sales]",CUBERANKEDMEMBER("ThisWorkbookDataModel",$G$24,7)) | D32: =CUBEVALUE("ThisWorkbookDataModel","[Measures].[Customer Lifetime Value (Historical)]",CUBERANKEDMEMBER("ThisWorkbookDataModel",$G$24,7))
B33: =CUBERANKEDMEMBER("ThisWorkbookDataModel",$G$24,8) | C33: =CUBEVALUE("ThisWorkbookDataModel","[Measures].[Net Sales]",CUBERANKEDMEMBER("ThisWorkbookDataModel",$G$24,8)) | D33: =CUBEVALUE("ThisWorkbookDataModel","[Measures].[Customer Lifetime Value (Historical)]",CUBERANKEDMEMBER("ThisWorkbookDataModel",$G$24,8))
B36: GEOGRAPHY
B37: Geography (Net Sales by Country) | F37: =CUBESET("ThisWorkbookDataModel","{[DIM_Customer].[Country].Children}","Geography (Net Sales by Country)","BDESC","[Measures].[Net Sales]")
B38: Country | C38: Net Sales
B39: =CUBERANKEDMEMBER("ThisWorkbookDataModel",$F$37,1) | C39: =CUBEVALUE("ThisWorkbookDataModel","[Measures].[Net Sales]",CUBERANKEDMEMBER("ThisWorkbookDataModel",$F$37,1))
B40: =CUBERANKEDMEMBER("ThisWorkbookDataModel",$F$37,2) | C40: =CUBEVALUE("ThisWorkbookDataModel","[Measures].[Net Sales]",CUBERANKEDMEMBER("ThisWorkbookDataModel",$F$37,2))
B41: =CUBERANKEDMEMBER("ThisWorkbookDataModel",$F$37,3) | C41: =CUBEVALUE("ThisWorkbookDataModel","[Measures].[Net Sales]",CUBERANKEDMEMBER("ThisWorkbookDataModel",$F$37,3))
B42: =CUBERANKEDMEMBER("ThisWorkbookDataModel",$F$37,4) | C42: =CUBEVALUE("ThisWorkbookDataModel","[Measures].[Net Sales]",CUBERANKEDMEMBER("ThisWorkbookDataModel",$F$37,4))
B43: =CUBERANKEDMEMBER("ThisWorkbookDataModel",$F$37,5) | C43: =CUBEVALUE("ThisWorkbookDataModel","[Measures].[Net Sales]",CUBERANKEDMEMBER("ThisWorkbookDataModel",$F$37,5))
B44: =CUBERANKEDMEMBER("ThisWorkbookDataModel",$F$37,6) | C44: =CUBEVALUE("ThisWorkbookDataModel","[Measures].[Net Sales]",CUBERANKEDMEMBER("ThisWorkbookDataModel",$F$37,6))
B45: =CUBERANKEDMEMBER("ThisWorkbookDataModel",$F$37,7) | C45: =CUBEVALUE("ThisWorkbookDataModel","[Measures].[Net Sales]",CUBERANKEDMEMBER("ThisWorkbookDataModel",$F$37,7))
B46: =CUBERANKEDMEMBER("ThisWorkbookDataModel",$F$37,8) | C46: =CUBEVALUE("ThisWorkbookDataModel","[Measures].[Net Sales]",CUBERANKEDMEMBER("ThisWorkbookDataModel",$F$37,8))
B47: =CUBERANKEDMEMBER("ThisWorkbookDataModel",$F$37,9) | C47: =CUBEVALUE("ThisWorkbookDataModel","[Measures].[Net Sales]",CUBERANKEDMEMBER("ThisWorkbookDataModel",$F$37,9))
B48: =CUBERANKEDMEMBER("ThisWorkbookDataModel",$F$37,10) | C48: =CUBEVALUE("ThisWorkbookDataModel","[Measures].[Net Sales]",CUBERANKEDMEMBER("ThisWorkbookDataModel",$F$37,10))
B51: KNOWN GAPS ON THIS SHEET (documented, not silently missing)
B52: Total Customers: No DAX measure counts the full customer roster — dax/MEASURES.md defines [Customers Active (Current Period)] (period-filtered) and [New Customers] (first-order-in-period), but no all-time DISTINCTCOUNT(DIM_Customer[CustomerKey]) measure exists. Mapping this card to either existing measure would misrepresent what it actually counts, so it's left undocumented rather than mislabeled.

Sheet 07_Inventory
A1: Inventory
A2: PASSRESS MIS | Home ▸ Inventory
A3: Sheet Documentation (use the + outline control at left to expand)
A4: Purpose | B4: Stock levels, valuation, and turnover.
A5: Input tables | B5: FACT_InventoryMovements, DIM_Product, DIM_Location.
A6: Output tables | B6: Inventory KPI row, Stock Trend chart, Stock by Location / Low Stock / Inventory Valuation breakdown tables (CUBE-function substitutes for a PivotTable).
A7: Relationships | B7: FACT_InventoryMovements links to DIM_Product and DIM_Location.
A8: Future data source | B8: Live now: reads dax/MEASURES.md's Inventory Metrics measures (§6) directly.
B11: INVENTORY VALUE | D11: UNITS ON HAND | F11: INVENTORY TURNS | H11: STOCKOUT RISK
B12: =CUBEVALUE("ThisWorkbookDataModel","[Measures].[Inventory Value]") | D12: N/A | F12: =CUBEVALUE("ThisWorkbookDataModel","[Measures].[Inventory Turnover]") | H12: N/A
B16: STOCK TREND
B17: Uses [Average Inventory Value], not [Inventory Value]: dax/MEASURES.md §6 documents that [Inventory Value] always returns the MOST RECENT snapshot regardless of any date filter — charting it by month would repeat the same 'today' figure 12 times, not show a real trend. [Average Inventory Value] is the measure specifically documented as date-filter-aware, so it's the one that actually plots a trend.
B18: Average Inventory Value — trailing 12 months
C19: =TEXT(EDATE(TODAY(),-11),"mmm-yy") | D19: =TEXT(EDATE(TODAY(),-10),"mmm-yy") | E19: =TEXT(EDATE(TODAY(),-9),"mmm-yy") | F19: =TEXT(EDATE(TODAY(),-8),"mmm-yy") | G19: =TEXT(EDATE(TODAY(),-7),"mmm-yy") | H19: =TEXT(EDATE(TODAY(),-6),"mmm-yy") | I19: =TEXT(EDATE(TODAY(),-5),"mmm-yy") | J19: =TEXT(EDATE(TODAY(),-4),"mmm-yy") | K19: =TEXT(EDATE(TODAY(),-3),"mmm-yy") | L19: =TEXT(EDATE(TODAY(),-2),"mmm-yy") | M19: =TEXT(EDATE(TODAY(),-1),"mmm-yy") | N19: =TEXT(EDATE(TODAY(),0),"mmm-yy")
C20: =CUBEVALUE("ThisWorkbookDataModel","[Measures].[Average Inventory Value]","[DIM_Date].[Year].&["&YEAR(EDATE(TODAY(),-11))&"]","[DIM_Date].[Month].&["&MONTH(EDATE(TODAY(),-11))&"]") | D20: =CUBEVALUE("ThisWorkbookDataModel","[Measures].[Average Inventory Value]","[DIM_Date].[Year].&["&YEAR(EDATE(TODAY(),-10))&"]","[DIM_Date].[Month].&["&MONTH(EDATE(TODAY(),-10))&"]") | E20: =CUBEVALUE("ThisWorkbookDataModel","[Measures].[Average Inventory Value]","[DIM_Date].[Year].&["&YEAR(EDATE(TODAY(),-9))&"]","[DIM_Date].[Month].&["&MONTH(EDATE(TODAY(),-9))&"]") | F20: =CUBEVALUE("ThisWorkbookDataModel","[Measures].[Average Inventory Value]","[DIM_Date].[Year].&["&YEAR(EDATE(TODAY(),-8))&"]","[DIM_Date].[Month].&["&MONTH(EDATE(TODAY(),-8))&"]") | G20: =CUBEVALUE("ThisWorkbookDataModel","[Measures].[Average Inventory Value]","[DIM_Date].[Year].&["&YEAR(EDATE(TODAY(),-7))&"]","[DIM_Date].[Month].&["&MONTH(EDATE(TODAY(),-7))&"]") | H20: =CUBEVALUE("ThisWorkbookDataModel","[Measures].[Average Inventory Value]","[DIM_Date].[Year].&["&YEAR(EDATE(TODAY(),-6))&"]","[DIM_Date].[Month].&["&MONTH(EDATE(TODAY(),-6))&"]") | I20: =CUBEVALUE("ThisWorkbookDataModel","[Measures].[Average Inventory Value]","[DIM_Date].[Year].&["&YEAR(EDATE(TODAY(),-5))&"]","[DIM_Date].[Month].&["&MONTH(EDATE(TODAY(),-5))&"]") | J20: =CUBEVALUE("ThisWorkbookDataModel","[Measures].[Average Inventory Value]","[DIM_Date].[Year].&["&YEAR(EDATE(TODAY(),-4))&"]","[DIM_Date].[Month].&["&MONTH(EDATE(TODAY(),-4))&"]") | K20: =CUBEVALUE("ThisWorkbookDataModel","[Measures].[Average Inventory Value]","[DIM_Date].[Year].&["&YEAR(EDATE(TODAY(),-3))&"]","[DIM_Date].[Month].&["&MONTH(EDATE(TODAY(),-3))&"]") | L20: =CUBEVALUE("ThisWorkbookDataModel","[Measures].[Average Inventory Value]","[DIM_Date].[Year].&["&YEAR(EDATE(TODAY(),-2))&"]","[DIM_Date].[Month].&["&MONTH(EDATE(TODAY(),-2))&"]") | M20: =CUBEVALUE("ThisWorkbookDataModel","[Measures].[Average Inventory Value]","[DIM_Date].[Year].&["&YEAR(EDATE(TODAY(),-1))&"]","[DIM_Date].[Month].&["&MONTH(EDATE(TODAY(),-1))&"]") | N20: =CUBEVALUE("ThisWorkbookDataModel","[Measures].[Average Inventory Value]","[DIM_Date].[Year].&["&YEAR(EDATE(TODAY(),0))&"]","[DIM_Date].[Month].&["&MONTH(EDATE(TODAY(),0))&"]")
B38: STOCK BY LOCATION
B39: Stock by Location (Inventory Value) | F39: =CUBESET("ThisWorkbookDataModel","{[DIM_Location].[LocationName].Children}","Stock by Location (Inventory Value)","BDESC","[Measures].[Inventory Value]")
B40: LocationName | C40: Inventory Value
B41: =CUBERANKEDMEMBER("ThisWorkbookDataModel",$F$39,1) | C41: =CUBEVALUE("ThisWorkbookDataModel","[Measures].[Inventory Value]",CUBERANKEDMEMBER("ThisWorkbookDataModel",$F$39,1))
B42: =CUBERANKEDMEMBER("ThisWorkbookDataModel",$F$39,2) | C42: =CUBEVALUE("ThisWorkbookDataModel","[Measures].[Inventory Value]",CUBERANKEDMEMBER("ThisWorkbookDataModel",$F$39,2))
B43: =CUBERANKEDMEMBER("ThisWorkbookDataModel",$F$39,3) | C43: =CUBEVALUE("ThisWorkbookDataModel","[Measures].[Inventory Value]",CUBERANKEDMEMBER("ThisWorkbookDataModel",$F$39,3))
B44: =CUBERANKEDMEMBER("ThisWorkbookDataModel",$F$39,4) | C44: =CUBEVALUE("ThisWorkbookDataModel","[Measures].[Inventory Value]",CUBERANKEDMEMBER("ThisWorkbookDataModel",$F$39,4))
B45: =CUBERANKEDMEMBER("ThisWorkbookDataModel",$F$39,5) | C45: =CUBEVALUE("ThisWorkbookDataModel","[Measures].[Inventory Value]",CUBERANKEDMEMBER("ThisWorkbookDataModel",$F$39,5))
B46: =CUBERANKEDMEMBER("ThisWorkbookDataModel",$F$39,6) | C46: =CUBEVALUE("ThisWorkbookDataModel","[Measures].[Inventory Value]",CUBERANKEDMEMBER("ThisWorkbookDataModel",$F$39,6))
B47: =CUBERANKEDMEMBER("ThisWorkbookDataModel",$F$39,7) | C47: =CUBEVALUE("ThisWorkbookDataModel","[Measures].[Inventory Value]",CUBERANKEDMEMBER("ThisWorkbookDataModel",$F$39,7))
B48: =CUBERANKEDMEMBER("ThisWorkbookDataModel",$F$39,8) | C48: =CUBEVALUE("ThisWorkbookDataModel","[Measures].[Inventory Value]",CUBERANKEDMEMBER("ThisWorkbookDataModel",$F$39,8))
B49: =CUBERANKEDMEMBER("ThisWorkbookDataModel",$F$39,9) | C49: =CUBEVALUE("ThisWorkbookDataModel","[Measures].[Inventory Value]",CUBERANKEDMEMBER("ThisWorkbookDataModel",$F$39,9))
B50: =CUBERANKEDMEMBER("ThisWorkbookDataModel",$F$39,10) | C50: =CUBEVALUE("ThisWorkbookDataModel","[Measures].[Inventory Value]",CUBERANKEDMEMBER("ThisWorkbookDataModel",$F$39,10))
B53: LOW STOCK LIST
B54: Ranked by Inventory Value, ascending — a unit-count 'low stock' measure doesn't exist (see Units on Hand, above); Inventory Value ascending is the closest existing-measure proxy for 'what's running low.'
B55: Low Stock List (Bottom 8 by Inventory Value) | F55: =CUBESET("ThisWorkbookDataModel","{[DIM_Product].[Title].Children}","Low Stock List (Bottom 8 by Inventory Value)","BASC","[Measures].[Inventory Value]")
B56: Title | C56: Inventory Value
B57: =CUBERANKEDMEMBER("ThisWorkbookDataModel",$F$55,1) | C57: =CUBEVALUE("ThisWorkbookDataModel","[Measures].[Inventory Value]",CUBERANKEDMEMBER("ThisWorkbookDataModel",$F$55,1))
B58: =CUBERANKEDMEMBER("ThisWorkbookDataModel",$F$55,2) | C58: =CUBEVALUE("ThisWorkbookDataModel","[Measures].[Inventory Value]",CUBERANKEDMEMBER("ThisWorkbookDataModel",$F$55,2))
B59: =CUBERANKEDMEMBER("ThisWorkbookDataModel",$F$55,3) | C59: =CUBEVALUE("ThisWorkbookDataModel","[Measures].[Inventory Value]",CUBERANKEDMEMBER("ThisWorkbookDataModel",$F$55,3))
B60: =CUBERANKEDMEMBER("ThisWorkbookDataModel",$F$55,4) | C60: =CUBEVALUE("ThisWorkbookDataModel","[Measures].[Inventory Value]",CUBERANKEDMEMBER("ThisWorkbookDataModel",$F$55,4))
B61: =CUBERANKEDMEMBER("ThisWorkbookDataModel",$F$55,5) | C61: =CUBEVALUE("ThisWorkbookDataModel","[Measures].[Inventory Value]",CUBERANKEDMEMBER("ThisWorkbookDataModel",$F$55,5))
B62: =CUBERANKEDMEMBER("ThisWorkbookDataModel",$F$55,6) | C62: =CUBEVALUE("ThisWorkbookDataModel","[Measures].[Inventory Value]",CUBERANKEDMEMBER("ThisWorkbookDataModel",$F$55,6))
B63: =CUBERANKEDMEMBER("ThisWorkbookDataModel",$F$55,7) | C63: =CUBEVALUE("ThisWorkbookDataModel","[Measures].[Inventory Value]",CUBERANKEDMEMBER("ThisWorkbookDataModel",$F$55,7))
B64: =CUBERANKEDMEMBER("ThisWorkbookDataModel",$F$55,8) | C64: =CUBEVALUE("ThisWorkbookDataModel","[Measures].[Inventory Value]",CUBERANKEDMEMBER("ThisWorkbookDataModel",$F$55,8))
B67: INVENTORY VALUATION
B68: Inventory Valuation (Top 8 Products by Inventory Value) | F68: =CUBESET("ThisWorkbookDataModel","{[DIM_Product].[Title].Children}","Inventory Valuation (Top 8 Products by Inventory Value)","BDESC","[Measures].[Inventory Value]")
B69: Title | C69: Inventory Value
B70: =CUBERANKEDMEMBER("ThisWorkbookDataModel",$F$68,1) | C70: =CUBEVALUE("ThisWorkbookDataModel","[Measures].[Inventory Value]",CUBERANKEDMEMBER("ThisWorkbookDataModel",$F$68,1))
B71: =CUBERANKEDMEMBER("ThisWorkbookDataModel",$F$68,2) | C71: =CUBEVALUE("ThisWorkbookDataModel","[Measures].[Inventory Value]",CUBERANKEDMEMBER("ThisWorkbookDataModel",$F$68,2))
B72: =CUBERANKEDMEMBER("ThisWorkbookDataModel",$F$68,3) | C72: =CUBEVALUE("ThisWorkbookDataModel","[Measures].[Inventory Value]",CUBERANKEDMEMBER("ThisWorkbookDataModel",$F$68,3))
B73: =CUBERANKEDMEMBER("ThisWorkbookDataModel",$F$68,4) | C73: =CUBEVALUE("ThisWorkbookDataModel","[Measures].[Inventory Value]",CUBERANKEDMEMBER("ThisWorkbookDataModel",$F$68,4))
B74: =CUBERANKEDMEMBER("ThisWorkbookDataModel",$F$68,5) | C74: =CUBEVALUE("ThisWorkbookDataModel","[Measures].[Inventory Value]",CUBERANKEDMEMBER("ThisWorkbookDataModel",$F$68,5))
B75: =CUBERANKEDMEMBER("ThisWorkbookDataModel",$F$68,6) | C75: =CUBEVALUE("ThisWorkbookDataModel","[Measures].[Inventory Value]",CUBERANKEDMEMBER("ThisWorkbookDataModel",$F$68,6))
B76: =CUBERANKEDMEMBER("ThisWorkbookDataModel",$F$68,7) | C76: =CUBEVALUE("ThisWorkbookDataModel","[Measures].[Inventory Value]",CUBERANKEDMEMBER("ThisWorkbookDataModel",$F$68,7))
B77: =CUBERANKEDMEMBER("ThisWorkbookDataModel",$F$68,8) | C77: =CUBEVALUE("ThisWorkbookDataModel","[Measures].[Inventory Value]",CUBERANKEDMEMBER("ThisWorkbookDataModel",$F$68,8))
B80: KNOWN GAPS ON THIS SHEET (documented, not silently missing)
B81: Units on Hand: No DAX measure sums on-hand units across products — dax/MEASURES.md's Inventory Metrics (§6) are all VALUE-based ([Inventory Value], [Average Inventory Value]) or RATIO-based (Turnover, Days of Inventory, Stock Coverage), never a plain unit-count aggregate of FACT_InventoryMovements[ResultingOnHand]. Adding one would be a new measure outside this phase's reuse-only scope.
B82: Stockout Risk: No DAX measure or defined threshold exists for stockout risk — dax/MEASURES.md defines Slow Moving / Dead Stock SKU Count (low or zero sales while holding stock) but nothing for the opposite risk (high sales velocity vs. low remaining stock). Building one would require inventing a new business rule (a velocity-vs-stock threshold), which this phase's 'no new KPIs' scope rules out.

Sheet 08_Finance
A1: Finance
A2: PASSRESS MIS | Home ▸ Finance
A3: Sheet Documentation (use the + outline control at left to expand)
A4: Purpose | B4: Core management-basis financial statements — Profit & Loss and Cash Flow summary (not audited books).
A5: Input tables | B5: FACT_OrderLines, FACT_ManualExpenses, FACT_Payments, Chart of Accounts mapping (15_Settings).
A6: Output tables | B6: Finance KPI row, P&L Trend chart, P&L Statement and Cash Flow Statement (CUBE-function substitutes for a PivotTable, transcribing dax/MEASURES.md §1/§3's own documented measure maps into working formulas).
A7: Relationships | B7: Combines Shopify-sourced facts with manually entered FACT_ManualExpenses, categorized via the Chart of Accounts mapping table.
A8: Future data source | B8: Live now: every line reads an existing dax/MEASURES.md measure directly.
B11: NET SALES | D11: TOTAL EXPENSES | F11: NET PROFIT | H11: CASH BALANCE
B12: =CUBEVALUE("ThisWorkbookDataModel","[Measures].[Net Sales]") | D12: =CUBEVALUE("ThisWorkbookDataModel","[Measures].[Operating Expenses]") | F12: =CUBEVALUE("ThisWorkbookDataModel","[Measures].[Net Profit]") | H12: =CUBEVALUE("ThisWorkbookDataModel","[Measures].[Cash Position (Direct, Cumulative)]")
B16: P&L TREND (Net Sales / Operating Expenses / Net Profit)
C18: =TEXT(EDATE(TODAY(),-11),"mmm-yy") | D18: =TEXT(EDATE(TODAY(),-10),"mmm-yy") | E18: =TEXT(EDATE(TODAY(),-9),"mmm-yy") | F18: =TEXT(EDATE(TODAY(),-8),"mmm-yy") | G18: =TEXT(EDATE(TODAY(),-7),"mmm-yy") | H18: =TEXT(EDATE(TODAY(),-6),"mmm-yy") | I18: =TEXT(EDATE(TODAY(),-5),"mmm-yy") | J18: =TEXT(EDATE(TODAY(),-4),"mmm-yy") | K18: =TEXT(EDATE(TODAY(),-3),"mmm-yy") | L18: =TEXT(EDATE(TODAY(),-2),"mmm-yy") | M18: =TEXT(EDATE(TODAY(),-1),"mmm-yy") | N18: =TEXT(EDATE(TODAY(),0),"mmm-yy")
B19: Net Sales | C19: =CUBEVALUE("ThisWorkbookDataModel","[Measures].[Net Sales]","[DIM_Date].[Year].&["&YEAR(EDATE(TODAY(),-11))&"]","[DIM_Date].[Month].&["&MONTH(EDATE(TODAY(),-11))&"]") | D19: =CUBEVALUE("ThisWorkbookDataModel","[Measures].[Net Sales]","[DIM_Date].[Year].&["&YEAR(EDATE(TODAY(),-10))&"]","[DIM_Date].[Month].&["&MONTH(EDATE(TODAY(),-10))&"]") | E19: =CUBEVALUE("ThisWorkbookDataModel","[Measures].[Net Sales]","[DIM_Date].[Year].&["&YEAR(EDATE(TODAY(),-9))&"]","[DIM_Date].[Month].&["&MONTH(EDATE(TODAY(),-9))&"]") | F19: =CUBEVALUE("ThisWorkbookDataModel","[Measures].[Net Sales]","[DIM_Date].[Year].&["&YEAR(EDATE(TODAY(),-8))&"]","[DIM_Date].[Month].&["&MONTH(EDATE(TODAY(),-8))&"]") | G19: =CUBEVALUE("ThisWorkbookDataModel","[Measures].[Net Sales]","[DIM_Date].[Year].&["&YEAR(EDATE(TODAY(),-7))&"]","[DIM_Date].[Month].&["&MONTH(EDATE(TODAY(),-7))&"]") | H19: =CUBEVALUE("ThisWorkbookDataModel","[Measures].[Net Sales]","[DIM_Date].[Year].&["&YEAR(EDATE(TODAY(),-6))&"]","[DIM_Date].[Month].&["&MONTH(EDATE(TODAY(),-6))&"]") | I19: =CUBEVALUE("ThisWorkbookDataModel","[Measures].[Net Sales]","[DIM_Date].[Year].&["&YEAR(EDATE(TODAY(),-5))&"]","[DIM_Date].[Month].&["&MONTH(EDATE(TODAY(),-5))&"]") | J19: =CUBEVALUE("ThisWorkbookDataModel","[Measures].[Net Sales]","[DIM_Date].[Year].&["&YEAR(EDATE(TODAY(),-4))&"]","[DIM_Date].[Month].&["&MONTH(EDATE(TODAY(),-4))&"]") | K19: =CUBEVALUE("ThisWorkbookDataModel","[Measures].[Net Sales]","[DIM_Date].[Year].&["&YEAR(EDATE(TODAY(),-3))&"]","[DIM_Date].[Month].&["&MONTH(EDATE(TODAY(),-3))&"]") | L19: =CUBEVALUE("ThisWorkbookDataModel","[Measures].[Net Sales]","[DIM_Date].[Year].&["&YEAR(EDATE(TODAY(),-2))&"]","[DIM_Date].[Month].&["&MONTH(EDATE(TODAY(),-2))&"]") | M19: =CUBEVALUE("ThisWorkbookDataModel","[Measures].[Net Sales]","[DIM_Date].[Year].&["&YEAR(EDATE(TODAY(),-1))&"]","[DIM_Date].[Month].&["&MONTH(EDATE(TODAY(),-1))&"]") | N19: =CUBEVALUE("ThisWorkbookDataModel","[Measures].[Net Sales]","[DIM_Date].[Year].&["&YEAR(EDATE(TODAY(),0))&"]","[DIM_Date].[Month].&["&MONTH(EDATE(TODAY(),0))&"]")
B20: Operating Expenses | C20: =CUBEVALUE("ThisWorkbookDataModel","[Measures].[Operating Expenses]","[DIM_Date].[Year].&["&YEAR(EDATE(TODAY(),-11))&"]","[DIM_Date].[Month].&["&MONTH(EDATE(TODAY(),-11))&"]") | D20: =CUBEVALUE("ThisWorkbookDataModel","[Measures].[Operating Expenses]","[DIM_Date].[Year].&["&YEAR(EDATE(TODAY(),-10))&"]","[DIM_Date].[Month].&["&MONTH(EDATE(TODAY(),-10))&"]") | E20: =CUBEVALUE("ThisWorkbookDataModel","[Measures].[Operating Expenses]","[DIM_Date].[Year].&["&YEAR(EDATE(TODAY(),-9))&"]","[DIM_Date].[Month].&["&MONTH(EDATE(TODAY(),-9))&"]") | F20: =CUBEVALUE("ThisWorkbookDataModel","[Measures].[Operating Expenses]","[DIM_Date].[Year].&["&YEAR(EDATE(TODAY(),-8))&"]","[DIM_Date].[Month].&["&MONTH(EDATE(TODAY(),-8))&"]") | G20: =CUBEVALUE("ThisWorkbookDataModel","[Measures].[Operating Expenses]","[DIM_Date].[Year].&["&YEAR(EDATE(TODAY(),-7))&"]","[DIM_Date].[Month].&["&MONTH(EDATE(TODAY(),-7))&"]") | H20: =CUBEVALUE("ThisWorkbookDataModel","[Measures].[Operating Expenses]","[DIM_Date].[Year].&["&YEAR(EDATE(TODAY(),-6))&"]","[DIM_Date].[Month].&["&MONTH(EDATE(TODAY(),-6))&"]") | I20: =CUBEVALUE("ThisWorkbookDataModel","[Measures].[Operating Expenses]","[DIM_Date].[Year].&["&YEAR(EDATE(TODAY(),-5))&"]","[DIM_Date].[Month].&["&MONTH(EDATE(TODAY(),-5))&"]") | J20: =CUBEVALUE("ThisWorkbookDataModel","[Measures].[Operating Expenses]","[DIM_Date].[Year].&["&YEAR(EDATE(TODAY(),-4))&"]","[DIM_Date].[Month].&["&MONTH(EDATE(TODAY(),-4))&"]") | K20: =CUBEVALUE("ThisWorkbookDataModel","[Measures].[Operating Expenses]","[DIM_Date].[Year].&["&YEAR(EDATE(TODAY(),-3))&"]","[DIM_Date].[Month].&["&MONTH(EDATE(TODAY(),-3))&"]") | L20: =CUBEVALUE("ThisWorkbookDataModel","[Measures].[Operating Expenses]","[DIM_Date].[Year].&["&YEAR(EDATE(TODAY(),-2))&"]","[DIM_Date].[Month].&["&MONTH(EDATE(TODAY(),-2))&"]") | M20: =CUBEVALUE("ThisWorkbookDataModel","[Measures].[Operating Expenses]","[DIM_Date].[Year].&["&YEAR(EDATE(TODAY(),-1))&"]","[DIM_Date].[Month].&["&MONTH(EDATE(TODAY(),-1))&"]") | N20: =CUBEVALUE("ThisWorkbookDataModel","[Measures].[Operating Expenses]","[DIM_Date].[Year].&["&YEAR(EDATE(TODAY(),0))&"]","[DIM_Date].[Month].&["&MONTH(EDATE(TODAY(),0))&"]")
B21: Net Profit | C21: =CUBEVALUE("ThisWorkbookDataModel","[Measures].[Net Profit]","[DIM_Date].[Year].&["&YEAR(EDATE(TODAY(),-11))&"]","[DIM_Date].[Month].&["&MONTH(EDATE(TODAY(),-11))&"]") | D21: =CUBEVALUE("ThisWorkbookDataModel","[Measures].[Net Profit]","[DIM_Date].[Year].&["&YEAR(EDATE(TODAY(),-10))&"]","[DIM_Date].[Month].&["&MONTH(EDATE(TODAY(),-10))&"]") | E21: =CUBEVALUE("ThisWorkbookDataModel","[Measures].[Net Profit]","[DIM_Date].[Year].&["&YEAR(EDATE(TODAY(),-9))&"]","[DIM_Date].[Month].&["&MONTH(EDATE(TODAY(),-9))&"]") | F21: =CUBEVALUE("ThisWorkbookDataModel","[Measures].[Net Profit]","[DIM_Date].[Year].&["&YEAR(EDATE(TODAY(),-8))&"]","[DIM_Date].[Month].&["&MONTH(EDATE(TODAY(),-8))&"]") | G21: =CUBEVALUE("ThisWorkbookDataModel","[Measures].[Net Profit]","[DIM_Date].[Year].&["&YEAR(EDATE(TODAY(),-7))&"]","[DIM_Date].[Month].&["&MONTH(EDATE(TODAY(),-7))&"]") | H21: =CUBEVALUE("ThisWorkbookDataModel","[Measures].[Net Profit]","[DIM_Date].[Year].&["&YEAR(EDATE(TODAY(),-6))&"]","[DIM_Date].[Month].&["&MONTH(EDATE(TODAY(),-6))&"]") | I21: =CUBEVALUE("ThisWorkbookDataModel","[Measures].[Net Profit]","[DIM_Date].[Year].&["&YEAR(EDATE(TODAY(),-5))&"]","[DIM_Date].[Month].&["&MONTH(EDATE(TODAY(),-5))&"]") | J21: =CUBEVALUE("ThisWorkbookDataModel","[Measures].[Net Profit]","[DIM_Date].[Year].&["&YEAR(EDATE(TODAY(),-4))&"]","[DIM_Date].[Month].&["&MONTH(EDATE(TODAY(),-4))&"]") | K21: =CUBEVALUE("ThisWorkbookDataModel","[Measures].[Net Profit]","[DIM_Date].[Year].&["&YEAR(EDATE(TODAY(),-3))&"]","[DIM_Date].[Month].&["&MONTH(EDATE(TODAY(),-3))&"]") | L21: =CUBEVALUE("ThisWorkbookDataModel","[Measures].[Net Profit]","[DIM_Date].[Year].&["&YEAR(EDATE(TODAY(),-2))&"]","[DIM_Date].[Month].&["&MONTH(EDATE(TODAY(),-2))&"]") | M21: =CUBEVALUE("ThisWorkbookDataModel","[Measures].[Net Profit]","[DIM_Date].[Year].&["&YEAR(EDATE(TODAY(),-1))&"]","[DIM_Date].[Month].&["&MONTH(EDATE(TODAY(),-1))&"]") | N21: =CUBEVALUE("ThisWorkbookDataModel","[Measures].[Net Profit]","[DIM_Date].[Year].&["&YEAR(EDATE(TODAY(),0))&"]","[DIM_Date].[Month].&["&MONTH(EDATE(TODAY(),0))&"]")
B41: P&L STATEMENT
B42: P&L Statement (dax/MEASURES.md §1)
B43: Gross Sales | D43: =CUBEVALUE("ThisWorkbookDataModel","[Measures].[Gross Sales]")
B44: Discounts | D44: =CUBEVALUE("ThisWorkbookDataModel","[Measures].[Discounts]")
B45: Returns | D45: =CUBEVALUE("ThisWorkbookDataModel","[Measures].[Returns]")
B46: Net Sales | D46: =CUBEVALUE("ThisWorkbookDataModel","[Measures].[Net Sales]")
B47: COGS | D47: =CUBEVALUE("ThisWorkbookDataModel","[Measures].[COGS]")
B48: Gross Profit | D48: =CUBEVALUE("ThisWorkbookDataModel","[Measures].[Gross Profit]")
B49: Gross Margin % | D49: =CUBEVALUE("ThisWorkbookDataModel","[Measures].[Gross Margin %]")
B50: Operating Expenses | D50: =CUBEVALUE("ThisWorkbookDataModel","[Measures].[Operating Expenses]")
B51: EBITDA | D51: =CUBEVALUE("ThisWorkbookDataModel","[Measures].[EBITDA]")
B52: Net Profit | D52: =CUBEVALUE("ThisWorkbookDataModel","[Measures].[Net Profit]")
B55: CASH FLOW STATEMENT
B56: Cash Flow Statement (dax/MEASURES.md §3)
B57: Cash Flow from Operating Activities | D57: =CUBEVALUE("ThisWorkbookDataModel","[Measures].[Cash Flow from Operating Activities]")
B58: Cash Flow from Investing Activities | D58: =CUBEVALUE("ThisWorkbookDataModel","[Measures].[Cash Flow from Investing Activities]")
B59: Cash Flow from Financing Activities | D59: =CUBEVALUE("ThisWorkbookDataModel","[Measures].[Cash Flow from Financing Activities]")
B60: Net Cash Flow | D60: =CUBEVALUE("ThisWorkbookDataModel","[Measures].[Net Cash Flow]")
B61: Cash Position (Direct, Cumulative) | D61: =CUBEVALUE("ThisWorkbookDataModel","[Measures].[Cash Position (Direct, Cumulative)]")
B65: BUDGET (Phase 5 — green cells = type here; Budget ID is automatic)
B66: Leave Month blank for a YEARLY budget line (the whole year's target for that Year+Category); fill in Month for a MONTHLY line. dax/MEASURES_PHASE5.md's [Budget Variance] / [Forecast vs Budget] measures match Actuals to whichever grain a report is built at.
B68: Budget ID | C68: Year | D68: Month | E68: Category | F68: Budget Amount | G68: Notes
B69: ="BUD-"&TEXT(ROW()-68,"00000") | C69: 2026 | E69: Revenue | F69: 500000 | G69: EXAMPLE — 2026 annual revenue budget

Sheet 09_Profitability
A1: Profitability
A2: PASSRESS MIS | Home ▸ Profitability
A3: Sheet Documentation (use the + outline control at left to expand)
A4: Purpose | B4: Margin analysis — gross margin and profitability by product and collection.
A5: Input tables | B5: FACT_OrderLines, DIM_Product, DIM_Collection.
A6: Output tables | B6: Profitability KPI row, Margin Trend chart, Margin by Product / Margin by Collection breakdown tables (CUBE-function substitutes for a PivotTable).
A7: Relationships | B7: FACT_OrderLines carries both revenue and COGS at line grain, enabling margin by any dimension.
A8: Future data source | B8: Live now: reads dax/MEASURES.md's Gross Margin %/Gross Profit measures directly.
B11: GROSS MARGIN % | D11: CONTRIBUTION MARGIN % | F11: BEST MARGIN CATEGORY | H11: WORST MARGIN CATEGORY | N11: =CUBESET("ThisWorkbookDataModel","{[DIM_Product].[ProductType].Children}","BestMarginCategory","BDESC","[Measures].[Gross Margin %]")
B12: =CUBEVALUE("ThisWorkbookDataModel","[Measures].[Gross Margin %]") | D12: N/A | F12: =CUBERANKEDMEMBER("ThisWorkbookDataModel",$N$11,1) | H12: =CUBERANKEDMEMBER("ThisWorkbookDataModel",$N$12,1) | N12: =CUBESET("ThisWorkbookDataModel","{[DIM_Product].[ProductType].Children}","WorstMarginCategory","BASC","[Measures].[Gross Margin %]")
B16: "Category" = Shopify's ProductType field (DIM_Product[ProductType]) — the workbook has no separate Category dimension. Same ranking caveat as BI_Insights' Best/Weakest Seller: a low-volume ProductType can rank first/last on a thin sample.
B17: MARGIN TREND
B18: Gross Margin % — trailing 12 months
C19: =TEXT(EDATE(TODAY(),-11),"mmm-yy") | D19: =TEXT(EDATE(TODAY(),-10),"mmm-yy") | E19: =TEXT(EDATE(TODAY(),-9),"mmm-yy") | F19: =TEXT(EDATE(TODAY(),-8),"mmm-yy") | G19: =TEXT(EDATE(TODAY(),-7),"mmm-yy") | H19: =TEXT(EDATE(TODAY(),-6),"mmm-yy") | I19: =TEXT(EDATE(TODAY(),-5),"mmm-yy") | J19: =TEXT(EDATE(TODAY(),-4),"mmm-yy") | K19: =TEXT(EDATE(TODAY(),-3),"mmm-yy") | L19: =TEXT(EDATE(TODAY(),-2),"mmm-yy") | M19: =TEXT(EDATE(TODAY(),-1),"mmm-yy") | N19: =TEXT(EDATE(TODAY(),0),"mmm-yy")
C20: =CUBEVALUE("ThisWorkbookDataModel","[Measures].[Gross Margin %]","[DIM_Date].[Year].&["&YEAR(EDATE(TODAY(),-11))&"]","[DIM_Date].[Month].&["&MONTH(EDATE(TODAY(),-11))&"]") | D20: =CUBEVALUE("ThisWorkbookDataModel","[Measures].[Gross Margin %]","[DIM_Date].[Year].&["&YEAR(EDATE(TODAY(),-10))&"]","[DIM_Date].[Month].&["&MONTH(EDATE(TODAY(),-10))&"]") | E20: =CUBEVALUE("ThisWorkbookDataModel","[Measures].[Gross Margin %]","[DIM_Date].[Year].&["&YEAR(EDATE(TODAY(),-9))&"]","[DIM_Date].[Month].&["&MONTH(EDATE(TODAY(),-9))&"]") | F20: =CUBEVALUE("ThisWorkbookDataModel","[Measures].[Gross Margin %]","[DIM_Date].[Year].&["&YEAR(EDATE(TODAY(),-8))&"]","[DIM_Date].[Month].&["&MONTH(EDATE(TODAY(),-8))&"]") | G20: =CUBEVALUE("ThisWorkbookDataModel","[Measures].[Gross Margin %]","[DIM_Date].[Year].&["&YEAR(EDATE(TODAY(),-7))&"]","[DIM_Date].[Month].&["&MONTH(EDATE(TODAY(),-7))&"]") | H20: =CUBEVALUE("ThisWorkbookDataModel","[Measures].[Gross Margin %]","[DIM_Date].[Year].&["&YEAR(EDATE(TODAY(),-6))&"]","[DIM_Date].[Month].&["&MONTH(EDATE(TODAY(),-6))&"]") | I20: =CUBEVALUE("ThisWorkbookDataModel","[Measures].[Gross Margin %]","[DIM_Date].[Year].&["&YEAR(EDATE(TODAY(),-5))&"]","[DIM_Date].[Month].&["&MONTH(EDATE(TODAY(),-5))&"]") | J20: =CUBEVALUE("ThisWorkbookDataModel","[Measures].[Gross Margin %]","[DIM_Date].[Year].&["&YEAR(EDATE(TODAY(),-4))&"]","[DIM_Date].[Month].&["&MONTH(EDATE(TODAY(),-4))&"]") | K20: =CUBEVALUE("ThisWorkbookDataModel","[Measures].[Gross Margin %]","[DIM_Date].[Year].&["&YEAR(EDATE(TODAY(),-3))&"]","[DIM_Date].[Month].&["&MONTH(EDATE(TODAY(),-3))&"]") | L20: =CUBEVALUE("ThisWorkbookDataModel","[Measures].[Gross Margin %]","[DIM_Date].[Year].&["&YEAR(EDATE(TODAY(),-2))&"]","[DIM_Date].[Month].&["&MONTH(EDATE(TODAY(),-2))&"]") | M20: =CUBEVALUE("ThisWorkbookDataModel","[Measures].[Gross Margin %]","[DIM_Date].[Year].&["&YEAR(EDATE(TODAY(),-1))&"]","[DIM_Date].[Month].&["&MONTH(EDATE(TODAY(),-1))&"]") | N20: =CUBEVALUE("ThisWorkbookDataModel","[Measures].[Gross Margin %]","[DIM_Date].[Year].&["&YEAR(EDATE(TODAY(),0))&"]","[DIM_Date].[Month].&["&MONTH(EDATE(TODAY(),0))&"]")
B38: MARGIN BY PRODUCT
B39: Margin by Product (Top 8 by Gross Profit) | G39: =CUBESET("ThisWorkbookDataModel","{[DIM_Product].[Title].Children}","Margin by Product (Top 8 by Gross Profit)","BDESC","[Measures].[Gross Profit]")
B40: Title | C40: Gross Profit | D40: Gross Margin %
B41: =CUBERANKEDMEMBER("ThisWorkbookDataModel",$G$39,1) | C41: =CUBEVALUE("ThisWorkbookDataModel","[Measures].[Gross Profit]",CUBERANKEDMEMBER("ThisWorkbookDataModel",$G$39,1)) | D41: =CUBEVALUE("ThisWorkbookDataModel","[Measures].[Gross Margin %]",CUBERANKEDMEMBER("ThisWorkbookDataModel",$G$39,1))
B42: =CUBERANKEDMEMBER("ThisWorkbookDataModel",$G$39,2) | C42: =CUBEVALUE("ThisWorkbookDataModel","[Measures].[Gross Profit]",CUBERANKEDMEMBER("ThisWorkbookDataModel",$G$39,2)) | D42: =CUBEVALUE("ThisWorkbookDataModel","[Measures].[Gross Margin %]",CUBERANKEDMEMBER("ThisWorkbookDataModel",$G$39,2))
B43: =CUBERANKEDMEMBER("ThisWorkbookDataModel",$G$39,3) | C43: =CUBEVALUE("ThisWorkbookDataModel","[Measures].[Gross Profit]",CUBERANKEDMEMBER("ThisWorkbookDataModel",$G$39,3)) | D43: =CUBEVALUE("ThisWorkbookDataModel","[Measures].[Gross Margin %]",CUBERANKEDMEMBER("ThisWorkbookDataModel",$G$39,3))
B44: =CUBERANKEDMEMBER("ThisWorkbookDataModel",$G$39,4) | C44: =CUBEVALUE("ThisWorkbookDataModel","[Measures].[Gross Profit]",CUBERANKEDMEMBER("ThisWorkbookDataModel",$G$39,4)) | D44: =CUBEVALUE("ThisWorkbookDataModel","[Measures].[Gross Margin %]",CUBERANKEDMEMBER("ThisWorkbookDataModel",$G$39,4))
B45: =CUBERANKEDMEMBER("ThisWorkbookDataModel",$G$39,5) | C45: =CUBEVALUE("ThisWorkbookDataModel","[Measures].[Gross Profit]",CUBERANKEDMEMBER("ThisWorkbookDataModel",$G$39,5)) | D45: =CUBEVALUE("ThisWorkbookDataModel","[Measures].[Gross Margin %]",CUBERANKEDMEMBER("ThisWorkbookDataModel",$G$39,5))
B46: =CUBERANKEDMEMBER("ThisWorkbookDataModel",$G$39,6) | C46: =CUBEVALUE("ThisWorkbookDataModel","[Measures].[Gross Profit]",CUBERANKEDMEMBER("ThisWorkbookDataModel",$G$39,6)) | D46: =CUBEVALUE("ThisWorkbookDataModel","[Measures].[Gross Margin %]",CUBERANKEDMEMBER("ThisWorkbookDataModel",$G$39,6))
B47: =CUBERANKEDMEMBER("ThisWorkbookDataModel",$G$39,7) | C47: =CUBEVALUE("ThisWorkbookDataModel","[Measures].[Gross Profit]",CUBERANKEDMEMBER("ThisWorkbookDataModel",$G$39,7)) | D47: =CUBEVALUE("ThisWorkbookDataModel","[Measures].[Gross Margin %]",CUBERANKEDMEMBER("ThisWorkbookDataModel",$G$39,7))
B48: =CUBERANKEDMEMBER("ThisWorkbookDataModel",$G$39,8) | C48: =CUBEVALUE("ThisWorkbookDataModel","[Measures].[Gross Profit]",CUBERANKEDMEMBER("ThisWorkbookDataModel",$G$39,8)) | D48: =CUBEVALUE("ThisWorkbookDataModel","[Measures].[Gross Margin %]",CUBERANKEDMEMBER("ThisWorkbookDataModel",$G$39,8))
B51: MARGIN BY COLLECTION
B52: Margin by Collection (Top 8 by Gross Profit) | G52: =CUBESET("ThisWorkbookDataModel","{[DIM_Collection].[Title].Children}","Margin by Collection (Top 8 by Gross Profit)","BDESC","[Measures].[Gross Profit]")
B53: Title | C53: Gross Profit | D53: Gross Margin %
B54: =CUBERANKEDMEMBER("ThisWorkbookDataModel",$G$52,1) | C54: =CUBEVALUE("ThisWorkbookDataModel","[Measures].[Gross Profit]",CUBERANKEDMEMBER("ThisWorkbookDataModel",$G$52,1)) | D54: =CUBEVALUE("ThisWorkbookDataModel","[Measures].[Gross Margin %]",CUBERANKEDMEMBER("ThisWorkbookDataModel",$G$52,1))
B55: =CUBERANKEDMEMBER("ThisWorkbookDataModel",$G$52,2) | C55: =CUBEVALUE("ThisWorkbookDataModel","[Measures].[Gross Profit]",CUBERANKEDMEMBER("ThisWorkbookDataModel",$G$52,2)) | D55: =CUBEVALUE("ThisWorkbookDataModel","[Measures].[Gross Margin %]",CUBERANKEDMEMBER("ThisWorkbookDataModel",$G$52,2))
B56: =CUBERANKEDMEMBER("ThisWorkbookDataModel",$G$52,3) | C56: =CUBEVALUE("ThisWorkbookDataModel","[Measures].[Gross Profit]",CUBERANKEDMEMBER("ThisWorkbookDataModel",$G$52,3)) | D56: =CUBEVALUE("ThisWorkbookDataModel","[Measures].[Gross Margin %]",CUBERANKEDMEMBER("ThisWorkbookDataModel",$G$52,3))
B57: =CUBERANKEDMEMBER("ThisWorkbookDataModel",$G$52,4) | C57: =CUBEVALUE("ThisWorkbookDataModel","[Measures].[Gross Profit]",CUBERANKEDMEMBER("ThisWorkbookDataModel",$G$52,4)) | D57: =CUBEVALUE("ThisWorkbookDataModel","[Measures].[Gross Margin %]",CUBERANKEDMEMBER("ThisWorkbookDataModel",$G$52,4))
B58: =CUBERANKEDMEMBER("ThisWorkbookDataModel",$G$52,5) | C58: =CUBEVALUE("ThisWorkbookDataModel","[Measures].[Gross Profit]",CUBERANKEDMEMBER("ThisWorkbookDataModel",$G$52,5)) | D58: =CUBEVALUE("ThisWorkbookDataModel","[Measures].[Gross Margin %]",CUBERANKEDMEMBER("ThisWorkbookDataModel",$G$52,5))
B59: =CUBERANKEDMEMBER("ThisWorkbookDataModel",$G$52,6) | C59: =CUBEVALUE("ThisWorkbookDataModel","[Measures].[Gross Profit]",CUBERANKEDMEMBER("ThisWorkbookDataModel",$G$52,6)) | D59: =CUBEVALUE("ThisWorkbookDataModel","[Measures].[Gross Margin %]",CUBERANKEDMEMBER("ThisWorkbookDataModel",$G$52,6))
B60: =CUBERANKEDMEMBER("ThisWorkbookDataModel",$G$52,7) | C60: =CUBEVALUE("ThisWorkbookDataModel","[Measures].[Gross Profit]",CUBERANKEDMEMBER("ThisWorkbookDataModel",$G$52,7)) | D60: =CUBEVALUE("ThisWorkbookDataModel","[Measures].[Gross Margin %]",CUBERANKEDMEMBER("ThisWorkbookDataModel",$G$52,7))
B61: =CUBERANKEDMEMBER("ThisWorkbookDataModel",$G$52,8) | C61: =CUBEVALUE("ThisWorkbookDataModel","[Measures].[Gross Profit]",CUBERANKEDMEMBER("ThisWorkbookDataModel",$G$52,8)) | D61: =CUBEVALUE("ThisWorkbookDataModel","[Measures].[Gross Margin %]",CUBERANKEDMEMBER("ThisWorkbookDataModel",$G$52,8))
B64: KNOWN GAPS ON THIS SHEET (documented, not silently missing)
B65: Contribution Margin %: dax/MEASURES.md doesn't define a Contribution Margin % measure — [Gross Margin %] (Net Sales less COGS) is a different, already-defined concept from Contribution Margin (Net Sales less variable costs only, excluding fixed costs), and Operating Expenses aren't split into fixed/variable in this model. Mapping this card to Gross Margin % would mislabel an existing measure as something it isn't, so it's left undocumented instead.

Sheet 10_Expenses
A1: Expenses
A2: PASSRESS MIS | Home ▸ Expenses
A3: Sheet Documentation (use the + outline control at left to expand)
A4: Purpose | B4: Complete operating-expense entry module — the manual-entry source for costs that do not come from Shopify (rent, salaries, ad spend, shipping, etc.), with category/subcategory lookups, optional SKU/Collection attribution, cost-center tagging, document references, and duplicate detection.
A5: Input tables | B5: 15_Settings lookup tables (Expense Category, Expense Subcategory, Payment Method, Currency, Cost Center), tbl_SupplierMaster (12_Suppliers), RAW_Variants / RAW_Collections (live Shopify SKUs/collections).
A6: Output tables | B6: FACT_ManualExpenses (Data Model-ready hidden mirror).
A7: Relationships | B7: Feeds the Data Model as its own fact table, kept structurally separate from Shopify-sourced facts so system-of-record vs. hand-entered data is always distinguishable. Related SKU/Collection dropdowns pull from the live Shopify RAW_ tables, not a separate manual list, so an expense can be tied to real product/collection data. Category list is fully configurable on 15_Settings — nothing is hardcoded.
A8: Future data source | B8: This IS the source — no external system. Document Management: Invoice Number/File Name/File Path/Cloud Link are references only — see passress-mis/PHASE3_DOCUMENTATION.md; a future phase may connect Cloud Link directly to OneDrive/SharePoint.
B11: EXPENSES MTD | D11: EXPENSES YTD | F11: LARGEST CATEGORY | H11: BUDGET VARIANCE
B12: N/A | D12: N/A | F12: N/A | H12: =CUBEVALUE("ThisWorkbookDataModel","[Measures].[Expense Actual vs Budget]")
B16: KNOWN GAPS ON THIS SHEET (documented, not silently missing)
B17: Expenses MTD: dax/MEASURES.md's time-intelligence pattern (§8: MTD/QTD/YTD/Previous Period/SPLY/Rolling) was only instantiated for Net Sales, Gross Profit, Net Profit, and Order Count — an 'Operating Expenses MTD' measure was never written out, though the pattern to add one is documented. Adding it is a new measure, outside this phase's reuse-only scope.
B18: Expenses YTD: Same root cause as Expenses MTD above — no YTD variant of [Operating Expenses] exists in dax/MEASURES.md or its addenda.
B19: Largest Category: Expense Category is a plain text column on FACT_ManualExpenses, not a Data Model dimension (DIM_Product/DIM_Collection/DIM_Customer/DIM_Location are — Expense Category isn't among them, per dax/README.md's relationship list) — CUBESET/CUBERANKEDMEMBER, the mechanism used everywhere else on this sheet, can only rank members of an actual dimension hierarchy.
B21: MANUAL EXPENSE ENTRY (green cells = type here — Expense ID and Possible Duplicate are automatic)
B22: Expense ID | C22: Expense Date | D22: Expense Category | E22: Expense Subcategory | F22: Supplier | G22: Amount | H22: Currency | I22: Payment Method | J22: Related Collection | K22: Related SKU | L22: Cost Center | M22: Notes | N22: Invoice Number | O22: File Name | P22: File Path | Q22: Cloud Link | R22: Possible Duplicate
B23: ="EXP-"&TEXT(ROW()-22,"00000") | C23: 2026-01-15 | D23: Rent | E23: Office | G23: 15000 | H23: EGP | I23: Bank Transfer | L23: Head Office | M23: EXAMPLE — January office rent | N23: INV-2026-0001 | O23: jan-rent.pdf | P23: /Finance/2026/Rent/ | R23: =IF(COUNTIFS(tbl_ManualExpenses[Expense Date],[@[Expense Date]],tbl_ManualExpenses[Supplier],[@Supplier],tbl_ManualExpenses[Amount],[@Amount])>1,"Possible Duplicate","")

Sheet 11_Capital
A1: Capital
A2: PASSRESS MIS | Home ▸ Capital
A3: Sheet Documentation (use the + outline control at left to expand)
A4: Purpose | B4: Tracks owner capital contributions and withdrawals, and the resulting owner-equity position.
A5: Input tables | B5: 15_Settings lookup tables (Owner, Capital Transaction Type).
A6: Output tables | B6: FACT_CapitalTransactions (Data Model-ready hidden mirror).
A7: Relationships | B7: The only source that grows/shrinks Capital Invested and Owner Equity in future financial calculations. Owner and Transaction Type are both configurable lookups on 15_Settings, not hardcoded.
A8: Future data source | B8: This IS the source — no external system. Manual entry only.
B11: CAPITAL INVESTED | D11: OWNER WITHDRAWALS | F11: NET OWNER EQUITY | H11: YTD MOVEMENT
B12: =CUBEVALUE("ThisWorkbookDataModel","[Measures].[Capital Invested (Cumulative)]") | D12: =CUBEVALUE("ThisWorkbookDataModel","[Measures].[Capital Withdrawals (Period)]") | F12: =CUBEVALUE("ThisWorkbookDataModel","[Measures].[Equity]") | H12: N/A
B16: KNOWN GAPS ON THIS SHEET (documented, not silently missing)
B17: YTD Movement: dax/MEASURES.md defines [Net Capital (Period)] and [Capital Invested (Cumulative)] (all-time, since inception) but no YTD-specific variant — the §8 time-intelligence pattern (TOTALYTD, etc.) was only instantiated for Net Sales/Gross Profit/Net Profit/Order Count, not Net Capital. Adding a 'Net Capital YTD' measure is outside this phase's reuse-only scope.
B19: CAPITAL TRANSACTIONS (green cells = type here — Capital ID and Possible Duplicate are automatic)
B20: Capital ID | C20: Date | D20: Owner | E20: Transaction Type | F20: Amount | G20: Notes | H20: Entered By | I20: Possible Duplicate
B21: ="CAP-"&TEXT(ROW()-20,"00000") | C21: 2026-01-01 | D21: Founder | E21: Capital Contribution | F21: 50000 | G21: EXAMPLE — founder capital injection | H21: Founder | I21: =IF(COUNTIFS(tbl_CapitalTransactions[Date],[@Date],tbl_CapitalTransactions[Owner],[@Owner],tbl_CapitalTransactions[Amount],[@Amount])>1,"Possible Duplicate","")

Sheet 12_Suppliers
A1: Suppliers
A2: PASSRESS MIS | Home ▸ Suppliers
A3: Sheet Documentation (use the + outline control at left to expand)
A4: Purpose | B4: Supplier master data and the complete purchasing engine: Purchase Order Header, Purchase Order Lines, and Goods Receipt, with a Draft-through-Closed status workflow.
A5: Input tables | B5: 15_Settings lookup tables (Supplier Type, Supplier Status, Currency, PO Status, Warehouse), RAW_Variants (live Shopify SKUs).
A6: Output tables | B6: DIM_Supplier, FACT_PurchaseOrderHeader, FACT_PurchaseOrderLines, FACT_GoodsReceipt (Data Model-ready hidden mirrors).
A7: Relationships | B7: PO Lines and Goods Receipt both key on PO Number (from PO Header) and SKU (from the live Shopify variant list), not a separate manual product list. Goods Receipt's Remaining Quantity and Variance from PO are computed by looking up PO Lines for the same PO Number + SKU.
A8: Future data source | B8: This IS the source today. Candidate for supplier-portal or accounting-system integration later (see Future Integrations in the Phase 0 architecture).
B11: ACTIVE SUPPLIERS | D11: OPEN POS | F11: PURCHASES YTD | H11: OUTSTANDING RECEIPTS
B12: =COUNTIFS(tbl_SupplierMaster[Status],"Active") | D12: =COUNTIFS(tbl_POHeader[Status],"<>Closed",tbl_POHeader[Status],"<>Cancelled") | F12: N/A | H12: =SUM(tbl_GoodsReceipt[Remaining Quantity])
B16: KNOWN GAPS ON THIS SHEET (documented, not silently missing)
B17: Purchases YTD: dax/MEASURES.md defines [Cash Paid for Purchases] (period-aggregate, driven by whatever filter context a report provides) but no YTD-specific variant — the §8 time-intelligence pattern was only instantiated for Net Sales/Gross Profit/Net Profit/Order Count. A worksheet SUMIFS reimplementing a Jan-1-to-today window against tbl_GoodsReceipt directly would be new logic, not a reuse of an existing formula or measure, so it wasn't added.
B19: SUPPLIER MASTER (green cells = type here — Supplier ID is automatic)
B20: Supplier ID | C20: Supplier Name | D20: Supplier Type | E20: Contact Person | F20: Phone | G20: Email | H20: Currency | I20: Payment Terms | J20: Status | K20: Notes
B21: ="SUP-"&TEXT(ROW()-20,"00000") | C21: EXAMPLE — ABC Textiles | D21: Fabric | E21: Mona Ahmed | F21: +20 100 000 0000 | G21: contact@example.com | H21: EGP | I21: Net 30 | J21: Active
B24: PURCHASE ORDER HEADER (green cells = type here — PO Number is automatic)
B25: PO Number | C25: Supplier | D25: Order Date | E25: Expected Delivery Date | F25: Status | G25: Currency | H25: Notes
B26: ="PO-"&TEXT(ROW()-25,"00000") | C26: EXAMPLE — ABC Textiles | D26: 2026-01-10 | E26: 2026-01-24 | F26: Draft | G26: EGP
B29: PURCHASE ORDER LINES (green cells = type here — Total Cost is automatic)
B30: PO Number | C30: SKU | D30: Quantity Ordered | E30: Unit Cost | F30: Total Cost
D31: 50 | E31: 120 | F31: =[@[Quantity Ordered]]*[@[Unit Cost]]
B34: GOODS RECEIPT (green cells = type here — Remaining Quantity and Variance from PO are automatic)
B35: PO Number | C35: SKU | D35: Goods Received Date | E35: Quantity Received | F35: Remaining Quantity | G35: Actual Unit Cost | H35: Variance from PO | I35: Warehouse | J35: Receiver
D36: 2026-01-20 | E36: 30 | F36: =SUMIFS(tbl_POLines[Quantity Ordered],tbl_POLines[PO Number],[@[PO Number]],tbl_POLines[SKU],[@SKU])-SUMIFS(tbl_GoodsReceipt[Quantity Received],tbl_GoodsReceipt[PO Number],[@[PO Number]],tbl_GoodsReceipt[SKU],[@SKU]) | G36: 122 | H36: =[@[Actual Unit Cost]]-SUMIFS(tbl_POLines[Unit Cost],tbl_POLines[PO Number],[@[PO Number]],tbl_POLines[SKU],[@SKU]) | I36: Main Warehouse

Sheet 13_Marketing
A1: Marketing
A2: PASSRESS MIS | Home ▸ Marketing
A3: Sheet Documentation (use the + outline control at left to expand)
A4: Purpose | B4: Campaign and discount-code performance tracking; future home for ad-spend ROAS once integrated.
A5: Input tables | B5: DIM_Collection, FACT_OrderLines (discount amounts). Future: FACT_MarketingSpend.
A6: Output tables | B6: Marketing KPI row, Discount Trend chart. Campaign Performance / Discount Code Usage remain undocumented gaps (no Campaign dimension in the Data Model).
A7: Relationships | B7: FACT_OrderLines[DiscountAmount] rolls up via the existing [Discounts] measure.
A8: Future data source | B8: Live now: Total Discount Given / Discount Trend read dax/MEASURES.md's [Discounts] directly. Meta/TikTok Ads API — future integration, still not connected (Marketing-Ready Layer, Phase 5).
B11: TOTAL DISCOUNT GIVEN | D11: ACTIVE CAMPAIGNS | F11: DISCOUNT RATE % | H11: ROAS (FUTURE)
B12: =CUBEVALUE("ThisWorkbookDataModel","[Measures].[Discounts]") | D12: N/A | F12: N/A | H12: N/A
B16: DISCOUNT TREND
B17: Discounts — trailing 12 months
C18: =TEXT(EDATE(TODAY(),-11),"mmm-yy") | D18: =TEXT(EDATE(TODAY(),-10),"mmm-yy") | E18: =TEXT(EDATE(TODAY(),-9),"mmm-yy") | F18: =TEXT(EDATE(TODAY(),-8),"mmm-yy") | G18: =TEXT(EDATE(TODAY(),-7),"mmm-yy") | H18: =TEXT(EDATE(TODAY(),-6),"mmm-yy") | I18: =TEXT(EDATE(TODAY(),-5),"mmm-yy") | J18: =TEXT(EDATE(TODAY(),-4),"mmm-yy") | K18: =TEXT(EDATE(TODAY(),-3),"mmm-yy") | L18: =TEXT(EDATE(TODAY(),-2),"mmm-yy") | M18: =TEXT(EDATE(TODAY(),-1),"mmm-yy") | N18: =TEXT(EDATE(TODAY(),0),"mmm-yy")
C19: =CUBEVALUE("ThisWorkbookDataModel","[Measures].[Discounts]","[DIM_Date].[Year].&["&YEAR(EDATE(TODAY(),-11))&"]","[DIM_Date].[Month].&["&MONTH(EDATE(TODAY(),-11))&"]") | D19: =CUBEVALUE("ThisWorkbookDataModel","[Measures].[Discounts]","[DIM_Date].[Year].&["&YEAR(EDATE(TODAY(),-10))&"]","[DIM_Date].[Month].&["&MONTH(EDATE(TODAY(),-10))&"]") | E19: =CUBEVALUE("ThisWorkbookDataModel","[Measures].[Discounts]","[DIM_Date].[Year].&["&YEAR(EDATE(TODAY(),-9))&"]","[DIM_Date].[Month].&["&MONTH(EDATE(TODAY(),-9))&"]") | F19: =CUBEVALUE("ThisWorkbookDataModel","[Measures].[Discounts]","[DIM_Date].[Year].&["&YEAR(EDATE(TODAY(),-8))&"]","[DIM_Date].[Month].&["&MONTH(EDATE(TODAY(),-8))&"]") | G19: =CUBEVALUE("ThisWorkbookDataModel","[Measures].[Discounts]","[DIM_Date].[Year].&["&YEAR(EDATE(TODAY(),-7))&"]","[DIM_Date].[Month].&["&MONTH(EDATE(TODAY(),-7))&"]") | H19: =CUBEVALUE("ThisWorkbookDataModel","[Measures].[Discounts]","[DIM_Date].[Year].&["&YEAR(EDATE(TODAY(),-6))&"]","[DIM_Date].[Month].&["&MONTH(EDATE(TODAY(),-6))&"]") | I19: =CUBEVALUE("ThisWorkbookDataModel","[Measures].[Discounts]","[DIM_Date].[Year].&["&YEAR(EDATE(TODAY(),-5))&"]","[DIM_Date].[Month].&["&MONTH(EDATE(TODAY(),-5))&"]") | J19: =CUBEVALUE("ThisWorkbookDataModel","[Measures].[Discounts]","[DIM_Date].[Year].&["&YEAR(EDATE(TODAY(),-4))&"]","[DIM_Date].[Month].&["&MONTH(EDATE(TODAY(),-4))&"]") | K19: =CUBEVALUE("ThisWorkbookDataModel","[Measures].[Discounts]","[DIM_Date].[Year].&["&YEAR(EDATE(TODAY(),-3))&"]","[DIM_Date].[Month].&["&MONTH(EDATE(TODAY(),-3))&"]") | L19: =CUBEVALUE("ThisWorkbookDataModel","[Measures].[Discounts]","[DIM_Date].[Year].&["&YEAR(EDATE(TODAY(),-2))&"]","[DIM_Date].[Month].&["&MONTH(EDATE(TODAY(),-2))&"]") | M19: =CUBEVALUE("ThisWorkbookDataModel","[Measures].[Discounts]","[DIM_Date].[Year].&["&YEAR(EDATE(TODAY(),-1))&"]","[DIM_Date].[Month].&["&MONTH(EDATE(TODAY(),-1))&"]") | N19: =CUBEVALUE("ThisWorkbookDataModel","[Measures].[Discounts]","[DIM_Date].[Year].&["&YEAR(EDATE(TODAY(),0))&"]","[DIM_Date].[Month].&["&MONTH(EDATE(TODAY(),0))&"]")
B37: CAMPAIGN PERFORMANCE / DISCOUNT CODE USAGE
B38: [ Campaign Performance (PivotTable) / Discount Code Usage (PivotTable) — Not implementable: No Campaign dimension exists (Active Campaigns' reason above applies identically). Discount Code Usage specifically: RAW_Discounts (Power Query staging) holds discount-code data, but it was never built into the star schema in Phase 4 — no DIM_/FACT_ table, no Data Model relationship, no DAX measure reads it. It's real, wired data (once Power Query is set up) but not reachable from the Data Model this sheet's other cards depend on. ]
B43: ↓ Drill into Discounts
B45: KNOWN GAPS ON THIS SHEET (documented, not silently missing)
B46: Active Campaigns: No Campaign dimension exists in the Data Model — the Marketing-Ready Layer (RAW_MetaAds/RAW_GoogleAds/etc., FACT_MarketingSpend) is reserved but deliberately not connected (no API wired, per Phase 5's explicit scope), so there's no campaign data to count.
B47: Discount Rate %: No DAX measure defines a discount-rate ratio — [Discounts] and [Gross Sales] both exist individually, but DIVIDE([Discounts],[Gross Sales]) as a named, reusable measure isn't in dax/MEASURES.md or its addenda. Adding one would be a new measure outside this phase's reuse-only scope, even though both inputs it would combine already exist.
B48: ROAS (future): Documented as a future metric since this card's own label was written (Phase 1) — ROAS needs ad spend data from the unconnected Marketing-Ready Layer, same root cause as Active Campaigns above. dax/PHASE5_MEASURES_ADDENDUM.md's KPI Targets section states this explicitly: the target is ready and editable, there's no Actual to compare it against yet.

Sheet 14_Data_Quality
A1: Data Quality
A2: PASSRESS MIS | Home ▸ Data Quality
A3: Sheet Documentation (use the + outline control at left to expand)
A4: Purpose | B4: Monitors refresh health, row counts, and validation checks so data problems surface immediately instead of silently propagating into dashboards.
A5: Input tables | B5: LOG_RefreshHistory, LOG_DataQuality.
A6: Output tables | B6: Refresh Status Summary, Validation Rules.
A7: Relationships | B7: Reads directly from the two hidden LOG_ sheets — this is their human-facing display, not a separate data source.
A8: Future data source | B8: LOG_RefreshHistory / LOG_DataQuality, populated by Power Query refresh events — Phase 2.
B11: LAST REFRESH | D11: ROWS LOADED | F11: ERRORS FOUND | H11: DATA FRESHNESS
B12: =IFERROR(TEXT(MAX(tbl_LOG_RefreshHistory[Timestamp]),"dd-mmm hh:mm"),"—") | D12: =IFERROR(SUM(tbl_LOG_RefreshHistory[RowsLoaded]),"—") | F12: =IFERROR(COUNTIF(tbl_LOG_DataQuality[Status],"WARNING*"),"—") | H12: =IFERROR(TODAY()-INT(MAX(tbl_LOG_RefreshHistory[Timestamp])),"—")
B16: VALIDATION RULES (orange cells = configurable)
B17: Rule ID | C17: Check Name | D17: Applies To | E17: Threshold
B18: DQ-001 | C18: No orders older than lookback window missing | D18: RAW_Orders | E18: 0 gaps
B21: REFRESH STATUS SUMMARY (calculated — Phase 2)
B22: Table | C22: Last Refreshed | D22: Row Count | E22: Status
B26: DATA QUALITY CHECKS
B27: Check Name | C27: Metric | D27: Result | E27: Status | F27: Notes
B28: Missing SKU | C28: RAW_Variants rows with a blank SKU | D28: =COUNTIFS(tbl_RAW_Variants[SKU],"") | E28: =IF(D28=0,"PASS","REVIEW") | F28: Reused from Alerts (ALT-04) — same check, not recomputed differently here.
B29: Missing Cost | C29: Order lines with no matching Product Cost Master row | D29: =CUBEVALUE("ThisWorkbookDataModel","[Measures].[Lines Missing Cost]") | E29: =IF(D29=0,"PASS","REVIEW") | F29: Reused from dax/MEASURES.md's [Lines Missing Cost] — same measure Alerts (ALT-03) reads.
B30: Missing Supplier | C30: SKUs with no PrimarySupplierID (DIM_Product) | D30: =COUNTIFS(tbl_DIM_Product[PrimarySupplierID],"") | E30: =IF(D30=0,"PASS","REVIEW") | F30: PrimarySupplierID is best-effort (most recent Goods Receipt per SKU) — see DIM_Product.pq. A count here is expected for never-received SKUs, not necessarily an error. Uses tbl_DIM_Product (the placeholder name): DIM_/FACT_ tables go through the exact same Phase-1-placeholder-until-wired lifecycle as RAW_/LOG_ tables (dax/README.md Step 1) — DIM_Product with no prefix doesn't exist until the Data Model is built, same root cause as the RAW_/LOG_ fix above.
B31: Duplicate Orders | C31: OrderIDs appearing more than once in RAW_Orders | D31: =SUMPRODUCT((COUNTIF(tbl_RAW_Orders[OrderID],tbl_RAW_Orders[OrderID])>1)*1) | E31: =IF(D31=0,"PASS","REVIEW") | F31: Should always be 0 — Shopify order IDs are unique. A nonzero count means the Power Query refresh appended duplicate rows; check RAW_Orders.pq's incremental-window logic first.
B32: Duplicate Expenses | C32: Manual Expenses flagged Possible Duplicate | D32: =COUNTIF(tbl_ManualExpenses[Possible Duplicate],"Possible Duplicate") | E32: =IF(D32=0,"PASS","REVIEW") | F32: Reused from Alerts (ALT-06) and Phase 3's own duplicate-flag column — not recomputed.
B33: Products without Collection | C33: RAW_Products rows with blank CollectionIDs | D33: =COUNTIFS(tbl_RAW_Products[CollectionIDs],"") | E33: =IF(D33=0,"PASS","REVIEW")
B34: Products without Images | C34: N/A — not computable with current data | D34: ="N/A" | E34: ="N/A" | F34: RAW_Products.pq never fetched image data (not in Phase 2's original scope, and Phase 6 must not modify Phase 2's files) — adding an `images` field to that GraphQL query is a clean, isolated future addition, not a Phase 6 change.
B35: Negative Inventory | C35: RAW_InventoryLevels rows with Available < 0 | D35: =COUNTIFS(tbl_RAW_InventoryLevels[Available],"<0") | E35: =IF(D35=0,"PASS","REVIEW") | F35: Should always be 0 — a negative available count usually signals an oversell or an inventory-sync issue in Shopify itself, not a workbook bug.
B36: Missing Customer | C36: RAW_Orders rows with a blank CustomerID | D36: =COUNTIFS(tbl_RAW_Orders[CustomerID],"") | E36: =IF(D36=0,"PASS","REVIEW") | F36: Expected to be nonzero for legitimate guest checkouts — a HIGH count relative to total orders is the actual signal worth investigating, not any nonzero count.
B37: Missing Payment | C37: Orders in RAW_Orders with no matching transaction in RAW_Transactions | D37: =SUMPRODUCT((COUNTIF(tbl_RAW_Transactions[OrderID],tbl_RAW_Orders[OrderID])=0)*1) | E37: =IF(D37=0,"PASS","REVIEW") | F37: An anti-join count — orders that exist but have zero associated payment transactions. Should be near 0 for a store where checkout = payment.
B38: Refresh Failures | C38: Refreshes with an error condition (from LOG_DataQuality) | D38: =COUNTIF(tbl_LOG_DataQuality[Status],"WARNING*") | E38: =IF(D38=0,"PASS","REVIEW") | F38: Reused from Alerts (ALT-11) — same LOG_DataQuality check, not recomputed.
B40: Overall Data Quality % | C40: =COUNTIF(E28:E38,"PASS")/(COUNTA(E28:E38)-COUNTIF(E28:E38,"N/A"))
B42: HISTORICAL REFRESH TREND (Rows Loaded per refresh, from LOG_RefreshHistory)

Sheet 15_Settings
A1: Settings
A2: PASSRESS MIS | Home ▸ Settings
A3: Sheet Documentation (use the + outline control at left to expand)
A4: Purpose | B4: Central control panel — every configurable parameter the rest of the workbook depends on. The single place non-technical changes should be made.
A5: Input tables | B5: None — this sheet is the input.
A6: Output tables | B6: DIM_Parameters (disconnected DAX table mirrors these values), Power Query parameters (Phase 2), Chart of Accounts mapping used by 08_Finance/09_Profitability.
A7: Relationships | B7: Every Power Query parameter and every DAX measure that needs a configurable constant reads from here — never hardcoded elsewhere.
A8: Future data source | B8: This IS the source. No external system.
B11: GENERAL SETTINGS (orange cells = configurable)
B12: Parameter | C12: Value | D12: Description
B13: Company Name | C13: Passress | D13: Legal/trading name shown across dashboards.
B14: Base Currency | C14: EGP | D14: Currency all imported Shopify data is stored in.
B15: Reporting Currency | C15: EGP | D15: Currency used for dashboard display. Phase 1: same as base.
B16: Fiscal Year Start Month | C16: January | D16: First month of fiscal year, used for YTD/FY calculations.
B17: Default VAT Rate | C17: 14% | D17: Egypt standard VAT — used for tax reconciliation.
B18: Target Gross Margin % | C18: 55% | D18: Benchmark used for profitability flags (Phase 3).
B21: SHOPIFY CONNECTION SETTINGS (fill in Store Domain to go live; token is never stored here)
B22: Parameter | C22: Value | D22: Description
B23: Shopify Store Domain | C23: your-store.myshopify.com | D23: Set this to your real *.myshopify.com domain to go live. The access token itself is never stored in this workbook — see power-query/README.md.
B24: Shopify API Version | C24: 2025-01 | D24: Admin GraphQL API version pinned for Power Query — reviewed twice a year.
B25: Lookback Days (Incremental Refresh) | C25: 7 | D25: Rolling re-check window: days of history re-pulled on every refresh so late-updated records are never missed.
B26: Historical Backfill Start Date | C26: 2024-01-01 | D26: Earliest date fetched on a first-ever run (empty staging table). Ignored once a table has data — Lookback Days takes over.
B27: Max Pages Per Refresh (Safety Cap) | C27: 500 | D27: Hard stop on pagination per query per refresh (500 pages x 250 records ≈ 125,000 rows), so a misconfigured filter can't run away.
B30: CHART OF ACCOUNTS MAPPING (orange cells = configurable)
B31: Account Code | C31: Account Name | D31: Statement | E31: P&L / BS Line | F31: Source
B32: 4000 | C32: EXAMPLE — Net Sales | D32: P&L | E32: Revenue | F32: FACT_OrderLines
B35: WORKBOOK VERSION LOG (system-maintained — every phase appends a row here)
B36: Version | C36: Date | D36: Phase | E36: Summary
B37: 1.0 | C37: 2026-07-26 | D37: Phase 1 — Workbook Foundation | E37: Structure, tables, named ranges, documentation. No live data, no calculations.
B38: 1.1 | C38: 2026-07-26 | D38: Phase 1 Finalization | E38: 01_Home's Workbook Version / Phase Completed KPI cards now read this table's last row live via formula — every future phase appends a row here and Home updates automatically.
B39: 2.0 | C39: 2026-07-26 | D39: Phase 2 — Shopify GraphQL Ingestion Layer | E39: Complete Power Query M layer: authentication (Extension.CurrentCredential, no hardcoded tokens), automatic cursor pagination, incremental refresh, HTTP/GraphQL error handling with backoff. Covers Products, Variants, Orders, Order Lines, Customers, Collections, Inventory Levels, Transactions, Refunds, Discounts — read-only (GraphQL query operations only). Added RAW_Transactions and RAW_Discounts staging sheets; revised RAW_Refunds and RAW_InventoryLevels to match verified Shopify Admin API schema. See /passress-mis/power-query/README.md and DOCUMENTATION.md. No dashboards yet.
B40: 3.0 | C40: 2026-07-26 | D40: Phase 3 — Business Master Data & Manual-Entry Engine | E40: Product Cost Master with historical/versioned costing (05_Products). Complete Manual Expenses module: category/subcategory lookups, duplicate-flag column, document references (10_Expenses). Capital module (11_Capital). Expanded Supplier Master + full Purchase Order engine — Header/Lines/Goods Receipt with a Draft-to-Closed status workflow (12_Suppliers). Every dropdown sourced from an editable lookup table on 15_Settings — no hardcoded values — with input prompts and stop-on-error messages. SKU/Collection dropdowns reference the live Shopify RAW_ tables, not a separate manual list. New hidden Data-Model-ready mirrors: DIM_Supplier, DIM_ProductCostHistory, FACT_CapitalTransactions, FACT_PurchaseOrderHeader, FACT_PurchaseOrderLines, FACT_GoodsReceipt. See /passress-mis/PHASE3_DOCUMENTATION.md. Still no dashboards, PivotTables, DAX, or financial statements.
B41: 4.0 | C41: 2026-07-26 | D41: Phase 4 — Financial Calculation Engine (Data Model + DAX) | E41: Completed the RAW_/manual-table -> star-schema transformation layer Phase 1 sketched but Phase 2-3 left empty (power-query/star-schema/, 18 M files): DIM_Date (generated calendar, fiscal-year aware), DIM_Product/Customer/Location/Collection/Supplier/ProductCostHistory, and every FACT_ table, including historically-correct COGS resolved per order line via fn_GetEffectiveCost (SKU + order date -> the Product Cost Master row active on that date, never today's cost). Full DAX measure library (dax/MEASURES.md): P&L, Balance Sheet, Cash Flow, Product Profitability, Customer Metrics (incl. cohorts), Inventory Metrics, Executive KPIs, and a full time-intelligence layer (MTD/QTD/YTD/previous period/SPLY/rolling 30-90-365) applied to the headline measures with the reusable pattern documented for extending to any other. Built as composable base measures referenced by name from composite ones — no duplicated calculations. Reconciliation section validates Balance Sheet (Assets=Liabilities+Equity), Cash Position (direct vs. indirect), Net Sales (FACT vs. RAW Shopify totals), and refund/cost-coverage integrity. Accounts Payable is a documented proxy (no payment-status field exists yet — flagged, not silently assumed). See /passress-mis/dax/README.md and MEASURES.md. Still no dashboards, PivotTables, PivotCharts, or KPI cards.
B42: 5.0 | C42: 2026-07-26 | D42: Phase 5 — BI Application Layer (Dashboards, Insights, Alerts, Budget, Forecast) | E42: 02_Partner_Dashboard and 03_CEO_Dashboard rebuilt with real content: live KPI cards, a 12-month trend chart, and a Top-5-products list, all built with CUBEVALUE/CUBESET/CUBERANKEDMEMBER formulas reading the Data Model directly — no PivotTable required, so these resolve for real once the Data Model is wired, not just placeholders. BI_Insights and BI_Alerts (new hidden BI_ sheets): CUBEVALUE-driven auto-generated business insights and operational alerts, reusing Phase 2-4's own data-quality/reconciliation logic rather than duplicating it. BI_Forecast: rolling linear-trend forecasts (Excel's native FORECAST.LINEAR) for Sales/Expenses/Profit/Inventory/Cash, with an explicit Method column so a future AI forecasting layer is a swap-in, not a redesign. KPI Targets (15_Settings) and a yearly/monthly Budget module (08_Finance) with Actual-vs-Target and Actual/Forecast-vs-Budget DAX measures (dax/PHASE5_MEASURES_ADDENDUM.md, additive to Phase 4's MEASURES.md). Marketing-Ready Layer: 6 reserved, unconnected RAW_ tables (Meta/Google Analytics/Google Ads/TikTok/Email/Influencer) plus FACT_MarketingSpend, matching Phase 1's original placeholder pattern. FUTURE_AI_Insights: a reserved, unimplemented inventory of future AI features. Every dashboard now has a clickable breadcrumb back to 01_Home (title_bar's Home link). Global Filters panel (01_Home) prepares named filter cells for future slicer-equivalent filtering; native Excel Slicers still need real PivotTables (Phase 6) to attach to. Dashboards are landscape, fit-to-width, print-area-scoped for clean PDF export. See /passress-mis/PHASE5_DOCUMENTATION.md.
B43: 6.0 | C43: 2026-07-26 | D43: Phase 6 — Operational Excellence, Automation, Auditability, Production Readiness | E43: RPT_ExecutiveBrief (new hidden sheet, linked from 01_Home): one-page A4-printable daily brief — today's Revenue/Orders/Gross Profit/Margin, Cash Position, Inventory Value, Revenue vs Yesterday, Top 5 Products/Collections, Critical Alerts, Business Health Score, Executive Commentary — also serves as the Automated Daily Report (print-ready from the start, no separate duplicate sheet). BI_HealthScore: the master 0-100 Business Health Score, 10 weighted components (weights editable on 15_Settings' new tbl_HealthScoreWeights), Red/Amber/Green status. 14_Data_Quality expanded with 11 checks (Missing SKU/Cost/Supplier, Duplicate Orders/Expenses, Products without Collection/Images, Negative Inventory, Missing Customer/Payment, Refresh Failures — Products without Images marked N/A, honestly, since RAW_Products.pq was never extended to fetch image data and Phase 6 must not modify Phase 2), an Overall Data Quality % (named range, reused by the Health Score), and a Historical Refresh Trend chart. RPT_Workflow (new hidden sheet): Purchase Orders/Open Orders/Pending Receipts/Inventory to Receive/Supplier Status/Capital Remaining/Outstanding Expenses/Monthly Purchasing — reuses existing measures under workflow-specific labels rather than inventing new ones. DIM_Date.pq extended (additively — every existing column unchanged) with IsWorkingDay/IsHoliday/HolidayName, reading a new empty-by-default Holidays table (15_Settings) — MTD/QTD/YTD/Rolling 12/Previous Year/SPLY needed no new columns, already fully covered by Phase 4's time intelligence. Drill-through hyperlinks added from Partner/CEO Dashboard KPI sections to their detail sheets (04_Sales/06_Customers/07_Inventory/09_Profitability/10_Expenses) — link-based navigation, not true OLAP drill-through, which needs real PivotTables (Phase 7+). PRODUCTION READINESS REVIEW found and fixed 5 real bugs: SKUList/CollectionTitleList named ranges and 3 Phase 5 Alert formulas referenced Phase 1's placeholder table names (tbl_RAW_Variants, tbl_LOG_RefreshHistory, tbl_LOG_DataQuality) instead of the permanent post-Power-Query-wiring names (RAW_Variants, LOG_RefreshHistory, LOG_DataQuality) — every DAX measure already used the correct convention; only these 5 worksheet-formula references were wrong, now fixed. Full findings in /passress-mis/PHASE6_PRODUCTION_READINESS_REVIEW.md; what's new in /passress-mis/PHASE6_DOCUMENTATION.md.
B44: 7.0 | C44: 2026-07-26 | D44: Phase 7 — Production Readiness Certification | E44: Full line-by-line review of build_workbook.py, every Power Query shared function, a representative cross-section of staging/star-schema queries, and the complete DAX measure library, against explicit correctness/performance/security criteria. Found and fixed 5 real defects: BI_Alerts ALT-10's stray placeholder-token formula (simplified, no functional change but removed a maintenance trap); 14_Data_Quality's Historical Refresh Trend chart was off-by-one, silently dropping the first logged refresh; BI_Insights' INS-06/INS-07 (Best/Weakest seller) called CUBERANKEDMEMBER against an unordered, unranked MDX set, so both insights always showed the identical arbitrary product instead of true sales-ranked results — fixed with proper CUBESET-backed ranking (BDESC/BASC by Net Sales), the same pattern used everywhere else in the workbook; 01_Home's and 14_Data_Quality's Last Refresh/Data Quality/Rows Loaded/Errors Found KPI cards were left as static Phase 1 placeholders despite their own doc_block promising live LOG_ data — wired to existing LOG_RefreshHistory/LOG_DataQuality/OverallDataQualityPct sources, no new measures. Also corrected the now-inaccurate 'Placeholder, built in Phase 4' label on 04_Sales/06_Customers/07_Inventory/09_Profitability/13_Marketing/05_Products/08_Finance's still-unbuilt generic dashboard chart/PivotTable placeholders — deliberately left unbuilt (never commissioned by any phase's brief, and wiring their KPI cards would require inventing new DAX measures outside this phase's 'no new features' scope) but the stale phase-attribution text was actively misleading and is now accurate. Four new documentation deliverables: DEPLOYMENT_GUIDE.md, OPERATIONS_MANUAL.md, TECHNICAL_DOCUMENTATION.md, and PHASE7_FINAL_ARCHITECTURE_REVIEW.md (technical debt, performance/security review, SQL Server + Power BI migration path). No architecture changes, no new dashboards or modules — additive fixes and documentation only, per this phase's explicit scope.
B45: 8.0 | C45: 2026-07-26 | D45: Phase 8 — Placeholder Completion (Reuse-Only) | E45: Completed every remaining placeholder KPI card, chart, and 'PivotTable' substitute that could be built from the existing Power Query layer, Data Model, and DAX measure library — architecture frozen, no new measures, no new KPIs, no new dashboards, per this phase's explicit scope. 04_Sales/05_Products/06_Customers/07_Inventory/08_Finance/09_Profitability/13_Marketing rebuilt: 20 of 28 KPI cards wired to existing measures, 6 new native charts (Sales/Stock/Margin/Discount trends, a 3-series P&L Trend, a Top-10-Products bar chart), 12 CUBE-function breakdown tables standing in for a PivotTable (Sales/Margin by Product/Collection, Stock by Location, Top Customers, Geography, etc. — a new add_cube_breakdown_table helper generalizing Phase 5's add_cube_top_n to multiple measure columns, same underlying mechanism), P&L Statement and Cash Flow Statement built directly from dax/MEASURES.md §1/§3's own documented measure maps. 10_Expenses/11_Capital/12_Suppliers' own unwired KPI cards (missed by Phase 7's sweep, caught in this phase's fuller scan) also completed — 6 of 12 wired, 3 of them reusing RPT_Workflow's own existing formulas verbatim. Order List and Variant Detail (row-level detail no CUBE function can produce) linked directly to RAW_Orders/DIM_Product instead of left blank. Every remaining gap (13 KPI cards, 4 chart/pivot items) is left as a visible, specific 'Not implementable: <reason>' note in the workbook itself, not just in documentation — no existing measure covers the concept, no Data Model dimension exists for the breakdown, the data is row-level and can't be produced by a CUBE function, or (Customer Cohorts alone) the underlying data exists but a true 2D matrix needs an execution-untestable nested-MDX pattern. Full inventory in /passress-mis/PHASE8_DOCUMENTATION.md. Second full scan after all fixes: 0 static placeholder cells, 0 generic placeholder boxes remaining, all structural validation clean.
B46: 9.0 | C46: 2026-07-26 | D46: Phase 9 — File-Corruption Hotfix (Real-World Test Finding) | E46: Triggered by the first real Windows Excel open of this workbook, which required a repair just to load ('Removed Records: Named range from workbook.xml' + 'Formula from sheet5/10/12.xml' — confirmed via workbook.xml.rels to be 05_Products/10_Expenses/12_Suppliers, the three sheets sourcing SKU/Collection dropdowns from SKUList/CollectionTitleList). Root cause: those two named ranges (and several worksheet formulas in BI_Alerts, 14_Data_Quality, RPT_Workflow, 01_Home added in Phases 6-8) pointed at the POST-WIRING table name (RAW_Variants, LOG_DataQuality, etc.) rather than the always-present tbl_-prefixed placeholder — a Phase 6 design choice that assumed an unresolved reference would simply show a formula error until Power Query is wired. A real Excel open proved otherwise: a workbook-scoped defined name referencing a table that doesn't exist ANYWHERE in the file is structurally invalid at load time, not just unresolved at calculation time, so Excel strips the name and every Data Validation dropdown depending on it, forcing a file repair. Reverted every affected named range and worksheet formula back to the tbl_-prefixed placeholder name (DAX measures untouched — they read the Data Model, not Excel Table objects, so were never affected). A second, related finding from the same stricter validation: 14_Data_Quality's Missing Supplier check referenced DIM_Product directly, and DIM_/FACT_ tables go through the identical placeholder-until-wired lifecycle as RAW_/LOG_ (dax/README.md Step 1) — fixed to tbl_DIM_Product. Added a permanent build-time check verifying every defined name and every Table[Column] formula reference resolves to a table that actually exists in the generated file — 0 issues found after the fix (previously no such check existed; bracket-balance/XML-well-formedness checks don't catch a semantically invalid table reference). New required manual step added to DEPLOYMENT_GUIDE.md §5.4: rename SKUList/CollectionTitleList via Name Manager to drop the tbl_ prefix once RAW_Variants/RAW_Collections are actually wired — documented as a one-time, unmissable step rather than left to be silently forgotten. Full findings in /passress-mis/PHASE9_DOCUMENTATION.md; PHASE6_PRODUCTION_READINESS_REVIEW.md's original (superseded) fix table annotated, not rewritten.
B47: 9.1 | C47: 2026-07-26 | D47: Phase 9 Addendum — Chart Category Type Fix | E47: A repair prompt was still reported after 9.0's fix, on a fresh Desktop Excel open. Investigated by reading the generated chart XML directly (LibreOffice was tried as an independent second validator but is unusable in this build environment — fails to load even a trivial one-cell test workbook, an environment limitation unrelated to this file). Finding: all 9 charts have text-valued category axes (month labels from a TEXT() formula, or product/customer names from CUBERANKEDMEMBER) but openpyxl's Chart.set_categories() unconditionally writes a numeric reference (<c:numRef>) regardless of the referenced cells' actual content — confirmed by reading openpyxl's own source. Present since the charting pattern was first used in Phase 5, not something Phase 8 introduced; only became visible once the file was actually tested against a repair-capable Desktop Excel. Fixed with a new set_text_categories() helper that builds each chart's category axis explicitly as a string reference (AxDataSource(strRef=StrRef(...))) instead — applied in all three chart-building functions. Verified in the regenerated file: every chart*.xml part now uses <c:strRef> for its category axis. Documented honestly as NOT yet confirmed to be the full explanation for the second repair report (no detailed repair log was available for this occurrence, unlike 9.0's) — a real, independent, spec-level defect fixed on its own merits; the next diagnostic step if a repair prompt still appears is the detailed 'Removed Records' log, not further speculation. Full addendum in /passress-mis/PHASE9_DOCUMENTATION.md §7.
B50: MASTER DATA LOOKUP TABLES (orange cells = configurable — edit freely, every dropdown in the workbook reads from here)
B51: Expense Category
B52: Rent
B53: Utilities
B54: Salaries
B55: Marketing
B56: Shipping & Logistics
B57: Packaging
B58: Software & Subscriptions
B59: Professional Fees
B60: Bank Charges
B61: Other
... B151: KPI TARGETS (green Target Value cells = type here)
B152: KPI Name | C152: Target Value | D152: Unit | E152: Period | F152: Notes
B153: Sales Target | C153: 500000 | D153: EGP | E153: Monthly | F153: Net Sales target
B154: Margin Target | C154: 0.55 | D154: % | E154: Monthly | F154: Gross Margin % target
B155: Orders Target | C155: 400 | D155: Count | E155: Monthly | F155: Order Count target
B156: Inventory Target | C156: 300000 | D156: EGP | E156: Monthly | F156: Inventory Value ceiling (avoid overstock)
B157: AOV Target | C157: 1200 | D157: EGP | E157: Monthly | F157: Average Order Value target
B158: CAC Target | C158: 150 | D158: EGP | E158: Monthly | F158: Customer Acquisition Cost ceiling — needs Marketing-Ready spend data (Phase 6+) to compute Actual
B159: ROAS Target | C159: 4 | D159: Ratio | E159: Monthly | F159: Return on Ad Spend target — needs Marketing-Ready spend data (Phase 6+) to compute Actual
B160: Repeat Customer % Target | C160: 0.3 | D160: % | E160: Monthly | F160: Returning Customers / Customers Active target
B161: Conversion Rate Target | C161: 0.02 | D161: % | E161: Monthly | F161: Needs Shopify session/traffic data (not fetched — Admin API has no storefront analytics) to compute Actual
B162: Inventory Turnover Target | C162: 6 | D162: Ratio | E162: Yearly | F162: COGS / Average Inventory Value target
B165: BUSINESS HEALTH SCORE WEIGHTS (green cells = type here — must be numeric, any scale)
B166: Component | C166: Weight
B167: Revenue Growth | C167: 15
B168: Gross Margin | C168: 15
B169: Cash Position | C169: 15
B170: Inventory Health | C170: 10
B171: Customer Growth | C171: 10
B172: Repeat Customers | C172: 10
B173: Return Rate | C173: 10
B174: Budget Performance | C174: 5
B175: Data Quality | C175: 5
B176: Alerts | C176: 5
B179: HOLIDAYS (green cells = type here — optional, empty by default)
B180: Date | C180: Holiday Name
C181: EXAMPLE — delete or overwrite this row; leave the table empty if no holidays apply

Sheet RAW_Orders
A1: RAW_Orders
A2: PASSRESS MIS | Home ▸ RAW_Orders
A3: Sheet Documentation (use the + outline control at left to expand)
A4: Purpose | B4: Power Query staging landing zone for the Shopify Orders resource. Shape-only transforms (type casting, flattening) happen here — no business logic.
A5: Input tables | B5: Shopify Admin GraphQL API, via the fn_ShopifyGraphQL / fn_ShopifyPagedConnection shared functions.
A6: Output tables | B6: Feeds the Data Model fact/dimension tables built from this resource (Phase 3).
A7: Relationships | B7: Connection-only in Excel; loaded to the Data Model, not to a worksheet grid, once wired in Excel.
A8: Future data source | B8: Live now: paste passress-mis/power-query/staging/RAW_Orders.pq into this query in Excel's Power Query Advanced Editor (Data > Get Data > Launch Power Query Editor > New Query > Blank Query). See passress-mis/power-query/README.md for full setup and passress-mis/power-query/DOCUMENTATION.md for the field-by-field mapping.
B11: OrderID | C11: OrderNumber | D11: CreatedAt | E11: UpdatedAt | F11: FinancialStatus | G11: FulfillmentStatus | H11: Currency | I11: TotalPrice | J11: SubtotalPrice | K11: TotalDiscounts | L11: TotalTax | M11: CustomerID | N11: LocationID

Sheet RAW_OrderLines
A1: RAW_OrderLines
A2: PASSRESS MIS | Home ▸ RAW_OrderLines
A3: Sheet Documentation (use the + outline control at left to expand)
A4: Purpose | B4: Power Query staging landing zone for the Shopify OrderLines resource. Shape-only transforms (type casting, flattening) happen here — no business logic.
A5: Input tables | B5: Shopify Admin GraphQL API, via the fn_ShopifyGraphQL / fn_ShopifyPagedConnection shared functions.
A6: Output tables | B6: Feeds the Data Model fact/dimension tables built from this resource (Phase 3).
A7: Relationships | B7: Connection-only in Excel; loaded to the Data Model, not to a worksheet grid, once wired in Excel.
A8: Future data source | B8: Live now: paste passress-mis/power-query/staging/RAW_OrderLines.pq into this query in Excel's Power Query Advanced Editor (Data > Get Data > Launch Power Query Editor > New Query > Blank Query). See passress-mis/power-query/README.md for full setup and passress-mis/power-query/DOCUMENTATION.md for the field-by-field mapping.
B11: LineItemID | C11: OrderID | D11: ProductID | E11: VariantID | F11: SKU | G11: Title | H11: Quantity | I11: UnitPrice | J11: DiscountAllocated | K11: TaxAllocated

Sheet RAW_Transactions
A1: RAW_Transactions
A2: PASSRESS MIS | Home ▸ RAW_Transactions
A3: Sheet Documentation (use the + outline control at left to expand)
A4: Purpose | B4: Power Query staging landing zone for the Shopify Transactions resource. Shape-only transforms (type casting, flattening) happen here — no business logic.
A5: Input tables | B5: Shopify Admin GraphQL API, via the fn_ShopifyGraphQL / fn_ShopifyPagedConnection shared functions.
A6: Output tables | B6: Feeds the Data Model fact/dimension tables built from this resource (Phase 3).
A7: Relationships | B7: Connection-only in Excel; loaded to the Data Model, not to a worksheet grid, once wired in Excel.
A8: Future data source | B8: Live now: paste passress-mis/power-query/staging/RAW_Transactions.pq into this query in Excel's Power Query Advanced Editor (Data > Get Data > Launch Power Query Editor > New Query > Blank Query). See passress-mis/power-query/README.md for full setup and passress-mis/power-query/DOCUMENTATION.md for the field-by-field mapping.
B11: TransactionID | C11: OrderID | D11: Kind | E11: Status | F11: Gateway | G11: AmountShop | H11: CurrencyShop | I11: CreatedAt | J11: ProcessedAt | K11: Test

Sheet RAW_Refunds
A1: RAW_Refunds
A2: PASSRESS MIS | Home ▸ RAW_Refunds
A3: Sheet Documentation (use the + outline control at left to expand)
A4: Purpose | B4: Power Query staging landing zone for the Shopify Refunds resource. Shape-only transforms (type casting, flattening) happen here — no business logic.
A5: Input tables | B5: Shopify Admin GraphQL API, via the fn_ShopifyGraphQL / fn_ShopifyPagedConnection shared functions.
A6: Output tables | B6: Feeds the Data Model fact/dimension tables built from this resource (Phase 3).
A7: Relationships | B7: Connection-only in Excel; loaded to the Data Model, not to a worksheet grid, once wired in Excel.
A8: Future data source | B8: Live now: paste passress-mis/power-query/staging/RAW_Refunds.pq into this query in Excel's Power Query Advanced Editor (Data > Get Data > Launch Power Query Editor > New Query > Blank Query). See passress-mis/power-query/README.md for full setup and passress-mis/power-query/DOCUMENTATION.md for the field-by-field mapping.
B11: RefundLineItemID | C11: RefundID | D11: OrderID | E11: LineItemID | F11: Quantity | G11: SubtotalAmount | H11: TaxAmount | I11: RefundCreatedAt | J11: RefundProcessedAt | K11: Note

Sheet RAW_Products
A1: RAW_Products
A2: PASSRESS MIS | Home ▸ RAW_Products
A3: Sheet Documentation (use the + outline control at left to expand)
A4: Purpose | B4: Power Query staging landing zone for the Shopify Products resource. Shape-only transforms (type casting, flattening) happen here — no business logic.
A5: Input tables | B5: Shopify Admin GraphQL API, via the fn_ShopifyGraphQL / fn_ShopifyPagedConnection shared functions.
A6: Output tables | B6: Feeds the Data Model fact/dimension tables built from this resource (Phase 3).
A7: Relationships | B7: Connection-only in Excel; loaded to the Data Model, not to a worksheet grid, once wired in Excel.
A8: Future data source | B8: Live now: paste passress-mis/power-query/staging/RAW_Products.pq into this query in Excel's Power Query Advanced Editor (Data > Get Data > Launch Power Query Editor > New Query > Blank Query). See passress-mis/power-query/README.md for full setup and passress-mis/power-query/DOCUMENTATION.md for the field-by-field mapping.
B11: ProductID | C11: Title | D11: ProductType | E11: Vendor | F11: CollectionIDs | G11: CreatedAt | H11: UpdatedAt | I11: Status

Sheet RAW_Variants
A1: RAW_Variants
A2: PASSRESS MIS | Home ▸ RAW_Variants
A3: Sheet Documentation (use the + outline control at left to expand)
A4: Purpose | B4: Power Query staging landing zone for the Shopify Variants resource. Shape-only transforms (type casting, flattening) happen here — no business logic.
A5: Input tables | B5: Shopify Admin GraphQL API, via the fn_ShopifyGraphQL / fn_ShopifyPagedConnection shared functions.
A6: Output tables | B6: Feeds the Data Model fact/dimension tables built from this resource (Phase 3).
A7: Relationships | B7: Connection-only in Excel; loaded to the Data Model, not to a worksheet grid, once wired in Excel.
A8: Future data source | B8: Live now: paste passress-mis/power-query/staging/RAW_Variants.pq into this query in Excel's Power Query Advanced Editor (Data > Get Data > Launch Power Query Editor > New Query > Blank Query). See passress-mis/power-query/README.md for full setup and passress-mis/power-query/DOCUMENTATION.md for the field-by-field mapping.
B11: VariantID | C11: ProductID | D11: SKU | E11: Title | F11: Price | G11: CompareAtPrice | H11: InventoryItemID | I11: UnitCost | J11: CreatedAt | K11: UpdatedAt

Sheet RAW_InventoryLevels
A1: RAW_InventoryLevels
A2: PASSRESS MIS | Home ▸ RAW_InventoryLevels
A3: Sheet Documentation (use the + outline control at left to expand)
A4: Purpose | B4: Power Query staging landing zone for the Shopify InventoryLevels resource. Shape-only transforms (type casting, flattening) happen here — no business logic.
A5: Input tables | B5: Shopify Admin GraphQL API, via the fn_ShopifyGraphQL / fn_ShopifyPagedConnection shared functions.
A6: Output tables | B6: Feeds the Data Model fact/dimension tables built from this resource (Phase 3).
A7: Relationships | B7: Connection-only in Excel; loaded to the Data Model, not to a worksheet grid, once wired in Excel.
A8: Future data source | B8: Live now: paste passress-mis/power-query/staging/RAW_InventoryLevels.pq into this query in Excel's Power Query Advanced Editor (Data > Get Data > Launch Power Query Editor > New Query > Blank Query). See passress-mis/power-query/README.md for full setup and passress-mis/power-query/DOCUMENTATION.md for the field-by-field mapping.
B11: InventoryItemID | C11: SKU | D11: LocationID | E11: Available | F11: UpdatedAt

Sheet RAW_Customers
A1: RAW_Customers
A2: PASSRESS MIS | Home ▸ RAW_Customers
A3: Sheet Documentation (use the + outline control at left to expand)
A4: Purpose | B4: Power Query staging landing zone for the Shopify Customers resource. Shape-only transforms (type casting, flattening) happen here — no business logic.
A5: Input tables | B5: Shopify Admin GraphQL API, via the fn_ShopifyGraphQL / fn_ShopifyPagedConnection shared functions.
A6: Output tables | B6: Feeds the Data Model fact/dimension tables built from this resource (Phase 3).
A7: Relationships | B7: Connection-only in Excel; loaded to the Data Model, not to a worksheet grid, once wired in Excel.
A8: Future data source | B8: Live now: paste passress-mis/power-query/staging/RAW_Customers.pq into this query in Excel's Power Query Advanced Editor (Data > Get Data > Launch Power Query Editor > New Query > Blank Query). See passress-mis/power-query/README.md for full setup and passress-mis/power-query/DOCUMENTATION.md for the field-by-field mapping.
B11: CustomerID | C11: FirstName | D11: LastName | E11: Email | F11: CreatedAt | G11: UpdatedAt | H11: OrdersCount | I11: TotalSpent | J11: DefaultAddressCountry

Sheet RAW_Collections
A1: RAW_Collections
A2: PASSRESS MIS | Home ▸ RAW_Collections
A3: Sheet Documentation (use the + outline control at left to expand)
A4: Purpose | B4: Power Query staging landing zone for the Shopify Collections resource. Shape-only transforms (type casting, flattening) happen here — no business logic.
A5: Input tables | B5: Shopify Admin GraphQL API, via the fn_ShopifyGraphQL / fn_ShopifyPagedConnection shared functions.
A6: Output tables | B6: Feeds the Data Model fact/dimension tables built from this resource (Phase 3).
A7: Relationships | B7: Connection-only in Excel; loaded to the Data Model, not to a worksheet grid, once wired in Excel.
A8: Future data source | B8: Live now: paste passress-mis/power-query/staging/RAW_Collections.pq into this query in Excel's Power Query Advanced Editor (Data > Get Data > Launch Power Query Editor > New Query > Blank Query). See passress-mis/power-query/README.md for full setup and passress-mis/power-query/DOCUMENTATION.md for the field-by-field mapping.
B11: CollectionID | C11: Title | D11: Handle

Sheet RAW_Discounts
A1: RAW_Discounts
A2: PASSRESS MIS | Home ▸ RAW_Discounts
A3: Sheet Documentation (use the + outline control at left to expand)
A4: Purpose | B4: Power Query staging landing zone for the Shopify Discounts resource. Shape-only transforms (type casting, flattening) happen here — no business logic.
A5: Input tables | B5: Shopify Admin GraphQL API, via the fn_ShopifyGraphQL / fn_ShopifyPagedConnection shared functions.
A6: Output tables | B6: Feeds the Data Model fact/dimension tables built from this resource (Phase 3).
A7: Relationships | B7: Connection-only in Excel; loaded to the Data Model, not to a worksheet grid, once wired in Excel.
A8: Future data source | B8: Live now: paste passress-mis/power-query/staging/RAW_Discounts.pq into this query in Excel's Power Query Advanced Editor (Data > Get Data > Launch Power Query Editor > New Query > Blank Query). See passress-mis/power-query/README.md for full setup and passress-mis/power-query/DOCUMENTATION.md for the field-by-field mapping.
B11: DiscountNodeID | C11: Typename | D11: Title | E11: Status | F11: Summary | G11: Code | H11: StartsAt | I11: EndsAt | J11: UsageLimit | K11: AsyncUsageCount | L11: CreatedAt | M11: UpdatedAt

Sheet DIM_Date
A1: DIM_Date
A2: PASSRESS MIS | Home ▸ DIM_Date
A3: Sheet Documentation (use the + outline control at left to expand)
A4: Purpose | B4: Dimension table for the star schema — describes the 'Date' entity that FACT_ tables relate to.
A5: Input tables | B5: RAW_ staging table(s) built in Phase 2.
A6: Output tables | B6: Related to FACT_ tables in the Data Model (one-to-many).
A7: Relationships | B7: One-to-many into the relevant FACT_ table(s) on this dimension's key column — see dax/README.md for the full relationship list.
A8: Future data source | B8: Live now: paste passress-mis/power-query/star-schema/DIM_Date.pq — see passress-mis/dax/README.md for setup order.
B11: DateKey | C11: Date | D11: Year | E11: FiscalYear | F11: Quarter | G11: Month | H11: MonthName | I11: Week | J11: Day | K11: DayName | L11: IsWeekend

Sheet DIM_Product
A1: DIM_Product
A2: PASSRESS MIS | Home ▸ DIM_Product
A3: Sheet Documentation (use the + outline control at left to expand)
A4: Purpose | B4: Dimension table for the star schema — describes the 'Product' entity that FACT_ tables relate to.
A5: Input tables | B5: RAW_ staging table(s) built in Phase 2.
A6: Output tables | B6: Related to FACT_ tables in the Data Model (one-to-many).
A7: Relationships | B7: One-to-many into the relevant FACT_ table(s) on this dimension's key column — see dax/README.md for the full relationship list.
A8: Future data source | B8: Live now: paste passress-mis/power-query/star-schema/DIM_Product.pq — see passress-mis/dax/README.md for setup order.
B11: ProductKey | C11: ProductID | D11: SKU | E11: Title | F11: ProductType | G11: Vendor | H11: Collection | I11: UnitCost | J11: Status

Sheet DIM_Customer
A1: DIM_Customer
A2: PASSRESS MIS | Home ▸ DIM_Customer
A3: Sheet Documentation (use the + outline control at left to expand)
A4: Purpose | B4: Dimension table for the star schema — describes the 'Customer' entity that FACT_ tables relate to.
A5: Input tables | B5: RAW_ staging table(s) built in Phase 2.
A6: Output tables | B6: Related to FACT_ tables in the Data Model (one-to-many).
A7: Relationships | B7: One-to-many into the relevant FACT_ table(s) on this dimension's key column — see dax/README.md for the full relationship list.
A8: Future data source | B8: Live now: paste passress-mis/power-query/star-schema/DIM_Customer.pq — see passress-mis/dax/README.md for setup order.
B11: CustomerKey | C11: CustomerID | D11: Name | E11: Email | F11: Country | G11: FirstOrderDate | H11: CustomerSegment

Sheet DIM_Location
A1: DIM_Location
A2: PASSRESS MIS | Home ▸ DIM_Location
A3: Sheet Documentation (use the + outline control at left to expand)
A4: Purpose | B4: Dimension table for the star schema — describes the 'Location' entity that FACT_ tables relate to.
A5: Input tables | B5: RAW_ staging table(s) built in Phase 2.
A6: Output tables | B6: Related to FACT_ tables in the Data Model (one-to-many).
A7: Relationships | B7: One-to-many into the relevant FACT_ table(s) on this dimension's key column — see dax/README.md for the full relationship list.
A8: Future data source | B8: Live now: paste passress-mis/power-query/star-schema/DIM_Location.pq — see passress-mis/dax/README.md for setup order.
B11: LocationKey | C11: LocationID | D11: LocationName | E11: City | F11: Country

Sheet DIM_Collection
A1: DIM_Collection
A2: PASSRESS MIS | Home ▸ DIM_Collection
A3: Sheet Documentation (use the + outline control at left to expand)
A4: Purpose | B4: Dimension table for the star schema — describes the 'Collection' entity that FACT_ tables relate to.
A5: Input tables | B5: RAW_ staging table(s) built in Phase 2.
A6: Output tables | B6: Related to FACT_ tables in the Data Model (one-to-many).
A7: Relationships | B7: One-to-many into the relevant FACT_ table(s) on this dimension's key column — see dax/README.md for the full relationship list.
A8: Future data source | B8: Live now: paste passress-mis/power-query/star-schema/DIM_Collection.pq — see passress-mis/dax/README.md for setup order.
B11: CollectionKey | C11: CollectionID | D11: Title | E11: Handle

Sheet DIM_Parameters
A1: DIM_Parameters
A2: PASSRESS MIS | Home ▸ DIM_Parameters
A3: Sheet Documentation (use the + outline control at left to expand)
A4: Purpose | B4: Disconnected mirror of 15_Settings, used so DAX measures can reference configurable constants without creating a relationship into the star schema.
A5: Input tables | B5: 15_Settings (linked manually / via Power Query, Phase 2).
A6: Output tables | B6: Referenced by DAX measures across all dashboards.
A7: Relationships | B7: N/A — disconnected table by design.
A8: Future data source | B8: Manual link to 15_Settings — Phase 3.
B11: ParameterName | C11: ParameterValue

Sheet DIM_Supplier
A1: DIM_Supplier
A2: PASSRESS MIS | Home ▸ DIM_Supplier
A3: Sheet Documentation (use the + outline control at left to expand)
A4: Purpose | B4: Data Model-ready mirror of 12_Suppliers (Supplier Master table).
A5: Input tables | B5: 12_Suppliers's master-data table.
A6: Output tables | B6: Related to FACT_ tables in the Data Model (one-to-many).
A7: Relationships | B7: SupplierID relates to FACT_ManualExpenses/FACT_PurchaseOrderHeader; PrimarySupplierID on DIM_Product relates back here (one-to-many).
A8: Future data source | B8: Live now: paste passress-mis/power-query/star-schema/DIM_Supplier.pq — see passress-mis/dax/README.md for setup order.
B11: SupplierKey | C11: SupplierID | D11: SupplierName | E11: SupplierType | F11: Currency | G11: Status

Sheet DIM_ProductCostHistory
A1: DIM_ProductCostHistory
A2: PASSRESS MIS | Home ▸ DIM_ProductCostHistory
A3: Sheet Documentation (use the + outline control at left to expand)
A4: Purpose | B4: Data Model-ready mirror of 05_Products (Product Cost Master table), time-variant (Effective From/To + Active Flag preserved) so Phase 4 can join each order line to the cost that was active on the order's date.
A5: Input tables | B5: 05_Products's master-data table.
A6: Output tables | B6: Related to FACT_ tables in the Data Model (one-to-many).
A7: Relationships | B7: SKU relates to FACT_OrderLines; EffectiveFromDate/EffectiveToDate bound which cost row applies to a given order date via fn_GetEffectiveCost (Power Query), not a Data Model relationship — see dax/README.md.
A8: Future data source | B8: Live now: paste passress-mis/power-query/star-schema/DIM_ProductCostHistory.pq — see passress-mis/dax/README.md for setup order.
B11: CostKey | C11: SKU | D11: Collection | E11: TotalLandedCost | F11: SellingPrice | G11: ExpectedGrossMarginPct | H11: EffectiveFromDate | I11: EffectiveToDate | J11: ActiveFlag

Sheet FACT_OrderLines
A1: FACT_OrderLines
A2: PASSRESS MIS | Home ▸ FACT_OrderLines
A3: Sheet Documentation (use the + outline control at left to expand)
A4: Purpose | B4: Fact table for the star schema — transaction-level grain, built from RAW_ staging data plus dimension keys via Power Query (not re-fetched from Shopify).
A5: Input tables | B5: RAW_ staging tables + DIM_ key lookups.
A6: Output tables | B6: Referenced by DAX measures — see passress-mis/dax/MEASURES.md.
A7: Relationships | B7: Many-to-one into each related DIM_ table — see dax/README.md for the full relationship list.
A8: Future data source | B8: Live now: paste passress-mis/power-query/star-schema/FACT_OrderLines.pq — see passress-mis/dax/README.md for setup order.
B11: OrderLineKey | C11: OrderID | D11: DateKey | E11: ProductKey | F11: CustomerKey | G11: LocationKey | H11: Quantity | I11: UnitPrice | J11: GrossAmount | K11: DiscountAmount | L11: TaxAmount | M11: NetAmount | N11: UnitCost | O11: COGS | P11: MissingCostFlag

Sheet FACT_Refunds
A1: FACT_Refunds
A2: PASSRESS MIS | Home ▸ FACT_Refunds
A3: Sheet Documentation (use the + outline control at left to expand)
A4: Purpose | B4: Fact table for the star schema — transaction-level grain, built from RAW_ staging data plus dimension keys via Power Query (not re-fetched from Shopify).
A5: Input tables | B5: RAW_ staging tables + DIM_ key lookups.
A6: Output tables | B6: Referenced by DAX measures — see passress-mis/dax/MEASURES.md.
A7: Relationships | B7: Many-to-one into each related DIM_ table — see dax/README.md for the full relationship list.
A8: Future data source | B8: Live now: paste passress-mis/power-query/star-schema/FACT_Refunds.pq — see passress-mis/dax/README.md for setup order.
B11: RefundKey | C11: OrderLineKey | D11: DateKey | E11: Quantity | F11: RefundAmount

Sheet FACT_InventoryMovements
A1: FACT_InventoryMovements
A2: PASSRESS MIS | Home ▸ FACT_InventoryMovements
A3: Sheet Documentation (use the + outline control at left to expand)
A4: Purpose | B4: Fact table for the star schema — transaction-level grain, built from RAW_ staging data plus dimension keys via Power Query (not re-fetched from Shopify).
A5: Input tables | B5: RAW_ staging tables + DIM_ key lookups.
A6: Output tables | B6: Referenced by DAX measures — see passress-mis/dax/MEASURES.md.
A7: Relationships | B7: Many-to-one into each related DIM_ table — see dax/README.md for the full relationship list.
A8: Future data source | B8: Live now: paste passress-mis/power-query/star-schema/FACT_InventoryMovements.pq — see passress-mis/dax/README.md for setup order.
B11: MovementKey | C11: DateKey | D11: ProductKey | E11: LocationKey | F11: MovementType | G11: QuantityChange | H11: ResultingOnHand

Sheet FACT_Payments
A1: FACT_Payments
A2: PASSRESS MIS | Home ▸ FACT_Payments
A3: Sheet Documentation (use the + outline control at left to expand)
A4: Purpose | B4: Fact table for the star schema — transaction-level grain, built from RAW_ staging data plus dimension keys via Power Query (not re-fetched from Shopify).
A5: Input tables | B5: RAW_ staging tables + DIM_ key lookups.
A6: Output tables | B6: Referenced by DAX measures — see passress-mis/dax/MEASURES.md.
A7: Relationships | B7: Many-to-one into each related DIM_ table — see dax/README.md for the full relationship list.
A8: Future data source | B8: Live now: paste passress-mis/power-query/star-schema/FACT_Payments.pq — see passress-mis/dax/README.md for setup order.
B11: PaymentKey | C11: OrderID | D11: DateKey | E11: PaymentMethod | F11: Currency | G11: Amount | H11: PresentmentAmount

Sheet FACT_ManualExpenses
A1: FACT_ManualExpenses
A2: PASSRESS MIS | Home ▸ FACT_ManualExpenses
A3: Sheet Documentation (use the + outline control at left to expand)
A4: Purpose | B4: Manually entered fact, kept structurally separate from Shopify-sourced facts. Mirrors the input table(s) on 10_Expenses — this is the Data Model-ready version of it.
A5: Input tables | B5: 10_Expenses manual entry table(s).
A6: Output tables | B6: Referenced by DAX measures — see passress-mis/dax/MEASURES.md.
A7: Relationships | B7: Grain matches its source table on the visible sheet, one-for-one.
A8: Future data source | B8: Live now: paste passress-mis/power-query/star-schema/FACT_ManualExpenses.pq — see passress-mis/dax/README.md for setup order.
B11: ExpenseKey | C11: DateKey | D11: ExpenseDate | E11: ExpenseCategory | F11: ExpenseSubcategory | G11: SupplierID | H11: Amount | I11: Currency | J11: PaymentMethod | K11: RelatedCollection | L11: RelatedSKU | M11: CostCenter | N11: InvoiceNumber

Sheet FACT_CapitalTransactions
A1: FACT_CapitalTransactions
A2: PASSRESS MIS | Home ▸ FACT_CapitalTransactions
A3: Sheet Documentation (use the + outline control at left to expand)
A4: Purpose | B4: Manually entered fact, kept structurally separate from Shopify-sourced facts. Mirrors the input table(s) on 11_Capital — this is the Data Model-ready version of it.
A5: Input tables | B5: 11_Capital manual entry table(s).
A6: Output tables | B6: Referenced by DAX measures — see passress-mis/dax/MEASURES.md.
A7: Relationships | B7: Grain matches its source table on the visible sheet, one-for-one.
A8: Future data source | B8: Live now: paste passress-mis/power-query/star-schema/FACT_CapitalTransactions.pq — see passress-mis/dax/README.md for setup order.
B11: CapitalKey | C11: DateKey | D11: Date | E11: Owner | F11: TransactionType | G11: Amount

Sheet FACT_PurchaseOrderHeader
A1: FACT_PurchaseOrderHeader
A2: PASSRESS MIS | Home ▸ FACT_PurchaseOrderHeader
A3: Sheet Documentation (use the + outline control at left to expand)
A4: Purpose | B4: Manually entered fact, kept structurally separate from Shopify-sourced facts. Mirrors the input table(s) on 12_Suppliers (PO Header table) — this is the Data Model-ready version of it.
A5: Input tables | B5: 12_Suppliers (PO Header table) manual entry table(s).
A6: Output tables | B6: Referenced by DAX measures — see passress-mis/dax/MEASURES.md.
A7: Relationships | B7: Grain matches its source table on the visible sheet, one-for-one.
A8: Future data source | B8: Live now: paste passress-mis/power-query/star-schema/FACT_PurchaseOrderHeader.pq — see passress-mis/dax/README.md for setup order.
B11: PONumber | C11: DateKey | D11: SupplierID | E11: OrderDate | F11: ExpectedDeliveryDate | G11: Status | H11: Currency

Sheet FACT_PurchaseOrderLines
A1: FACT_PurchaseOrderLines
A2: PASSRESS MIS | Home ▸ FACT_PurchaseOrderLines
A3: Sheet Documentation (use the + outline control at left to expand)
A4: Purpose | B4: Manually entered fact, kept structurally separate from Shopify-sourced facts. Mirrors the input table(s) on 12_Suppliers (PO Lines table) — this is the Data Model-ready version of it.
A5: Input tables | B5: 12_Suppliers (PO Lines table) manual entry table(s).
A6: Output tables | B6: Referenced by DAX measures — see passress-mis/dax/MEASURES.md.
A7: Relationships | B7: Grain matches its source table on the visible sheet, one-for-one.
A8: Future data source | B8: Live now: paste passress-mis/power-query/star-schema/FACT_PurchaseOrderLines.pq — see passress-mis/dax/README.md for setup order.
B11: PONumber | C11: SKU | D11: QuantityOrdered | E11: UnitCost | F11: TotalCost

Sheet FACT_GoodsReceipt
A1: FACT_GoodsReceipt
A2: PASSRESS MIS | Home ▸ FACT_GoodsReceipt
A3: Sheet Documentation (use the + outline control at left to expand)
A4: Purpose | B4: Manually entered fact, kept structurally separate from Shopify-sourced facts. Mirrors the input table(s) on 12_Suppliers (Goods Receipt table) — this is the Data Model-ready version of it.
A5: Input tables | B5: 12_Suppliers (Goods Receipt table) manual entry table(s).
A6: Output tables | B6: Referenced by DAX measures — see passress-mis/dax/MEASURES.md.
A7: Relationships | B7: Grain matches its source table on the visible sheet, one-for-one.
A8: Future data source | B8: Live now: paste passress-mis/power-query/star-schema/FACT_GoodsReceipt.pq — see passress-mis/dax/README.md for setup order.
B11: PONumber | C11: DateKey | D11: SKU | E11: GoodsReceivedDate | F11: QuantityReceived | G11: RemainingQuantity | H11: ActualUnitCost | I11: VarianceFromPO | J11: Warehouse

Sheet LOG_RefreshHistory
A1: LOG_RefreshHistory
A2: PASSRESS MIS | Home ▸ LOG_RefreshHistory
A3: Sheet Documentation (use the + outline control at left to expand)
A4: Purpose | B4: Append-only log of every workbook refresh: what ran, how many rows moved, and how long it took.
A5: Input tables | B5: Written by the Power Query refresh process (Phase 2).
A6: Output tables | B6: Displayed on 14_Data_Quality and summarized on 01_Home.
A7: Relationships | B7: No Data Model relationship — a flat audit trail, queried directly by 14_Data_Quality.
A8: Future data source | B8: Populated automatically on every Refresh All — Phase 2.
B11: RefreshID | C11: Timestamp | D11: Source | E11: RowsLoaded | F11: RowsUpdated | G11: Errors | H11: DurationSeconds | I11: TriggeredBy

Sheet LOG_DataQuality
A1: LOG_DataQuality
A2: PASSRESS MIS | Home ▸ LOG_DataQuality
A3: Sheet Documentation (use the + outline control at left to expand)
A4: Purpose | B4: Append-only log of validation-rule results, one row per check per refresh.
A5: Input tables | B5: Written by the Power Query refresh process (Phase 2).
A6: Output tables | B6: Displayed on 14_Data_Quality and summarized on 01_Home.
A7: Relationships | B7: No Data Model relationship — a flat audit trail, queried directly by 14_Data_Quality.
A8: Future data source | B8: Populated automatically on every Refresh All — Phase 2.
B11: CheckID | C11: Timestamp | D11: CheckName | E11: TableName | F11: Status | G11: Details

Sheet RAW_MetaAds
A1: RAW_MetaAds
A2: PASSRESS MIS | Home ▸ RAW_MetaAds
A3: Sheet Documentation (use the + outline control at left to expand)
A4: Purpose | B4: RESERVED, NOT CONNECTED — placeholder for future Meta Ads (Facebook/Instagram) API ingestion. No API calls, no credentials, no scheduled refresh exist for this yet.
A5: Input tables | B5: None yet. Future: Meta Ads (Facebook/Instagram)'s own API/export.
A6: Output tables | B6: Will feed FACT_MarketingSpend once connected.
A7: Relationships | B7: DateKey -> DIM_Date; Campaign -> a future DIM_Campaign (not yet built — see FACT_MarketingSpend's notes).
A8: Future data source | B8: Meta Ads (Facebook/Instagram) API — a future phase (6+), following the exact Power Query pattern power-query/README.md established for Shopify (auth via Extension.CurrentCredential, paginated fetch, incremental refresh).
B11: DateKey | C11: CampaignID | D11: CampaignName | E11: Spend | F11: Impressions | G11: Clicks | H11: Conversions | I11: Currency

Sheet RAW_GoogleAnalytics
A1: RAW_GoogleAnalytics
A2: PASSRESS MIS | Home ▸ RAW_GoogleAnalytics
A3: Sheet Documentation (use the + outline control at left to expand)
A4: Purpose | B4: RESERVED, NOT CONNECTED — placeholder for future Google Analytics API ingestion. No API calls, no credentials, no scheduled refresh exist for this yet.
A5: Input tables | B5: None yet. Future: Google Analytics's own API/export.
A6: Output tables | B6: Will feed FACT_MarketingSpend once connected.
A7: Relationships | B7: DateKey -> DIM_Date; Campaign -> a future DIM_Campaign (not yet built — see FACT_MarketingSpend's notes).
A8: Future data source | B8: Google Analytics API — a future phase (6+), following the exact Power Query pattern power-query/README.md established for Shopify (auth via Extension.CurrentCredential, paginated fetch, incremental refresh).
B11: DateKey | C11: CampaignID | D11: CampaignName | E11: Spend | F11: Impressions | G11: Clicks | H11: Conversions | I11: Currency

Sheet RAW_GoogleAds
A1: RAW_GoogleAds
A2: PASSRESS MIS | Home ▸ RAW_GoogleAds
A3: Sheet Documentation (use the + outline control at left to expand)
A4: Purpose | B4: RESERVED, NOT CONNECTED — placeholder for future Google Ads API ingestion. No API calls, no credentials, no scheduled refresh exist for this yet.
A5: Input tables | B5: None yet. Future: Google Ads's own API/export.
A6: Output tables | B6: Will feed FACT_MarketingSpend once connected.
A7: Relationships | B7: DateKey -> DIM_Date; Campaign -> a future DIM_Campaign (not yet built — see FACT_MarketingSpend's notes).
A8: Future data source | B8: Google Ads API — a future phase (6+), following the exact Power Query pattern power-query/README.md established for Shopify (auth via Extension.CurrentCredential, paginated fetch, incremental refresh).
B11: DateKey | C11: CampaignID | D11: CampaignName | E11: Spend | F11: Impressions | G11: Clicks | H11: Conversions | I11: Currency

Sheet RAW_TikTokAds
A1: RAW_TikTokAds
A2: PASSRESS MIS | Home ▸ RAW_TikTokAds
A3: Sheet Documentation (use the + outline control at left to expand)
A4: Purpose | B4: RESERVED, NOT CONNECTED — placeholder for future TikTok Ads API ingestion. No API calls, no credentials, no scheduled refresh exist for this yet.
A5: Input tables | B5: None yet. Future: TikTok Ads's own API/export.
A6: Output tables | B6: Will feed FACT_MarketingSpend once connected.
A7: Relationships | B7: DateKey -> DIM_Date; Campaign -> a future DIM_Campaign (not yet built — see FACT_MarketingSpend's notes).
A8: Future data source | B8: TikTok Ads API — a future phase (6+), following the exact Power Query pattern power-query/README.md established for Shopify (auth via Extension.CurrentCredential, paginated fetch, incremental refresh).
B11: DateKey | C11: CampaignID | D11: CampaignName | E11: Spend | F11: Impressions | G11: Clicks | H11: Conversions | I11: Currency

Sheet RAW_EmailMarketing
A1: RAW_EmailMarketing
A2: PASSRESS MIS | Home ▸ RAW_EmailMarketing
A3: Sheet Documentation (use the + outline control at left to expand)
A4: Purpose | B4: RESERVED, NOT CONNECTED — placeholder for future Email Marketing (e.g. Klaviyo/Mailchimp) API ingestion. No API calls, no credentials, no scheduled refresh exist for this yet.
A5: Input tables | B5: None yet. Future: Email Marketing (e.g. Klaviyo/Mailchimp)'s own API/export.
A6: Output tables | B6: Will feed FACT_MarketingSpend once connected.
A7: Relationships | B7: DateKey -> DIM_Date; Campaign -> a future DIM_Campaign (not yet built — see FACT_MarketingSpend's notes).
A8: Future data source | B8: Email Marketing (e.g. Klaviyo/Mailchimp) API — a future phase (6+), following the exact Power Query pattern power-query/README.md established for Shopify (auth via Extension.CurrentCredential, paginated fetch, incremental refresh).
B11: DateKey | C11: CampaignID | D11: CampaignName | E11: Spend | F11: Impressions | G11: Clicks | H11: Conversions | I11: Currency

Sheet RAW_InfluencerCampaigns
A1: RAW_InfluencerCampaigns
A2: PASSRESS MIS | Home ▸ RAW_InfluencerCampaigns
A3: Sheet Documentation (use the + outline control at left to expand)
A4: Purpose | B4: RESERVED, NOT CONNECTED — placeholder for future Influencer Campaigns API ingestion. No API calls, no credentials, no scheduled refresh exist for this yet.
A5: Input tables | B5: None yet. Future: Influencer Campaigns's own API/export.
A6: Output tables | B6: Will feed FACT_MarketingSpend once connected.
A7: Relationships | B7: DateKey -> DIM_Date; Campaign -> a future DIM_Campaign (not yet built — see FACT_MarketingSpend's notes).
A8: Future data source | B8: Influencer Campaigns API — a future phase (6+), following the exact Power Query pattern power-query/README.md established for Shopify (auth via Extension.CurrentCredential, paginated fetch, incremental refresh).
B11: DateKey | C11: CampaignID | D11: CampaignName | E11: Spend | F11: Impressions | G11: Clicks | H11: Conversions | I11: Currency

Sheet FACT_MarketingSpend
A1: FACT_MarketingSpend
A2: PASSRESS MIS | Home ▸ FACT_MarketingSpend
A3: Sheet Documentation (use the + outline control at left to expand)
A4: Purpose | B4: RESERVED, NOT CONNECTED — the unified cross-channel spend fact every RAW_<Channel>Ads table above would roll into, so DAX (CAC, ROAS) can query one table instead of six. Channel-specific fields (e.g. TikTok's video view counts) stay on each RAW_ table; only the common shape (spend, date, campaign, conversions) is unified here.
A5: Input tables | B5: Will be built from every RAW_MetaAds/RAW_GoogleAds/RAW_TikTokAds/etc. table above, once connected.
A6: Output tables | B6: dax/MEASURES.md's [CAC] and [ROAS] (currently unbuildable — see KPI Targets' notes on those two rows) will read from here.
A7: Relationships | B7: DateKey -> DIM_Date; ChannelName is a plain attribute (not worth its own dimension at this scale); CampaignID -> a future DIM_Campaign.
A8: Future data source | B8: Union of the RAW_<Channel>Ads tables above, in Power Query — a future phase (6+).
B11: DateKey | C11: ChannelName | D11: CampaignID | E11: CampaignName | F11: Spend | G11: Conversions | H11: Currency

Sheet FUTURE_AI_Insights
A1: FUTURE_AI_Insights
A2: PASSRESS MIS | Home ▸ FUTURE_AI_Insights
A3: Sheet Documentation (use the + outline control at left to expand)
A4: Purpose | B4: RESERVED, NOT IMPLEMENTED — placeholder inventory of AI-generated features a future phase could add (Executive Summary, Daily/Weekly/Monthly Summary, Recommendations, Anomaly Detection, Natural Language Q&A). No AI model is called anywhere in this workbook today.
A5: Input tables | B5: None yet. Future: the Data Model (dax/MEASURES.md) + BI_Insights/BI_Alerts (Phase 5's own rule-based versions of Summary/Anomaly-Detection, which an AI layer would eventually supersede or enrich, not duplicate).
A6: Output tables | B6: None yet.
A7: Relationships | B7: None yet.
A8: Future data source | B8: A future phase's AI integration (e.g. an LLM API call summarizing the Data Model's current state) — not scoped or estimated here.
B11: FeatureName | C11: Status | D11: Description | E11: WouldReplaceOrEnrich
B12: Executive Summary | C12: Not Implemented | D12: One-paragraph AI-written summary of the period's performance | E12: Enriches BI_Insights (adds narrative synthesis on top of the rule-based bullet points)

Sheet BI_Insights
A1: BI_Insights
A2: PASSRESS MIS | Home ▸ BI_Insights
A3: Sheet Documentation (use the + outline control at left to expand)
A4: Purpose | B4: Auto-generated business insights, one row per insight, built from CUBEVALUE formulas reading dax/MEASURES.md's measures directly (no PivotTable needed). Recalculates on every workbook open/refresh — nothing here is typed by hand.
A5: Input tables | B5: The Data Model (dax/MEASURES.md) via CUBEVALUE/CUBESET/CUBERANKEDMEMBER.
A6: Output tables | B6: 02_Partner_Dashboard and 03_CEO_Dashboard both surface a subset of these rows under 'Key Insights'.
A7: Relationships | B7: No Data Model relationship — reads the model via CUBE functions, same mechanism the dashboards themselves use.
A8: Future data source | B8: Already live: resolves for real once the Data Model + measures are wired per dax/README.md. Until then shows blank/0 — expected, not an error.
B11: InsightID | C11: Category | D11: InsightText | E11: Severity
B14: INSIGHT FORMULAS (CUBEVALUE-driven — see dax/PHASE5_MEASURES_ADDENDUM.md for the exact measures each one reads)
B15: INS-01 | C15: Sales | D15: ="Net Sales "&TEXT(ABS(CUBEVALUE("ThisWorkbookDataModel","[Measures].[Revenue Growth % (YoY)]")),"0.0%")&IF(CUBEVALUE("ThisWorkbookDataModel","[Measures].[Revenue Growth % (YoY)]")>=0," higher"," lower")&" than the same period last year." | E15: Info
B16: INS-02 | C16: Margin | D16: ="Gross Margin is "&TEXT(CUBEVALUE("ThisWorkbookDataModel","[Measures].[Gross Margin %]"),"0.0%")&", vs. a target of "&TEXT(CUBEVALUE("ThisWorkbookDataModel","[Measures].[Margin Target]"),"0.0%")&"." | E16: Info
B17: INS-03 | C17: Customers | D17: ="Customer Retention (month-over-month) is "&TEXT(CUBEVALUE("ThisWorkbookDataModel","[Measures].[Customer Retention Rate (MoM)]"),"0.0%")&"." | E17: Info
B18: INS-04 | C18: Inventory | D18: =IF(CUBEVALUE("ThisWorkbookDataModel","[Measures].[Inventory Turnover]")<CUBEVALUE("ThisWorkbookDataModel","[Measures].[Inventory Turnover Target]"),"Inventory turnover is below target — stock may be moving slower than planned.","Inventory turnover is at or above target.") | E18: Info
B19: INS-05 | C19: Cash | D19: =IF(CUBEVALUE("ThisWorkbookDataModel","[Measures].[Cash Position (Direct, Cumulative)]")>0,"Cash position is healthy (positive).","Cash position is negative — review Reconciliation: Cash Variance before acting on this.") | E19: Info
B20: INS-06 | C20: Products | D20: ="Best seller: "&CUBERANKEDMEMBER("ThisWorkbookDataModel",$H$20,1)&"." | E20: Info | H20: =CUBESET("ThisWorkbookDataModel","{[DIM_Product].[Title].Children}","BestSeller","BDESC","[Measures].[Net Sales]")
B21: INS-07 | C21: Products | D21: ="Weakest seller (with any sales): "&CUBERANKEDMEMBER("ThisWorkbookDataModel",$H$21,1)&" — see 05_Products for the full ranked list rather than relying on one row here." | E21: Info | H21: =CUBESET("ThisWorkbookDataModel","{[DIM_Product].[Title].Children}","WeakestSeller","BASC","[Measures].[Net Sales]")
B22: INS-08 | C22: Orders | D22: ="Average Order Value is "&TEXT(CUBEVALUE("ThisWorkbookDataModel","[Measures].[Average Order Value]"),"#,##0")&" EGP, vs. a target of "&TEXT(CUBEVALUE("ThisWorkbookDataModel","[Measures].[AOV Target]"),"#,##0")&" EGP." | E22: Info

Sheet BI_Alerts
A1: BI_Alerts
A2: PASSRESS MIS | Home ▸ BI_Alerts
A3: Sheet Documentation (use the + outline control at left to expand)
A4: Purpose | B4: Auto-generated operational alerts, one row per alert type, built from CUBEVALUE formulas plus a few direct structural checks already computed elsewhere (Product Cost Master's Overlap Warning, Manual Expenses' Possible Duplicate) rather than re-deriving them — reuses, doesn't duplicate, Phase 2-4's own data-quality logic.
A5: Input tables | B5: The Data Model (dax/MEASURES.md) via CUBEVALUE; LOG_DataQuality; tbl_ProductCostMaster/tbl_ManualExpenses' existing flag columns.
A6: Output tables | B6: 14_Data_Quality and 03_CEO_Dashboard both surface these under 'Alerts'.
A7: Relationships | B7: No Data Model relationship — reads via CUBE functions and direct cell/table references.
A8: Future data source | B8: Already live: resolves for real once the Data Model + measures are wired per dax/README.md.
B11: AlertID | C11: AlertName | D11: Condition | E11: Status | F11: Severity
B14: ALERT FORMULAS
B15: ALT-01 | C15: Low Inventory | D15: Inventory Value below target | E15: =IF(CUBEVALUE("ThisWorkbookDataModel","[Measures].[Inventory Value]")<CUBEVALUE("ThisWorkbookDataModel","[Measures].[Inventory Target]")*0.5,"TRIGGERED","OK") | F15: Warning
B16: ALT-02 | C16: Negative Margin | D16: Gross Margin % below 0 | E16: =IF(CUBEVALUE("ThisWorkbookDataModel","[Measures].[Gross Margin %]")<0,"TRIGGERED","OK") | F16: Critical
B17: ALT-03 | C17: Products without Cost | D17: Order lines with no matching Product Cost Master row | E17: =IF(CUBEVALUE("ThisWorkbookDataModel","[Measures].[Lines Missing Cost]")>0,"TRIGGERED ("&CUBEVALUE("ThisWorkbookDataModel","[Measures].[Lines Missing Cost]")&" lines)","OK") | F17: Warning
B18: ALT-04 | C18: Products without SKU | D18: RAW_Variants rows with a blank SKU | E18: =IF(COUNTIFS(tbl_RAW_Variants[SKU],"")>0,"TRIGGERED","OK") | F18: Warning
B19: ALT-05 | C19: Expenses without Category | D19: Manual Expenses rows with a blank Expense Category | E19: =IF(COUNTIFS(tbl_ManualExpenses[Expense Category],"")>0,"TRIGGERED","OK") | F19: Warning
B20: ALT-06 | C20: Duplicate Expenses | D20: Manual Expenses flagged Possible Duplicate | E20: =IF(COUNTIF(tbl_ManualExpenses[Possible Duplicate],"Possible Duplicate")>0,"TRIGGERED ("&COUNTIF(tbl_ManualExpenses[Possible Duplicate],"Possible Duplicate")&")","OK") | F20: Info
B21: ALT-07 | C21: Inactive Products | D21: Product Cost Master rows marked Inactive with no Active replacement | E21: =IF(CUBEVALUE("ThisWorkbookDataModel","[Measures].[Lines Missing Cost]")>0,"REVIEW — see Products without Cost above (same root cause)","OK") | F21: Info
B22: ALT-08 | C22: Slow Moving Inventory | D22: SKUs below the Slow Moving threshold (dax/MEASURES.md) | E22: =IF(CUBEVALUE("ThisWorkbookDataModel","[Measures].[Slow Moving SKU Count]")>0,"TRIGGERED ("&CUBEVALUE("ThisWorkbookDataModel","[Measures].[Slow Moving SKU Count]")&" SKUs)","OK") | F22: Info
B23: ALT-09 | C23: Dead Stock | D23: SKUs with zero sales in 180 days while still holding stock | E23: =IF(CUBEVALUE("ThisWorkbookDataModel","[Measures].[Dead Stock SKU Count]")>0,"TRIGGERED ("&CUBEVALUE("ThisWorkbookDataModel","[Measures].[Dead Stock SKU Count]")&" SKUs)","OK") | F23: Warning
B24: ALT-10 | C24: Missing Shopify Sync | D24: No successful refresh recorded in the last 2 days | E24: =IF(COUNTIFS(tbl_LOG_RefreshHistory[Timestamp],">="&TODAY()-2)=0,"TRIGGERED","OK") | F24: Critical
B25: ALT-11 | C25: Refresh Errors | D25: LOG_DataQuality rows with a WARNING status this refresh | E25: =IF(COUNTIF(tbl_LOG_DataQuality[Status],"WARNING*")>0,"TRIGGERED","OK") | F25: Warning
B26: ALT-12 | C26: Over Budget Expenses | D26: Operating Expenses exceed the Budget for the current period | E26: =IF(CUBEVALUE("ThisWorkbookDataModel","[Measures].[Operating Expenses]")>CUBEVALUE("ThisWorkbookDataModel","[Measures].[Expense Budget (Period)]"),"TRIGGERED","OK") | F26: Warning

Sheet BI_Forecast
A1: BI_Forecast
A2: PASSRESS MIS | Home ▸ BI_Forecast
A3: Sheet Documentation (use the + outline control at left to expand)
A4: Purpose | B4: Rolling-trend forecast for Sales, Expenses, Profit, Inventory, and Cash — Excel's native FORECAST.LINEAR projecting one period ahead from each metric's trailing 12-month actuals (pulled via CUBEVALUE). Deliberately simple (linear trend, not seasonality-aware) so it's easy to audit and easy to replace.
A5: Input tables | B5: The Data Model (dax/MEASURES.md) via CUBEVALUE, trailing 12 months.
A6: Output tables | B6: 03_CEO_Dashboard's Forecast section.
A7: Relationships | B7: No Data Model relationship.
A8: Future data source | B8: AI forecasting — replace this table's Method/Formula columns with a call to an external forecasting service once one exists; every other column (Metric, ForecastPeriod, ForecastValue) stays the same shape so downstream references don't break.
B11: Metric | C11: Method | D11: ForecastPeriod | E11: ForecastValue
B14: TRAILING 12-MONTH ACTUALS (feeds the forecasts below)
B15: Sales — trailing 12 months
C16: =TEXT(EDATE(TODAY(),-11),"mmm-yy") | D16: =TEXT(EDATE(TODAY(),-10),"mmm-yy") | E16: =TEXT(EDATE(TODAY(),-9),"mmm-yy") | F16: =TEXT(EDATE(TODAY(),-8),"mmm-yy") | G16: =TEXT(EDATE(TODAY(),-7),"mmm-yy") | H16: =TEXT(EDATE(TODAY(),-6),"mmm-yy") | I16: =TEXT(EDATE(TODAY(),-5),"mmm-yy") | J16: =TEXT(EDATE(TODAY(),-4),"mmm-yy") | K16: =TEXT(EDATE(TODAY(),-3),"mmm-yy") | L16: =TEXT(EDATE(TODAY(),-2),"mmm-yy") | M16: =TEXT(EDATE(TODAY(),-1),"mmm-yy") | N16: =TEXT(EDATE(TODAY(),0),"mmm-yy")
C17: =CUBEVALUE("ThisWorkbookDataModel","[Measures].[Net Sales]","[DIM_Date].[Year].&["&YEAR(EDATE(TODAY(),-11))&"]","[DIM_Date].[Month].&["&MONTH(EDATE(TODAY(),-11))&"]") | D17: =CUBEVALUE("ThisWorkbookDataModel","[Measures].[Net Sales]","[DIM_Date].[Year].&["&YEAR(EDATE(TODAY(),-10))&"]","[DIM_Date].[Month].&["&MONTH(EDATE(TODAY(),-10))&"]") | E17: =CUBEVALUE("ThisWorkbookDataModel","[Measures].[Net Sales]","[DIM_Date].[Year].&["&YEAR(EDATE(TODAY(),-9))&"]","[DIM_Date].[Month].&["&MONTH(EDATE(TODAY(),-9))&"]") | F17: =CUBEVALUE("ThisWorkbookDataModel","[Measures].[Net Sales]","[DIM_Date].[Year].&["&YEAR(EDATE(TODAY(),-8))&"]","[DIM_Date].[Month].&["&MONTH(EDATE(TODAY(),-8))&"]") | G17: =CUBEVALUE("ThisWorkbookDataModel","[Measures].[Net Sales]","[DIM_Date].[Year].&["&YEAR(EDATE(TODAY(),-7))&"]","[DIM_Date].[Month].&["&MONTH(EDATE(TODAY(),-7))&"]") | H17: =CUBEVALUE("ThisWorkbookDataModel","[Measures].[Net Sales]","[DIM_Date].[Year].&["&YEAR(EDATE(TODAY(),-6))&"]","[DIM_Date].[Month].&["&MONTH(EDATE(TODAY(),-6))&"]") | I17: =CUBEVALUE("ThisWorkbookDataModel","[Measures].[Net Sales]","[DIM_Date].[Year].&["&YEAR(EDATE(TODAY(),-5))&"]","[DIM_Date].[Month].&["&MONTH(EDATE(TODAY(),-5))&"]") | J17: =CUBEVALUE("ThisWorkbookDataModel","[Measures].[Net Sales]","[DIM_Date].[Year].&["&YEAR(EDATE(TODAY(),-4))&"]","[DIM_Date].[Month].&["&MONTH(EDATE(TODAY(),-4))&"]") | K17: =CUBEVALUE("ThisWorkbookDataModel","[Measures].[Net Sales]","[DIM_Date].[Year].&["&YEAR(EDATE(TODAY(),-3))&"]","[DIM_Date].[Month].&["&MONTH(EDATE(TODAY(),-3))&"]") | L17: =CUBEVALUE("ThisWorkbookDataModel","[Measures].[Net Sales]","[DIM_Date].[Year].&["&YEAR(EDATE(TODAY(),-2))&"]","[DIM_Date].[Month].&["&MONTH(EDATE(TODAY(),-2))&"]") | M17: =CUBEVALUE("ThisWorkbookDataModel","[Measures].[Net Sales]","[DIM_Date].[Year].&["&YEAR(EDATE(TODAY(),-1))&"]","[DIM_Date].[Month].&["&MONTH(EDATE(TODAY(),-1))&"]") | N17: =CUBEVALUE("ThisWorkbookDataModel","[Measures].[Net Sales]","[DIM_Date].[Year].&["&YEAR(EDATE(TODAY(),0))&"]","[DIM_Date].[Month].&["&MONTH(EDATE(TODAY(),0))&"]")
B19: Expenses — trailing 12 months
C20: =TEXT(EDATE(TODAY(),-11),"mmm-yy") | D20: =TEXT(EDATE(TODAY(),-10),"mmm-yy") | E20: =TEXT(EDATE(TODAY(),-9),"mmm-yy") | F20: =TEXT(EDATE(TODAY(),-8),"mmm-yy") | G20: =TEXT(EDATE(TODAY(),-7),"mmm-yy") | H20: =TEXT(EDATE(TODAY(),-6),"mmm-yy") | I20: =TEXT(EDATE(TODAY(),-5),"mmm-yy") | J20: =TEXT(EDATE(TODAY(),-4),"mmm-yy") | K20: =TEXT(EDATE(TODAY(),-3),"mmm-yy") | L20: =TEXT(EDATE(TODAY(),-2),"mmm-yy") | M20: =TEXT(EDATE(TODAY(),-1),"mmm-yy") | N20: =TEXT(EDATE(TODAY(),0),"mmm-yy")
C21: =CUBEVALUE("ThisWorkbookDataModel","[Measures].[Operating Expenses]","[DIM_Date].[Year].&["&YEAR(EDATE(TODAY(),-11))&"]","[DIM_Date].[Month].&["&MONTH(EDATE(TODAY(),-11))&"]") | D21: =CUBEVALUE("ThisWorkbookDataModel","[Measures].[Operating Expenses]","[DIM_Date].[Year].&["&YEAR(EDATE(TODAY(),-10))&"]","[DIM_Date].[Month].&["&MONTH(EDATE(TODAY(),-10))&"]") | E21: =CUBEVALUE("ThisWorkbookDataModel","[Measures].[Operating Expenses]","[DIM_Date].[Year].&["&YEAR(EDATE(TODAY(),-9))&"]","[DIM_Date].[Month].&["&MONTH(EDATE(TODAY(),-9))&"]") | F21: =CUBEVALUE("ThisWorkbookDataModel","[Measures].[Operating Expenses]","[DIM_Date].[Year].&["&YEAR(EDATE(TODAY(),-8))&"]","[DIM_Date].[Month].&["&MONTH(EDATE(TODAY(),-8))&"]") | G21: =CUBEVALUE("ThisWorkbookDataModel","[Measures].[Operating Expenses]","[DIM_Date].[Year].&["&YEAR(EDATE(TODAY(),-7))&"]","[DIM_Date].[Month].&["&MONTH(EDATE(TODAY(),-7))&"]") | H21: =CUBEVALUE("ThisWorkbookDataModel","[Measures].[Operating Expenses]","[DIM_Date].[Year].&["&YEAR(EDATE(TODAY(),-6))&"]","[DIM_Date].[Month].&["&MONTH(EDATE(TODAY(),-6))&"]") | I21: =CUBEVALUE("ThisWorkbookDataModel","[Measures].[Operating Expenses]","[DIM_Date].[Year].&["&YEAR(EDATE(TODAY(),-5))&"]","[DIM_Date].[Month].&["&MONTH(EDATE(TODAY(),-5))&"]") | J21: =CUBEVALUE("ThisWorkbookDataModel","[Measures].[Operating Expenses]","[DIM_Date].[Year].&["&YEAR(EDATE(TODAY(),-4))&"]","[DIM_Date].[Month].&["&MONTH(EDATE(TODAY(),-4))&"]") | K21: =CUBEVALUE("ThisWorkbookDataModel","[Measures].[Operating Expenses]","[DIM_Date].[Year].&["&YEAR(EDATE(TODAY(),-3))&"]","[DIM_Date].[Month].&["&MONTH(EDATE(TODAY(),-3))&"]") | L21: =CUBEVALUE("ThisWorkbookDataModel","[Measures].[Operating Expenses]","[DIM_Date].[Year].&["&YEAR(EDATE(TODAY(),-2))&"]","[DIM_Date].[Month].&["&MONTH(EDATE(TODAY(),-2))&"]") | M21: =CUBEVALUE("ThisWorkbookDataModel","[Measures].[Operating Expenses]","[DIM_Date].[Year].&["&YEAR(EDATE(TODAY(),-1))&"]","[DIM_Date].[Month].&["&MONTH(EDATE(TODAY(),-1))&"]") | N21: =CUBEVALUE("ThisWorkbookDataModel","[Measures].[Operating Expenses]","[DIM_Date].[Year].&["&YEAR(EDATE(TODAY(),0))&"]","[DIM_Date].[Month].&["&MONTH(EDATE(TODAY(),0))&"]")
B23: Profit — trailing 12 months
C24: =TEXT(EDATE(TODAY(),-11),"mmm-yy") | D24: =TEXT(EDATE(TODAY(),-10),"mmm-yy") | E24: =TEXT(EDATE(TODAY(),-9),"mmm-yy") | F24: =TEXT(EDATE(TODAY(),-8),"mmm-yy") | G24: =TEXT(EDATE(TODAY(),-7),"mmm-yy") | H24: =TEXT(EDATE(TODAY(),-6),"mmm-yy") | I24: =TEXT(EDATE(TODAY(),-5),"mmm-yy") | J24: =TEXT(EDATE(TODAY(),-4),"mmm-yy") | K24: =TEXT(EDATE(TODAY(),-3),"mmm-yy") | L24: =TEXT(EDATE(TODAY(),-2),"mmm-yy") | M24: =TEXT(EDATE(TODAY(),-1),"mmm-yy") | N24: =TEXT(EDATE(TODAY(),0),"mmm-yy")
C25: =CUBEVALUE("ThisWorkbookDataModel","[Measures].[Net Profit]","[DIM_Date].[Year].&["&YEAR(EDATE(TODAY(),-11))&"]","[DIM_Date].[Month].&["&MONTH(EDATE(TODAY(),-11))&"]") | D25: =CUBEVALUE("ThisWorkbookDataModel","[Measures].[Net Profit]","[DIM_Date].[Year].&["&YEAR(EDATE(TODAY(),-10))&"]","[DIM_Date].[Month].&["&MONTH(EDATE(TODAY(),-10))&"]") | E25: =CUBEVALUE("ThisWorkbookDataModel","[Measures].[Net Profit]","[DIM_Date].[Year].&["&YEAR(EDATE(TODAY(),-9))&"]","[DIM_Date].[Month].&["&MONTH(EDATE(TODAY(),-9))&"]") | F25: =CUBEVALUE("ThisWorkbookDataModel","[Measures].[Net Profit]","[DIM_Date].[Year].&["&YEAR(EDATE(TODAY(),-8))&"]","[DIM_Date].[Month].&["&MONTH(EDATE(TODAY(),-8))&"]") | G25: =CUBEVALUE("ThisWorkbookDataModel","[Measures].[Net Profit]","[DIM_Date].[Year].&["&YEAR(EDATE(TODAY(),-7))&"]","[DIM_Date].[Month].&["&MONTH(EDATE(TODAY(),-7))&"]") | H25: =CUBEVALUE("ThisWorkbookDataModel","[Measures].[Net Profit]","[DIM_Date].[Year].&["&YEAR(EDATE(TODAY(),-6))&"]","[DIM_Date].[Month].&["&MONTH(EDATE(TODAY(),-6))&"]") | I25: =CUBEVALUE("ThisWorkbookDataModel","[Measures].[Net Profit]","[DIM_Date].[Year].&["&YEAR(EDATE(TODAY(),-5))&"]","[DIM_Date].[Month].&["&MONTH(EDATE(TODAY(),-5))&"]") | J25: =CUBEVALUE("ThisWorkbookDataModel","[Measures].[Net Profit]","[DIM_Date].[Year].&["&YEAR(EDATE(TODAY(),-4))&"]","[DIM_Date].[Month].&["&MONTH(EDATE(TODAY(),-4))&"]") | K25: =CUBEVALUE("ThisWorkbookDataModel","[Measures].[Net Profit]","[DIM_Date].[Year].&["&YEAR(EDATE(TODAY(),-3))&"]","[DIM_Date].[Month].&["&MONTH(EDATE(TODAY(),-3))&"]") | L25: =CUBEVALUE("ThisWorkbookDataModel","[Measures].[Net Profit]","[DIM_Date].[Year].&["&YEAR(EDATE(TODAY(),-2))&"]","[DIM_Date].[Month].&["&MONTH(EDATE(TODAY(),-2))&"]") | M25: =CUBEVALUE("ThisWorkbookDataModel","[Measures].[Net Profit]","[DIM_Date].[Year].&["&YEAR(EDATE(TODAY(),-1))&"]","[DIM_Date].[Month].&["&MONTH(EDATE(TODAY(),-1))&"]") | N25: =CUBEVALUE("ThisWorkbookDataModel","[Measures].[Net Profit]","[DIM_Date].[Year].&["&YEAR(EDATE(TODAY(),0))&"]","[DIM_Date].[Month].&["&MONTH(EDATE(TODAY(),0))&"]")
B27: Inventory — trailing 12 months
C28: =TEXT(EDATE(TODAY(),-11),"mmm-yy") | D28: =TEXT(EDATE(TODAY(),-10),"mmm-yy") | E28: =TEXT(EDATE(TODAY(),-9),"mmm-yy") | F28: =TEXT(EDATE(TODAY(),-8),"mmm-yy") | G28: =TEXT(EDATE(TODAY(),-7),"mmm-yy") | H28: =TEXT(EDATE(TODAY(),-6),"mmm-yy") | I28: =TEXT(EDATE(TODAY(),-5),"mmm-yy") | J28: =TEXT(EDATE(TODAY(),-4),"mmm-yy") | K28: =TEXT(EDATE(TODAY(),-3),"mmm-yy") | L28: =TEXT(EDATE(TODAY(),-2),"mmm-yy") | M28: =TEXT(EDATE(TODAY(),-1),"mmm-yy") | N28: =TEXT(EDATE(TODAY(),0),"mmm-yy")
C29: =CUBEVALUE("ThisWorkbookDataModel","[Measures].[Inventory Value]","[DIM_Date].[Year].&["&YEAR(EDATE(TODAY(),-11))&"]","[DIM_Date].[Month].&["&MONTH(EDATE(TODAY(),-11))&"]") | D29: =CUBEVALUE("ThisWorkbookDataModel","[Measures].[Inventory Value]","[DIM_Date].[Year].&["&YEAR(EDATE(TODAY(),-10))&"]","[DIM_Date].[Month].&["&MONTH(EDATE(TODAY(),-10))&"]") | E29: =CUBEVALUE("ThisWorkbookDataModel","[Measures].[Inventory Value]","[DIM_Date].[Year].&["&YEAR(EDATE(TODAY(),-9))&"]","[DIM_Date].[Month].&["&MONTH(EDATE(TODAY(),-9))&"]") | F29: =CUBEVALUE("ThisWorkbookDataModel","[Measures].[Inventory Value]","[DIM_Date].[Year].&["&YEAR(EDATE(TODAY(),-8))&"]","[DIM_Date].[Month].&["&MONTH(EDATE(TODAY(),-8))&"]") | G29: =CUBEVALUE("ThisWorkbookDataModel","[Measures].[Inventory Value]","[DIM_Date].[Year].&["&YEAR(EDATE(TODAY(),-7))&"]","[DIM_Date].[Month].&["&MONTH(EDATE(TODAY(),-7))&"]") | H29: =CUBEVALUE("ThisWorkbookDataModel","[Measures].[Inventory Value]","[DIM_Date].[Year].&["&YEAR(EDATE(TODAY(),-6))&"]","[DIM_Date].[Month].&["&MONTH(EDATE(TODAY(),-6))&"]") | I29: =CUBEVALUE("ThisWorkbookDataModel","[Measures].[Inventory Value]","[DIM_Date].[Year].&["&YEAR(EDATE(TODAY(),-5))&"]","[DIM_Date].[Month].&["&MONTH(EDATE(TODAY(),-5))&"]") | J29: =CUBEVALUE("ThisWorkbookDataModel","[Measures].[Inventory Value]","[DIM_Date].[Year].&["&YEAR(EDATE(TODAY(),-4))&"]","[DIM_Date].[Month].&["&MONTH(EDATE(TODAY(),-4))&"]") | K29: =CUBEVALUE("ThisWorkbookDataModel","[Measures].[Inventory Value]","[DIM_Date].[Year].&["&YEAR(EDATE(TODAY(),-3))&"]","[DIM_Date].[Month].&["&MONTH(EDATE(TODAY(),-3))&"]") | L29: =CUBEVALUE("ThisWorkbookDataModel","[Measures].[Inventory Value]","[DIM_Date].[Year].&["&YEAR(EDATE(TODAY(),-2))&"]","[DIM_Date].[Month].&["&MONTH(EDATE(TODAY(),-2))&"]") | M29: =CUBEVALUE("ThisWorkbookDataModel","[Measures].[Inventory Value]","[DIM_Date].[Year].&["&YEAR(EDATE(TODAY(),-1))&"]","[DIM_Date].[Month].&["&MONTH(EDATE(TODAY(),-1))&"]") | N29: =CUBEVALUE("ThisWorkbookDataModel","[Measures].[Inventory Value]","[DIM_Date].[Year].&["&YEAR(EDATE(TODAY(),0))&"]","[DIM_Date].[Month].&["&MONTH(EDATE(TODAY(),0))&"]")
B31: Cash — trailing 12 months
C32: =TEXT(EDATE(TODAY(),-11),"mmm-yy") | D32: =TEXT(EDATE(TODAY(),-10),"mmm-yy") | E32: =TEXT(EDATE(TODAY(),-9),"mmm-yy") | F32: =TEXT(EDATE(TODAY(),-8),"mmm-yy") | G32: =TEXT(EDATE(TODAY(),-7),"mmm-yy") | H32: =TEXT(EDATE(TODAY(),-6),"mmm-yy") | I32: =TEXT(EDATE(TODAY(),-5),"mmm-yy") | J32: =TEXT(EDATE(TODAY(),-4),"mmm-yy") | K32: =TEXT(EDATE(TODAY(),-3),"mmm-yy") | L32: =TEXT(EDATE(TODAY(),-2),"mmm-yy") | M32: =TEXT(EDATE(TODAY(),-1),"mmm-yy") | N32: =TEXT(EDATE(TODAY(),0),"mmm-yy")
C33: =CUBEVALUE("ThisWorkbookDataModel","[Measures].[Cash Position (Direct, Cumulative)]","[DIM_Date].[Year].&["&YEAR(EDATE(TODAY(),-11))&"]","[DIM_Date].[Month].&["&MONTH(EDATE(TODAY(),-11))&"]") | D33: =CUBEVALUE("ThisWorkbookDataModel","[Measures].[Cash Position (Direct, Cumulative)]","[DIM_Date].[Year].&["&YEAR(EDATE(TODAY(),-10))&"]","[DIM_Date].[Month].&["&MONTH(EDATE(TODAY(),-10))&"]") | E33: =CUBEVALUE("ThisWorkbookDataModel","[Measures].[Cash Position (Direct, Cumulative)]","[DIM_Date].[Year].&["&YEAR(EDATE(TODAY(),-9))&"]","[DIM_Date].[Month].&["&MONTH(EDATE(TODAY(),-9))&"]") | F33: =CUBEVALUE("ThisWorkbookDataModel","[Measures].[Cash Position (Direct, Cumulative)]","[DIM_Date].[Year].&["&YEAR(EDATE(TODAY(),-8))&"]","[DIM_Date].[Month].&["&MONTH(EDATE(TODAY(),-8))&"]") | G33: =CUBEVALUE("ThisWorkbookDataModel","[Measures].[Cash Position (Direct, Cumulative)]","[DIM_Date].[Year].&["&YEAR(EDATE(TODAY(),-7))&"]","[DIM_Date].[Month].&["&MONTH(EDATE(TODAY(),-7))&"]") | H33: =CUBEVALUE("ThisWorkbookDataModel","[Measures].[Cash Position (Direct, Cumulative)]","[DIM_Date].[Year].&["&YEAR(EDATE(TODAY(),-6))&"]","[DIM_Date].[Month].&["&MONTH(EDATE(TODAY(),-6))&"]") | I33: =CUBEVALUE("ThisWorkbookDataModel","[Measures].[Cash Position (Direct, Cumulative)]","[DIM_Date].[Year].&["&YEAR(EDATE(TODAY(),-5))&"]","[DIM_Date].[Month].&["&MONTH(EDATE(TODAY(),-5))&"]") | J33: =CUBEVALUE("ThisWorkbookDataModel","[Measures].[Cash Position (Direct, Cumulative)]","[DIM_Date].[Year].&["&YEAR(EDATE(TODAY(),-4))&"]","[DIM_Date].[Month].&["&MONTH(EDATE(TODAY(),-4))&"]") | K33: =CUBEVALUE("ThisWorkbookDataModel","[Measures].[Cash Position (Direct, Cumulative)]","[DIM_Date].[Year].&["&YEAR(EDATE(TODAY(),-3))&"]","[DIM_Date].[Month].&["&MONTH(EDATE(TODAY(),-3))&"]") | L33: =CUBEVALUE("ThisWorkbookDataModel","[Measures].[Cash Position (Direct, Cumulative)]","[DIM_Date].[Year].&["&YEAR(EDATE(TODAY(),-2))&"]","[DIM_Date].[Month].&["&MONTH(EDATE(TODAY(),-2))&"]") | M33: =CUBEVALUE("ThisWorkbookDataModel","[Measures].[Cash Position (Direct, Cumulative)]","[DIM_Date].[Year].&["&YEAR(EDATE(TODAY(),-1))&"]","[DIM_Date].[Month].&["&MONTH(EDATE(TODAY(),-1))&"]") | N33: =CUBEVALUE("ThisWorkbookDataModel","[Measures].[Cash Position (Direct, Cumulative)]","[DIM_Date].[Year].&["&YEAR(EDATE(TODAY(),0))&"]","[DIM_Date].[Month].&["&MONTH(EDATE(TODAY(),0))&"]")
B36: FORECAST (next period, linear trend)
B37: Sales | C37: Linear Trend (FORECAST.LINEAR) | D37: Next Month | E37: =_xlfn.FORECAST.LINEAR(13,C17:N17,{1,2,3,4,5,6,7,8,9,10,11,12})
B38: Expenses | C38: Linear Trend (FORECAST.LINEAR) | D38: Next Month | E38: =_xlfn.FORECAST.LINEAR(13,C21:N21,{1,2,3,4,5,6,7,8,9,10,11,12})
B39: Profit | C39: Linear Trend (FORECAST.LINEAR) | D39: Next Month | E39: =_xlfn.FORECAST.LINEAR(13,C25:N25,{1,2,3,4,5,6,7,8,9,10,11,12})
B40: Inventory | C40: Linear Trend (FORECAST.LINEAR) | D40: Next Month | E40: =_xlfn.FORECAST.LINEAR(13,C29:N29,{1,2,3,4,5,6,7,8,9,10,11,12})
B41: Cash | C41: Linear Trend (FORECAST.LINEAR) | D41: Next Month | E41: =_xlfn.FORECAST.LINEAR(13,C33:N33,{1,2,3,4,5,6,7,8,9,10,11,12})

Sheet BI_HealthScore
A1: BI_HealthScore
A2: PASSRESS MIS | Home ▸ BI_HealthScore
A3: Sheet Documentation (use the + outline control at left to expand)
A4: Purpose | B4: The single master KPI (0-100, Red/Amber/Green) combining 10 weighted components across growth, profitability, cash, inventory, customers, budget, data quality, and alerts — the one number an executive glances at first.
A5: Input tables | B5: The Data Model (dax/MEASURES.md, PHASE5/6 addenda) via CUBEVALUE; 14_Data_Quality's Overall Data Quality %; BI_Alerts' Status column; tbl_HealthScoreWeights (15_Settings).
A6: Output tables | B6: 02_Partner_Dashboard, 03_CEO_Dashboard, and RPT_ExecutiveBrief all reference this sheet's Total Score cell directly.
A7: Relationships | B7: No Data Model relationship — reads via CUBE functions and direct cell/table references, same mechanism as BI_Insights/BI_Alerts.
A8: Future data source | B8: Already live: resolves for real once the Data Model + measures are wired.
B11: Component | C11: Score (0-100) | D11: Weight | E11: Weighted Contribution
B14: COMPONENT SCORES (formulas — do not edit; change weights on 15_Settings instead)
B15: Revenue Growth | C15: =MIN(100,MAX(0,50+CUBEVALUE("ThisWorkbookDataModel","[Measures].[Revenue Growth % (YoY)]")*250)) | D15: =INDEX(tbl_HealthScoreWeights[Weight],MATCH(B15,tbl_HealthScoreWeights[Component],0)) | E15: =C15*D15
B16: Gross Margin | C16: =MIN(100,MAX(0,IFERROR(CUBEVALUE("ThisWorkbookDataModel","[Measures].[Gross Margin %]")/CUBEVALUE("ThisWorkbookDataModel","[Measures].[Margin Target]")*100,0))) | D16: =INDEX(tbl_HealthScoreWeights[Weight],MATCH(B16,tbl_HealthScoreWeights[Component],0)) | E16: =C16*D16
B17: Cash Position | C17: =MIN(100,MAX(0,IFERROR(CUBEVALUE("ThisWorkbookDataModel","[Measures].[Cash Position (Direct, Cumulative)]")/CUBEVALUE("ThisWorkbookDataModel","[Measures].[Expense Budget (Period)]")*100,0))) | D17: =INDEX(tbl_HealthScoreWeights[Weight],MATCH(B17,tbl_HealthScoreWeights[Component],0)) | E17: =C17*D17
B18: Inventory Health | C18: =MIN(100,MAX(0,IFERROR(CUBEVALUE("ThisWorkbookDataModel","[Measures].[Inventory Turnover]")/CUBEVALUE("ThisWorkbookDataModel","[Measures].[Inventory Turnover Target]")*100,0))) | D18: =INDEX(tbl_HealthScoreWeights[Weight],MATCH(B18,tbl_HealthScoreWeights[Component],0)) | E18: =C18*D18
B19: Customer Growth | C19: =MIN(100,MAX(0,50+CUBEVALUE("ThisWorkbookDataModel","[Measures].[Customer Growth % (YoY)]")*250)) | D19: =INDEX(tbl_HealthScoreWeights[Weight],MATCH(B19,tbl_HealthScoreWeights[Component],0)) | E19: =C19*D19
B20: Repeat Customers | C20: =MIN(100,MAX(0,IFERROR(CUBEVALUE("ThisWorkbookDataModel","[Measures].[Repeat Customer % Actual]")/CUBEVALUE("ThisWorkbookDataModel","[Measures].[Repeat Customer % Target]")*100,0))) | D20: =INDEX(tbl_HealthScoreWeights[Weight],MATCH(B20,tbl_HealthScoreWeights[Component],0)) | E20: =C20*D20
B21: Return Rate | C21: =MIN(100,MAX(0,100-CUBEVALUE("ThisWorkbookDataModel","[Measures].[Return Rate %]")*1000)) | D21: =INDEX(tbl_HealthScoreWeights[Weight],MATCH(B21,tbl_HealthScoreWeights[Component],0)) | E21: =C21*D21
B22: Budget Performance | C22: =MIN(100,MAX(0,100-ABS(IFERROR(CUBEVALUE("ThisWorkbookDataModel","[Measures].[Expense Actual vs Budget]")/CUBEVALUE("ThisWorkbookDataModel","[Measures].[Expense Budget (Period)]"),0))*100)) | D22: =INDEX(tbl_HealthScoreWeights[Weight],MATCH(B22,tbl_HealthScoreWeights[Component],0)) | E22: =C22*D22
B23: Data Quality | C23: =MIN(100,MAX(0,OverallDataQualityPct*100)) | D23: =INDEX(tbl_HealthScoreWeights[Weight],MATCH(B23,tbl_HealthScoreWeights[Component],0)) | E23: =C23*D23
B24: Alerts | C24: =MIN(100,MAX(0,100-COUNTIF('BI_Alerts'!E15:E26,"TRIGGERED*")*(100/12))) | D24: =INDEX(tbl_HealthScoreWeights[Weight],MATCH(B24,tbl_HealthScoreWeights[Component],0)) | E24: =C24*D24
B26: TOTAL BUSINESS HEALTH SCORE | C26: =SUM(E15:E24)/SUM(D15:D24)
B27: Status (Red < 50, Amber 50-75, Green > 75) | C27: =IF(C26>75,"GREEN",IF(C26>=50,"AMBER","RED"))

Sheet RPT_ExecutiveBrief
A1: Daily Executive Brief
A2: PASSRESS MIS | Home ▸ Daily Executive Brief
A3: Sheet Documentation (use the + outline control at left to expand)
A4: Purpose | B4: One-page, auto-summarized snapshot of today's business — printable as-is, no editing or slicers, suitable to hand a partner without walking them through the workbook.
A5: Input tables | B5: The Data Model via CUBEVALUE/CUBESET; BI_HealthScore; BI_Alerts; BI_Insights.
A6: Output tables | B6: A single printable A4 page.
A7: Relationships | B7: Reads the Data Model and the BI_ sheets directly — this page computes nothing new itself.
A8: Future data source | B8: Already live: resolves for real once the Data Model + measures are wired.
B11: REVENUE TODAY | C11: ORDERS TODAY | D11: GROSS PROFIT | E11: MARGIN % | F11: CASH POSITION | G11: INVENTORY VALUE
B12: =CUBEVALUE("ThisWorkbookDataModel","[Measures].[Net Sales]","[DIM_Date].[Year].&["&YEAR(TODAY())&"]","[DIM_Date].[Month].&["&MONTH(TODAY())&"]","[DIM_Date].[Day].&["&DAY(TODAY())&"]") | C12: =CUBEVALUE("ThisWorkbookDataModel","[Measures].[Order Count]","[DIM_Date].[Year].&["&YEAR(TODAY())&"]","[DIM_Date].[Month].&["&MONTH(TODAY())&"]","[DIM_Date].[Day].&["&DAY(TODAY())&"]") | D12: =CUBEVALUE("ThisWorkbookDataModel","[Measures].[Gross Profit]","[DIM_Date].[Year].&["&YEAR(TODAY())&"]","[DIM_Date].[Month].&["&MONTH(TODAY())&"]","[DIM_Date].[Day].&["&DAY(TODAY())&"]") | E12: =CUBEVALUE("ThisWorkbookDataModel","[Measures].[Gross Margin %]","[DIM_Date].[Year].&["&YEAR(TODAY())&"]","[DIM_Date].[Month].&["&MONTH(TODAY())&"]","[DIM_Date].[Day].&["&DAY(TODAY())&"]") | F12: =CUBEVALUE("ThisWorkbookDataModel","[Measures].[Cash Position (Direct, Cumulative)]") | G12: =CUBEVALUE("ThisWorkbookDataModel","[Measures].[Inventory Value]")
B15: Revenue vs Yesterday
B16: =IFERROR(CUBEVALUE("ThisWorkbookDataModel","[Measures].[Net Sales]","[DIM_Date].[Year].&["&YEAR(TODAY())&"]","[DIM_Date].[Month].&["&MONTH(TODAY())&"]","[DIM_Date].[Day].&["&DAY(TODAY())&"]")-CUBEVALUE("ThisWorkbookDataModel","[Measures].[Net Sales]","[DIM_Date].[Year].&["&YEAR(TODAY()-1)&"]","[DIM_Date].[Month].&["&MONTH(TODAY()-1)&"]","[DIM_Date].[Day].&["&DAY(TODAY()-1)&"]"),0) | C16: =IF(B16>=0,"▲ Increase","▼ Decrease")
B18: TOP 5 PRODUCTS | G18: TOP 5 COLLECTIONS
B19: Top 5 Products (Brief) | F19: =CUBESET("ThisWorkbookDataModel","{[DIM_Product].[Title].Children}","Top 5 Products (Brief)","BDESC","[Measures].[Net Sales]") | G19: Top 5 Collections (Brief) | K19: =CUBESET("ThisWorkbookDataModel","{[DIM_Collection].[Title].Children}","Top 5 Collections (Brief)","BDESC","[Measures].[Net Sales]")
B20: =CUBERANKEDMEMBER("ThisWorkbookDataModel",$F$19,1) | D20: =CUBEVALUE("ThisWorkbookDataModel","[Measures].[Net Sales]",CUBERANKEDMEMBER("ThisWorkbookDataModel",$F$19,1)) | G20: =CUBERANKEDMEMBER("ThisWorkbookDataModel",$K$19,1) | I20: =CUBEVALUE("ThisWorkbookDataModel","[Measures].[Net Sales]",CUBERANKEDMEMBER("ThisWorkbookDataModel",$K$19,1))
B21: =CUBERANKEDMEMBER("ThisWorkbookDataModel",$F$19,2) | D21: =CUBEVALUE("ThisWorkbookDataModel","[Measures].[Net Sales]",CUBERANKEDMEMBER("ThisWorkbookDataModel",$F$19,2)) | G21: =CUBERANKEDMEMBER("ThisWorkbookDataModel",$K$19,2) | I21: =CUBEVALUE("ThisWorkbookDataModel","[Measures].[Net Sales]",CUBERANKEDMEMBER("ThisWorkbookDataModel",$K$19,2))
B22: =CUBERANKEDMEMBER("ThisWorkbookDataModel",$F$19,3) | D22: =CUBEVALUE("ThisWorkbookDataModel","[Measures].[Net Sales]",CUBERANKEDMEMBER("ThisWorkbookDataModel",$F$19,3)) | G22: =CUBERANKEDMEMBER("ThisWorkbookDataModel",$K$19,3) | I22: =CUBEVALUE("ThisWorkbookDataModel","[Measures].[Net Sales]",CUBERANKEDMEMBER("ThisWorkbookDataModel",$K$19,3))
B23: =CUBERANKEDMEMBER("ThisWorkbookDataModel",$F$19,4) | D23: =CUBEVALUE("ThisWorkbookDataModel","[Measures].[Net Sales]",CUBERANKEDMEMBER("ThisWorkbookDataModel",$F$19,4)) | G23: =CUBERANKEDMEMBER("ThisWorkbookDataModel",$K$19,4) | I23: =CUBEVALUE("ThisWorkbookDataModel","[Measures].[Net Sales]",CUBERANKEDMEMBER("ThisWorkbookDataModel",$K$19,4))
B24: =CUBERANKEDMEMBER("ThisWorkbookDataModel",$F$19,5) | D24: =CUBEVALUE("ThisWorkbookDataModel","[Measures].[Net Sales]",CUBERANKEDMEMBER("ThisWorkbookDataModel",$F$19,5)) | G24: =CUBERANKEDMEMBER("ThisWorkbookDataModel",$K$19,5) | I24: =CUBEVALUE("ThisWorkbookDataModel","[Measures].[Net Sales]",CUBERANKEDMEMBER("ThisWorkbookDataModel",$K$19,5))
B26: CRITICAL ALERTS
B27: Negative Margin | D27: ='BI_Alerts'!E16
B28: Missing Shopify Sync | D28: ='BI_Alerts'!E24
B30: BUSINESS HEALTH SCORE
B31: =BusinessHealthScore | D31: =BusinessHealthStatus
B33: EXECUTIVE COMMENTARY
B34: ="• "&IFERROR('BI_Insights'!D15,"(resolves once Data Model is wired)")
B35: ="• "&IFERROR('BI_Insights'!D16,"(resolves once Data Model is wired)")
B36: ="• "&IFERROR('BI_Insights'!D19,"(resolves once Data Model is wired)")
B37: ="• "&IFERROR('BI_Insights'!D20,"(resolves once Data Model is wired)")

Sheet RPT_Workflow
A1: RPT_Workflow
A2: PASSRESS MIS | Home ▸ RPT_Workflow
A3: Sheet Documentation (use the + outline control at left to expand)
A4: Purpose | B4: Operational workflow view: purchasing pipeline, order fulfillment status, supplier standing, and cash/expense runway — the day-to-day ops picture, distinct from the financial-statement framing of 08_Finance or the executive framing of the CEO Dashboard.
A5: Input tables | B5: tbl_POHeader/tbl_POLines/tbl_GoodsReceipt (12_Suppliers), tbl_SupplierMaster, RAW_Orders, the Data Model via CUBEVALUE.
A6: Output tables | B6: A single operational dashboard page.
A7: Relationships | B7: No new relationships — reads existing Phase 3 tables and Phase 4/5 measures directly.
A8: Future data source | B8: Already live: resolves for real once Power Query (Phase 2) and the Data Model (Phase 4) are wired.
B11: Metric | C11: Value | D11: Notes
B14: PURCHASING & RECEIVING
B15: Purchase Orders (Total) | C15: =COUNTA(tbl_POHeader[PO Number]) | D15: All POs ever entered, any status.
B16: Open Orders | C16: =COUNTIFS(tbl_RAW_Orders[FulfillmentStatus],"<>FULFILLED") | D16: Shopify orders not yet fully fulfilled.
B17: Pending Receipts | C17: =COUNTIFS(tbl_POHeader[Status],"Approved")+COUNTIFS(tbl_POHeader[Status],"Sent")+COUNTIFS(tbl_POHeader[Status],"Partially Received") | D17: POs Approved, Sent, or Partially Received — not yet fully in hand.
B18: Inventory to Receive (units) | C18: =SUM(tbl_GoodsReceipt[Remaining Quantity]) | D18: Reuses Phase 3's own Remaining Quantity column (12_Suppliers) — not recomputed here.
B19: Monthly Purchasing (this month) | C19: =CUBEVALUE("ThisWorkbookDataModel","[Measures].[Cash Paid for Purchases]") | D19: Current-period Cash Paid for Purchases (dax/MEASURES.md).
B22: SUPPLIER STATUS
B23: Active | C23: =COUNTIFS(tbl_SupplierMaster[Status],"Active")
B24: Inactive | C24: =COUNTIFS(tbl_SupplierMaster[Status],"Inactive")
B25: On Hold | C25: =COUNTIFS(tbl_SupplierMaster[Status],"On Hold")
B28: CASH & EXPENSES
B29: Capital Remaining | C29: =CUBEVALUE("ThisWorkbookDataModel","[Measures].[Cash Position (Direct, Cumulative)]") | D29: Same figure as Cash Position elsewhere — "remaining" is a workflow-page label, not a different calculation.
B30: Outstanding Expenses | C30: =CUBEVALUE("ThisWorkbookDataModel","[Measures].[Accounts Payable (Proxy)]") | D30: Reuses the Balance Sheet's Accounts Payable proxy (dax/MEASURES.md §2) — same documented limitation applies (no payment-status field exists).
B33: MONTHLY PURCHASING — TRAILING 12 MONTHS
B34: Monthly Purchasing
C35: =TEXT(EDATE(TODAY(),-11),"mmm-yy") | D35: =TEXT(EDATE(TODAY(),-10),"mmm-yy") | E35: =TEXT(EDATE(TODAY(),-9),"mmm-yy") | F35: =TEXT(EDATE(TODAY(),-8),"mmm-yy") | G35: =TEXT(EDATE(TODAY(),-7),"mmm-yy") | H35: =TEXT(EDATE(TODAY(),-6),"mmm-yy") | I35: =TEXT(EDATE(TODAY(),-5),"mmm-yy") | J35: =TEXT(EDATE(TODAY(),-4),"mmm-yy") | K35: =TEXT(EDATE(TODAY(),-3),"mmm-yy") | L35: =TEXT(EDATE(TODAY(),-2),"mmm-yy") | M35: =TEXT(EDATE(TODAY(),-1),"mmm-yy") | N35: =TEXT(EDATE(TODAY(),0),"mmm-yy")
C36: =CUBEVALUE("ThisWorkbookDataModel","[Measures].[Cash Paid for Purchases]","[DIM_Date].[Year].&["&YEAR(EDATE(TODAY(),-11))&"]","[DIM_Date].[Month].&["&MONTH(EDATE(TODAY(),-11))&"]") | D36: =CUBEVALUE("ThisWorkbookDataModel","[Measures].[Cash Paid for Purchases]","[DIM_Date].[Year].&["&YEAR(EDATE(TODAY(),-10))&"]","[DIM_Date].[Month].&["&MONTH(EDATE(TODAY(),-10))&"]") | E36: =CUBEVALUE("ThisWorkbookDataModel","[Measures].[Cash Paid for Purchases]","[DIM_Date].[Year].&["&YEAR(EDATE(TODAY(),-9))&"]","[DIM_Date].[Month].&["&MONTH(EDATE(TODAY(),-9))&"]") | F36: =CUBEVALUE("ThisWorkbookDataModel","[Measures].[Cash Paid for Purchases]","[DIM_Date].[Year].&["&YEAR(EDATE(TODAY(),-8))&"]","[DIM_Date].[Month].&["&MONTH(EDATE(TODAY(),-8))&"]") | G36: =CUBEVALUE("ThisWorkbookDataModel","[Measures].[Cash Paid for Purchases]","[DIM_Date].[Year].&["&YEAR(EDATE(TODAY(),-7))&"]","[DIM_Date].[Month].&["&MONTH(EDATE(TODAY(),-7))&"]") | H36: =CUBEVALUE("ThisWorkbookDataModel","[Measures].[Cash Paid for Purchases]","[DIM_Date].[Year].&["&YEAR(EDATE(TODAY(),-6))&"]","[DIM_Date].[Month].&["&MONTH(EDATE(TODAY(),-6))&"]") | I36: =CUBEVALUE("ThisWorkbookDataModel","[Measures].[Cash Paid for Purchases]","[DIM_Date].[Year].&["&YEAR(EDATE(TODAY(),-5))&"]","[DIM_Date].[Month].&["&MONTH(EDATE(TODAY(),-5))&"]") | J36: =CUBEVALUE("ThisWorkbookDataModel","[Measures].[Cash Paid for Purchases]","[DIM_Date].[Year].&["&YEAR(EDATE(TODAY(),-4))&"]","[DIM_Date].[Month].&["&MONTH(EDATE(TODAY(),-4))&"]") | K36: =CUBEVALUE("ThisWorkbookDataModel","[Measures].[Cash Paid for Purchases]","[DIM_Date].[Year].&["&YEAR(EDATE(TODAY(),-3))&"]","[DIM_Date].[Month].&["&MONTH(EDATE(TODAY(),-3))&"]") | L36: =CUBEVALUE("ThisWorkbookDataModel","[Measures].[Cash Paid for Purchases]","[DIM_Date].[Year].&["&YEAR(EDATE(TODAY(),-2))&"]","[DIM_Date].[Month].&["&MONTH(EDATE(TODAY(),-2))&"]") | M36: =CUBEVALUE("ThisWorkbookDataModel","[Measures].[Cash Paid for Purchases]","[DIM_Date].[Year].&["&YEAR(EDATE(TODAY(),-1))&"]","[DIM_Date].[Month].&["&MONTH(EDATE(TODAY(),-1))&"]") | N36: =CUBEVALUE("ThisWorkbookDataModel","[Measures].[Cash Paid for Purchases]","[DIM_Date].[Year].&["&YEAR(EDATE(TODAY(),0))&"]","[DIM_Date].[Month].&["&MONTH(EDATE(TODAY(),0))&"]")
